Workbook

Sheet NL
A1: Planilha das NL
A2: Nº da NL | B2: Data da NL | C2: Histórico da NL | D2: Grupo de Despesa/FONTE
D3: ODC (IU 8) – NBA | E3: ODC (IU 0) – NDA | F3: ODC – NAA | G3: ODC – NAA | H3: INV. (IU 8) – NBA | I3: INV – NAA | J3: INV. - NAA
D4: '1000 / 3008 | E4: 1000 | F4: 1050 | G4: 3050 | H4: 1000 | I4: 1051 | J4: 1050
A5: 2025NL000481 | B5: 45742 | C5: LIM. ORC. (DECRETO N. 12.416, DE 21 DE MARCO DE 2025 ) FTE TESOURO | D5: =K5*D68 -> 38204321 | H5: =K5*H68 -> 2197573.1 | K5: 40401894
A6: 2025NL000593 | B6: 45742 | C6: LIM. ORC. (DECRETO N. 12.416, DE 21 DE MARCO DE 2025 ) FTE TESOURO INVESTIMENTO | D6: =K6*D68 -> 1313343.4 | H6: =K6*H68 -> 75545.593 | K6: 1388889
A7: 2025NL000793 | B7: 45742 | C7: LIM. ORC. (DECRETO N. 12.416, DE 21 DE MARCO DE 2025 ) FTE TESOURO CUSTEIO | E7: 11838003
A8: 2025NL000907 | B8: 45742 | C8: (44)LIM. ORC. (DECRETO N. 12.416, DE 21 DE MARÃ?O DE 2025) - FONTE 1050 | F8: =K8*F68 -> 19303829 | J8: =K8*J68 -> 5154049.7 | K8: 24457878
A9: 2025NL001105 | B9: 45749 | C9: (42)LIM. ORC. (DECRETO N. 12.416, DE 21 DE MARCO DE 2025) - FONTE 1050 | F9: =K9*F68 -> 2002085.6 | J9: =K9*J68 -> 534549.33 | K9: 2536634.9
A10: 2025NL001242 | B10: 45756 | C10: (41)LIM. ORC. (DECRETO N. 12.416, DE 21 DE MARCO DE 2025) - FONTE 1050 | F10: =K10*F68 -> 484702.22 | J10: =K10*J68 -> 129413.67 | K10: 614115.89
A11: 2025NL001363 | B11: 45763 | C11: (38)LIM. ORC. (DECRETO N. 12.416, DE 21 DE MARCO DE 2025) - FONTE 1050 | F11: =K11*F68 -> 1800710.6 | J11: =K11*J68 -> 480782.97 | K11: 2281493.6
A12: 2025NL001477 | B12: 45770 | C12: (41)LIM. ORC. (DECRETO N. 12.416, DE 21 DE MARCO DE 2025) - FONTE 1050 | F12: =K12*F68 -> 1775932.2 | J12: =K12*J68 -> 474167.23 | K12: 2250099.4
A13: 2025NL001577 | B13: 45771 | C13: LIM. ORC. (DECRETO N. 12.416, DE 12 DE MARCO DE 2025 ) FTE TESOURO CUSTEIO - ASSIST. ESTUDANTIL | E13: 5878207
A14: 2025NL001777 | B14: 45777 | C14: (42)LIM. ORC. (DECRETO N. 12.416, DE 21 DE MARCO DE 2025) - FONTE 1050 | F14: =K14*F68 -> 110580.16 | J14: =K14*J68 -> 29524.488 | K14: 140104.65
A15: 2025NL001885 | B15: 45782 | C15: LIM. ORC. (DECRETO N. 12.448, DE 30 DE ABRIL DE 2025 ) FTE TESOURO CUSTEIO | D15: =K15*D68 -> -1406262.3 | H15: =K15*H68 -> -80890.436 | K15: -1487152.8
A16: 2025NL001838 | B16: 45782 | C16: LIM. ORC. (DECRETO N. 12.448, DE 30 DE ABRIL DE 2025 ) FTE TESOURO CUSTEIO | E16: -12702583
A17: 2025NL002085 | B17: 45784 | C17: (42)LIM. ORC. (DECRETO N. 12.448, DE 30 DE ABRIL DE 2025) - FONTE 1050 | F17: =K17*F68 -> 1468712.6 | J17: =K17*J68 -> 392140.74 | K17: 1860853.3
A18: 2025NL002461 | B18: 45791 | C18: (41)LIM. ORC. (DECRETO NÂº 12.448, DE 30 DE ABRIL DE 2025) - FONTE 1050 | F18: =K18*$F$68 -> 499518.13 | J18: =K18*$J$68 -> 133369.46 | K18: 632887.59
A19: 2025NL002631 | B19: 21Mai25 | C19: (42)LIM. ORC. (DECRETO NÂº 12.448, DE 30 DE ABRIL DE 2025) - FONTE 1050 | F19: =K19*$F$68 -> 1986592 | J19: =K19*$J$68 -> 530412.6 | K19: 2517004.6
A20: 2025NL002803 | B20: 45805 | C20: (42)LIM. ORC. (DECRETO NÂº 12.448, DE 30 DE ABRIL DE 2025) - FONTE 1050 | F20: =K20*$F$68 -> 86481.859 | J20: =K20*$J$68 -> 23090.331 | K20: 109572.19
A21: 2025NL002300 | B21: 45789 | C21: LIM. ORC. (DECRETO N. 12.448, DE 30 DE ABRIL DE 2025 ) FTE TESOURO CUSTEIO | D21: =K21*$D$68 -> 1406262.3 | H21: =K21*$H$68 -> 80890.436 | K21: 1487152.8
A22: 2025NL002530 | B22: 45792 | C22: LIM. ORC. (DECRETO N. 12.416, DE 21 DE MARCO DE 2025 ) FTE TESOURO AJUSTE DE LIMITE | D22: =K22*$D$68 -> 1891214.4 | H22: =K22*$H$68 -> 108785.65 | K22: 2000000
A23: 2025NL002192 | B23: 45789 | C23: LIM. ORC. (DECRETO N. 12.416, DE 12 DE MARCO DE 2025 ) FTE TESOURO CUSTEIO | E23: 12702583
A24: 2025NL002529 | B24: 45792 | C24: LIM. ORC. (DECRETO N. 12.416, DE 21 DE MARCO DE 2025 ) FTE TESOURO AJUSTE DE LIMITE | E24: -2000000
A25: 2025NL002927 | B25: 45810 | C25: LIM. ORC. (DECRETO N. 12.477, DE 30 DE MAIO DE 2025 ) FTE TESOURO | D25: =K25*D68 -> 40222131 | E25: 4548257 | H25: =K25*H68 -> 2313640.7 | K25: 42535772
A26: 2025NL003177 | B26: 45812 | C26: (42)LIM. ORC. (DECRETO NÂº 12.448, DE 30 DE ABRIL DE 2025) - FONTE 1050 | F26: =K26*F68 -> 1542404.8 | J26: =K26*J68 -> 411816.29 | K26: 1954221.1
A27: 2025NL003387 | B27: 45819 | C27: (42)LIM. ORC. (DECRETO NÂº 12.448, DE 30 DE ABRIL DE 2025) - FONTE 1050 | F27: =K27*F68 -> 436252.9 | J27: =K27*J68 -> 116477.88 | K27: 552730.78
A28: 2025NL003781 | B28: 45835 | C28: LIM. ORC. (DECRETO N. 12.477, DE 30 DE MAIO DE 2025 ) FTE TESOURO | D28: =K28*D68 -> 13605168 | H28: =K28*H68 -> 782590.83 | K28: 14387759
A29: 2025NL004001 | B29: 45835 | C29: LIM. ORC. (DECRETO N. 12.477, DE 30 DE MAIO DE 2025 ) FTE TESOURO RECOMP PLOA | D29: =K29 -> 20516.42 | H29: =K29*H68 -> 1115.946 | K29: 20516.42
A30: 2025NL003537 | B30: 45826 | C30: (42)LIM. ORC. (DECRETO NÂº 12.448, DE 30 DE ABRIL DE 2025) - FONTE 1050 | F30: =K30*F68 -> 1824550.4 | J30: =K30*J68 -> 487148.1 | K30: 2311698.5
A31: 2025NL003665 | B31: 45833 | C31: (41)LIM. ORC. (DECRETO NÂº 12.448, DE 30 DE ABRIL DE 2025) - FONTE 1050 | F31: =K31*F68 -> 465734.75 | J31: =K31*J68 -> 124349.43 | K31: 590084.18
A32: 2025NL003892 | B32: 45835 | C32: (41)LIM. ORC. (DECRETO NÂº 12.448, DE 30 DE ABRIL DE 2025) - FONTE 1050 | E32: 3377411.2
A33: 2025NL004421 | B33: 45840 | C33: (41)LIM. ORC. (DECRETO NÂº 12.448, DE 30 DE ABRIL DE 2025) - FONTE 1050 | F33: =K33*F68 -> 1981561.9 | J33: =K33*J68 -> 529069.59 | K33: 2510631.5
A34: 2025NL004320 | B34: 45840 | C34: (100)LIM. ORC. (DECRETO NÂº 12.448, DE 30 DE ABRIL DE 2025) - FONTE 1051 | I34: 538270
A35: 2025NL004421 | B35: 45847 | C35: (41)LIM. ORC. (DECRETO NÂº 12.448, DE 30 DE ABRIL DE 2025) - FONTE 1050 | F35: =K35*F68 -> 518392.8 | J35: =K35*J68 -> 138408.93 | K35: 656801.73
A36: 2025NL004564 | B36: 45854 | C36: (41)LIM. ORC. (DECRETO N. 12.448, DE 30 DE ABRIL DE 2025) - FONTE 1050 | F36: =K36*F68 -> 1378671.5 | J36: =K36*J68 -> 368100.12 | K36: 1746771.7
A37: 2025NL004734 | B37: 45861 | C37: (43)LIM. ORC. (DECRETO N. 12.448, DE 30 DE ABRIL DE 2025) - FONTE 1050 | F37: =K37*F68 -> 476910.78 | J37: =K37*J68 -> 127333.39 | K37: 604244.17
A38: 2025NL005346 | B38: 45868 | C38: (41)LIM. ORC. (DECRETO N. 12.448, DE 30 DE ABRIL DE 2025) - FONTE 1050 | F38: =K38*F68 -> 311352.34 | J38: =K38*J68 -> 83129.904 | K38: 394482.24
A39: 2025NL005553 | B39: 45869 | C39: LIM. ORC. (DECRETO N. 12.566, DE 30 DE JULHO DE 2025 ) FTE TESOURO | D39: =K39*D68 -> 13607940 | H39: =K39*H68 -> 782750.25 | K39: 14390690
A40: 2025NL005444 | B40: 45869 | C40: LIM. ORC. (DECRETO N. 12.566, DE 30 DE JULHO DE 2025 ) FTE TESOURO | E40: 3377411.2
A41: 2025NL005686 | B41: 45873 | C41: LIM. ORC. (DECRETO N. 12.566, DE 30 DE JULHO DE 2025 ) FTE TESOURO | D41: =K41*D68 -> 13607940 | H41: =K41*H68 -> 782750.25 | K41: 14390690
A42: 2025NL005779 | B42: 45873 | C42: LIM. ORC. (DECRETO N. 12.416, DE 12 DE MARCO DE 2025 ) FTE TESOURO | E42: 3377411.2
A43: 2025NL005970 | B43: 45875 | C43: (40)LIM. ORC. (DECRETO N. 12.448, DE 30 DE ABRIL DE 2025) - FONTE 1050 | F43: =K43*F68 -> 1630832.5 | J43: =K43*J68 -> 435426.15 | K43: 2066258.6
A44: 2025NL006130 | B44: 45882 | C44: (38)LIM. ORC. (DECRETO N. 12.416, DE 21 DE MARCO DE 2025) - FONTE 1050 | F44: =K44*F68 -> -1275851.8 | J44: =K44*J68 -> -340647.63 | K44: =-1616499.42 -> -1616499.4
A45: 2025NL006274 | B45: 45889 | C45: (37)LIM. ORC. (DECRETO N. 12.416, DE 21 DE MARCO DE 2025) - FONTE 1050 | F45: =K45*F68 -> 1827483.1 | J45: =K45*J68 -> 487931.11 | K45: 2315414.2
A46: 2025NL006402 | B46: 45896 | C46: (37)LIM. ORC. (DECRETO N. 12.448, DE 30 DE ABRIL DE 2025) - FONTE 1050 | F46: =K46*F68 -> 300780.91 | J46: =K46*J68 -> 80307.373 | K46: 381088.28
A47: 2025NL006528 | B47: 45903 | C47: (37)LIM. ORC. (DECRETO N. 12.448, DE 30 DE ABRIL DE 2025) - FONTE 1050 | F47: =K47*F68 -> 1557809.4 | J47: =K47*J68 -> 415929.26 | K47: 1973738.7
A48: 2025NL006650 | B48: 45910 | C48: (37)LIM. ORC. (DECRETO N. 12.448, DE 30 DE ABRIL DE 2025) - FONTE 1050 | F48: =K48*F68 -> 413768.77 | J48: =K48*J68 -> 110474.71 | K48: 524243.48
A49: 2025NL006770 | B49: 45917 | C49: (36)LIM. ORC. (DECRETO N. 12.448, DE 30 DE ABRIL DE 2025) - FONTE 1050 | F49: =K49*F68 -> 1512488.4 | J49: =J68*K49 -> 403828.71 | K49: 1916317.1
A50: 2025NL007024 | B50: 45931 | C50: (35)LIM. ORC. (DECRETO N. 12.448, DE 30 DE ABRIL DE 2025) - FONTE 1050 | F50: =K50*F68 -> 1414709.8 | J50: =K50*J68 -> 377722.19 | K50: 1792431.9
A51: 2025NL007119 | B51: 45931 | C51: LIM. ORC. (DECRETO N. 12.637, DE 30 DE SETEMBRO DE 2025 ) FTE TESOURO | D51: =K51*D68 -> 27215879 | H51: =K51*H68 -> 1565500.5 | K51: 28781380
A52: 2025NL007231 | B52: 45931 | C52: LIM. ORC. (DECRETO N. 12.637, DE 30 DE SETEMBRO DE 2025 ) FTE TESOURO | E52: =K52 -> 6754822.3 | K52: 6754822.3
A53: 2025NL007370 | B53: 45938 | C53: (31)LIM. ORC. (DECRETO N. 12.448, DE 30 DE ABRIL DE 2025) - FONTE 1050 | F53: =K53*F68 -> 525632.88 | J53: =J68*K53 -> 140342 | K53: 665974.88
A54: 2025NL007533 | B54: 45945 | C54: (32)LIM. ORC. (DECRETO N. 12.448, DE 30 DE ABRIL DE 2025) - FONTE 1050 | F54: =K54*F68 -> 1167618.1 | J54: =K54*J68 -> 311749.66 | K54: 1479367.8
A66: Total | D66: =SUM(D5:D65) -> 1.4968845e+08 | E66: =SUM(E5:E65) -> 37151523 | F66: =SUM(F5:F65) -> 47530248 | G66: =SUM(G5:G65) -> 0 | H66: =SUM(H5:H65) -> 8610252.7 | I66: =SUM(I5:I65) -> 538270 | J66: =SUM(J5:J65) -> 12690398
A67: Contas Contábeis | B67: 723200200 | C67: limite recebido
B68: 823200100 | C68: saldo limite recebido | D68: 0.94560718 | F68: 0.78926832 | H68: 0.054392823 | I68: 1 | J68: 0.21073168
D69: 79130053 | H69: 7196501.5
F72: =H66 -> 8610252.7
F74: 4245723

Sheet UO_26271
B3: UO 26271 - Execução dos Limites Liberados (Decreto nº 12.416 de 21 de março de 2025)
B6: Atualizado: 20/10/2025 | J6: =I6*12 -> 0
B7: TOTAL FONTE TESOURO + PRÓPRIAS | C7: =C9+C28 -> 214628958 | D7: =D9+D28 -> 233958183 | E7: =E9+E28 -> 0 | F7: =F9+F28 -> 2.5742673e+08 | G7: =G9+G28 -> 61976502 | H7: =H9+H28 -> 2.5620914e+08 | I7: =I9+I28 -> 1.897026 | J7: =J9+J28 -> 1.8583912e+08 | K7: =K9+K28 -> 37495264
B8: FONTE TESOURO | C8: DOTAÇÃO INICIAL 2025 (sem emendas) | D8: DOTAÇÃO ATUALIZADA 2025 (sem emendas) | E8: LIMITE RETIDO | F8: LIMITE LIBERADO 2024 | G8: LIBERAÇÃO LIMITE EXTRA | H8: TOTAL LIMITE LIBERADO | I8: % LIMITE LIBERADO (Total Lim. Lib./Dot Inic.) | J8: EMPENHADO | K8: A EMPENHAR | N8: Indicador TCU (Dotação Inicial/Limite recebido)
B9: TOTAL (CUSTEIO+INVESTIMENTO) | C9: =C10+C20 -> 213182043 | D9: =D10+D20 -> 213217214 | E9: =E10+E20 -> 0 | F9: =F10+F20 -> 1.9545023e+08 | G9: =G10+G20 -> 0 | H9: =H10+H20 -> 1.9545023e+08 | I9: =H9/D9 -> 0.9166719 | J9: =J10+J20 -> 1.8583912e+08 | K9: =D9-J9 -> 27378091 | N9: Tesouro | O9: =C7/F7 -> 0.83374775
B10: CUSTEIO | C10: =SUM(C11:C19) -> 198789040 | D10: =SUM(D11:D19) -> 203824211 | E10: =SUM(E11:E17) -> 0 | F10: =F11+F13 -> 1.8683998e+08 | G10: =SUM(G11:G17) -> 0 | H10: =H11+H13 -> 1.8683998e+08 | I10: =H10/D10 -> 0.91667214 | J10: =SUM(J11:J19) -> 1.834836e+08 | K10: =D10-J10 -> 20340614 | N10: Próprios | O10: =C29/H29 -> 0.024026893
B11: Assistência Estudantil – 4002 | C11: =SUM(Z139:Z142) -> 40235215 | D11: =SUM(AA139:AA142) -> 40235215 | E11: 0 | F11: =NL!E66 -> 37151523 | H11: =F11+G11 -> 37151523 | I11: =H11/(D11+D12) -> 0.91666667 | J11: =SUM(AB139:AB142) -> 36791928 | K11: =D11-J11 -> 3443287.1
B12: Anuidades – 00PW e 00UU | C12: =SUM(Z95:Z128) -> 293719 | D12: =SUM(AA95:AA128) -> 293719 | J12: =SUM(AB95:AB128) -> 88886.7 | K12: =D12-J12 -> 204832.3 | L12: =D12/12 -> 24476.583
B13: Funcionamento – 20RK | C13: =SUM(Z132) -> 153807483 | D13: =SUM(AA132) -> 158842654 | E13: 0 | F13: =NL!D66 -> 1.4968845e+08 | H13: =F13+G13 -> 1.4968845e+08 | I13: =H13/SUM(D13:D19) -> 0.9166735 | J13: =SUM(AB132) -> 1.4334438e+08 | K13: =D13-J13 -> 15498276 | L13: =L12*11 -> 269242.42
B14: HVET – 20RK | C14: =SUM(Z135) -> 484811 | D14: =SUM(AA135) -> 484811 | J14: =SUM(AB135) -> 464965.24 | K14: =D14-J14 -> 19845.76 | L14: =L13-J12 -> 180355.72 | M14: =7202095.87-L14 -> 7021740.2
B15: Reestruturação e Modernização – 8282 (Museus) | C15: =SUM(Z144) -> 52100 | D15: =SUM(AA144) -> 52100 | J15: =SUM(AB144) -> 0 | K15: =D15-J15 -> 52100
B16: Fomento – 20GK | C16: =SUM(Z129:Z131) -> 2321331 | D16: =SUM(AA129:AA131) -> 2321331 | J16: =SUM(AB129:AB131) -> 1959831 | K16: =D16-J16 -> 361500
B17: Capacitação – 4572 | C17: =SUM(Z143) -> 1083763 | D17: =SUM(AA143) -> 1083763 | J17: =SUM(AB143) -> 516512.68 | K17: =D17-J17 -> 567250.32
B18: Internacionalização – 21GS | C18: =SUM(Z137:Z138) -> 418416 | D18: =SUM(AA137:AA138) -> 418416 | J18: =SUM(AB137:AB138) -> 317095.81 | K18: =D18-J18 -> 101320.19
B19: Educação à Distância – 21D7 | C19: =SUM(Z136) -> 92202 | D19: =SUM(AA136) -> 92202 | J19: =SUM(AB136) -> 0 | K19: =D19-J19 -> 92202
B20: INVESTIMENTO | C20: =SUM(C21:C22) -> 14393003 | D20: =SUM(D21:D22) -> 9393003 | E20: =SUM(E21:E22) -> 0 | F20: =SUM(F21:F22) -> 8610252.7 | G20: =SUM(G21:G22) -> 0 | H20: =SUM(H21:H22) -> 8610252.7 | I20: =I21 -> 0.91666667 | J20: =SUM(J21:J22) -> 2355526 | K20: =SUM(K21:K22) -> 7037477
B21: Funcionamento – 20RK | C21: =Z90 -> 14393003 | D21: =AA90 -> 9393003 | E21: 0 | F21: =NL!H66 -> 8610252.7 | G21: 0 | H21: =F21+G21 -> 8610252.7 | I21: =H21/SUM(D21:D22) -> 0.91666667 | J21: =SUM(AB90) -> 2355526 | K21: =D21-J21 -> 7037477
B22: Reestruturação – 8282 | C22: 0 | D22: 0 | J22: =SUM(AB94) -> 0 | K22: =D22-J22 -> 0
B27: RECEITA PRÓPRIA - DEPENDE DE ARRECADAÇÃO | C27: DOTAÇÃO INICIAL 2025 (sem emendas) | D27: DOTAÇÃO ATUALIZADA 2025 (sem emendas) | E27: LIMITE RETIDO | F27: ARRECADAÇÃO (1050) | G27: LIMITE AUTORIZADO 2024 | H27: LIMITE LIBERADO 2024 | I27: % LIMITE LIBERADO (Total Lim. Lib./Arrecadação) | J27: EMPENHADO | K27: A EMPENHAR
B28: TOTAL (1050+1051+3050+3051) | C28: =C29+C33+C35 -> 1446915 | D28: =D29+D33+D35 -> 20740969 | E28: =E29+E33+E35 -> 0 | F28: =F29+F33+F35 -> 61976502 | G28: =G29+G33+G35 -> 61976502 | H28: =H29+H33 -> 60758916 | I28: =H28/F28 -> 0.98035407 | J28: =J29+J33 -> 0 | K28: =K29+K33 -> 10117173
B29: TOTAL PRÓPRIOS – fonte 1050 | C29: =SUM(C30:C32) -> 1446915 | D29: =SUM(D30:D32) -> 10655443 | E29: =SUM(E30:E32) -> 0 | F29: =SUM(F30:F32) -> 61438232 | G29: =SUM(G30:G32) -> 61438232 | H29: =SUM(H30:H32) -> 60220646 | I29: =H29/F29 -> 0.98018195 | J29: =SUM(J30:J32) -> 0 | K29: =SUM(K30:K32) -> 10117173
B30: CUSTEIO (fonte 1050) - 20RK | C30: =SUM(Z134) -> 0 | D30: =SUM(AA134) -> 10067173 | E30: 0 | F30: =SUM(Receitas!O5:O18) -> 61438232 | G30: =F30 -> 61438232 | H30: =NL!F66+NL!J66 -> 60220646 | I30: =H30/F30 -> 0.98018195 | J30: =SUM(AB134) -> 0 | K30: =D30-J30 -> 10067173
B31: INVESTIMENTO (fonte 1050) - 20RK | C31: =Z92 -> 1396915 | D31: =AA92 -> 538270 | J31: =AB92 -> 0 | K31: =AC92 -> 0
B32: INVESTIMENTO (fonte 1050) - 8282 | C32: =SUM(Z94) -> 50000 | D32: =SUM(AA94) -> 50000 | J32: =SUM(AB94) -> 0 | K32: =D32-J32 -> 50000
B33: TOTAL PRÓPRIOS – fonte 1051 | C33: =C34 -> 0 | D33: =D34 -> 18353 | E33: =E34 -> 0 | F33: =F34 -> 538270 | G33: =G34 -> 538270 | H33: =H34 -> 538270 | I33: =H33/F33 -> 1 | J33: =J34 -> 0
B34: INVESTIMENTO (fonte 1051) - 20RK | C34: =SUM(Z93) -> 0 | D34: =SUM(AA93) -> 18353 | E34: 0 | F34: =Receitas!O19 -> 538270 | G34: =F34 -> 538270 | H34: =NL!I66 -> 538270 | I34: =H34/F34 -> 1 | J34: =SUM(AB93) -> 0 | K34: =D34-J34 -> 18353
B35: TOTAL PRÓPRIOS – fonte 3050 e 3051 (SUPERÁVIT) | C35: =C36 -> 0 | D35: =D36 -> 10067173 | E35: =E36 -> 0 | F35: =F36 -> 0 | G35: =G36 -> 0 | H35: =H36 -> - | I35: =H35/F35 -> #VALUE! | J35: =J36 -> 0
B36: Custeio (fonte 3050) - 20RK | C36: =Z134 -> 0 | D36: =AA134 -> 10067173 | E36: 0 | F36: =Receitas!O21 -> 0 | G36: =F36 -> 0 | H36: - | I36: =H36/F36 -> #VALUE! | J36: =SUM(AB95) -> 0 | K36: =D36-J36 -> 10067173
B37: Investimento (fonte 3051) - 20RK | C37: =Z93 -> 0 | D37: =AA93 -> 18353 | E37: 0 | F37: =Receitas!O22 -> 0 | G37: =F37 -> 0 | H37: =NL!I69 -> 0 | I37: =H37/F37 -> #DIV/0! | J37: =SUM(AB96) -> 0 | K37: =D37-J37 -> 18353
F39: 58738456
H40: Tesouro (IU 0-4002 e Anuidades) | I40: Tesouro (IU 8)* | J40: Próprios | K40: DRU
G41: Limite Disponível | H41: =H11-SUM(J11:J12) -> 270708.23 | I41: =H13+H20-SUM(J13:J19)-J20 -> 9340397.1 | J41: =H28-J28 -> 60758916 | K41: =8725941.34+2152152.02+16333.73+2745.09+774677.75+254192.52 -> 11926042
G42: Total | H42: =H41+I41+J41 -> 70370021
G43: Conta Limite Orçamentário a Utilizar: 823200100
B46: EMENDAS | C46: DOTAÇÃO INICIAL 2025 | D46: DOTAÇÃO ATUALIZADA 2025 | E46: CRÉDITO BLOQUEADO | F46: LIMITE LIBERADO 2024 | G46: EMPENHADO 2024 | H46: PAGO 2024 | I46: 15071740 | K46: Crédito Livre custeio 1050
B47: TOTAL | C47: =C48+C52 -> 65080888 | D47: =D48+D52 -> 74850888 | E47: =E48+E52 -> 6736334 | F47: =F48+F52 -> 33325419 | G47: =G48+G52 -> 7841555.7 | H47: =H48+H52 -> 1373041 | K47: 8711534.4
B48: CUSTEIO | C48: =SUM(C49:C51) -> 32166888 | D48: =SUM(D49:D51) -> 44606401 | E48: =SUM(E49:E51) -> 2500001 | F48: =SUM(F49:F51) -> 21313692 | G48: =SUM(G49:G51) -> 7328157.5 | H48: =SUM(H49:H51) -> 1373041
B49: RP 2 - Despesa Discricionária - Emenda de Bancada | F49: 0 | K49: Crédito Livre custeio 1000
B50: RP 6 - Discricionária e decorrente de Emenda Individual | C50: =Z146+Z147 -> 1950001 | D50: =AA146+AA147 -> 4220001 | E50: 1 | F50: 1950000 | G50: =AB146+AB147 -> 532712.64 | H50: =AC146+AC147 -> 0 | K50: =44565589.98+9796183.09 -> 54361773
B51: RP 7 - Despesa Discricionária - Emenda de Bancada | C51: =Z150 -> 30216887 | D51: =AA150 -> 40386400 | E51: 2500000 | F51: =15117969+4245723 -> 19363692 | G51: =AB150 -> 6795444.8 | H51: =AC150 -> 1373041
B52: INVESTIMENTO | C52: =SUM(C53:C54) -> 32914000 | D52: =SUM(D53:D54) -> 30244487 | E52: =SUM(E53:E54) -> 4236333 | F52: =SUM(F53:F54) -> 12011727 | G52: =SUM(G53:G54) -> 513398.19 | H52: =SUM(H53:H54) -> 0
B53: RP 6 - Discricionária e decorrente de Emenda Individual | C53: =Z145 -> 50000 | D53: =AA145 -> 50000 | E53: 0 | F53: 50000 | G53: =AB145 -> 0 | H53: =AC145 -> 0
B54: RP 7 - Despesa Discricionária - Emenda de Bancada | C54: =Z148+Z149 -> 32864000 | D54: =AA148+AA149 -> 30194487 | E54: 4236333 | F54: 11961727 | G54: =AB148 -> 513398.19 | H54: =AC148 -> 0
B55: Contas de Bloqueio SOF: 622120105; 622120106; 622120108.
R88: Unidade Orçamentária | S88: Resultado Lei | U88: Grupo Despesa | V88: Ação Governo | W88: Plano Orçamentário | Y88: Item Informação | Z88: DOTACAO INICIAL | AA88: DOTACAO ATUALIZADA | AB88: DESPESAS EMPENHADAS | AC88: DESPESAS PAGAS
Y89: Fonte SOF | Z89: Saldo - Moeda Origem (Conta Contábil) | AA89: Saldo - Moeda Origem (Conta Contábil) | AB89: Saldo - Moeda Origem (Conta Contábil) | AC89: Saldo - Moeda Origem (Conta Contábil)
R90: 26271 | S90: 2 | T90: PRIMARIO DISCRICIONARIO | U90: 4 | V90: 20RK | W90: 0000 | X90: FUNCIONAMENTO DE INSTITUICOES FEDERAIS DE ENSINO SUPERIOR - DESPESAS DIVERSAS | Y90: 1000 | Z90: 14393003 | AA90: 9393003 | AB90: 2355526 | AC90: 700702.76
Y91: 1050 | Z91: 20450001 | AA91: 21308646 | AB91: 6001804.7 | AC91: 1015546.1
Y92: 1051 | Z92: 1396915 | AA92: 538270
Y93: 3051 | AA93: 18353
V94: 8282 | W94: 0000 | X94: REESTRUTURACAO E MODERNIZACAO DAS INSTITUICOES FEDERAIS DE ENSINO SUPERIOR - DESPESAS DIVERSAS | Y94: 1050 | Z94: 50000 | AA94: 50000
U95: 3 | V95: 00PW | W95: 0002 | X95: CONTRIBUICAO A ASSOCIACAO BRASILEIRA DE EDUCACAO INTERNACIONAL (FAUBAI) | Y95: 1000 | Z95: 2796 | AA95: 2900
W96: 0003 | X96: CONTRIBUICAO A ASSOCIACAO GRUPO COIMBRA DE UNIVERSIDADES BRASILEIRAS (GCUB) | Y96: 1000 | Z96: 16700 | AA96: 16700
W97: 0004 | X97: CONTRIBUICAO A ASSOCIACAO DE UNIVERSIDADES EM REDE (UNIREDE) | Y97: 1000 | Z97: 2000 | AA97: 2000
W98: 0007 | X98: CONTRIBUICAO AO FORUM NACIONAL DE PRO-REITORES DE PESQUISA E POS-GRADUACAO (FOPROP) | Y98: 1000 | Z98: 1500 | AA98: 1500
W99: 0008 | X99: CONTRIBUICAO A ASSOCIACAO BRASILEIRA DE EDUCACAO MEDICA (ABEM) | Y99: 1000 | Z99: 6807 | AA99: 11912 | AB99: 6806 | AC99: 6806
W100: 000A | X100: CONTRIBUICAO A ASSOCIACAO NACIONAL DOS DIRIGENTES DAS INSTITUICOES FEDERAIS DE ENSINO SUPERIOR (ANDIFES) | Y100: 1000 | Z100: 100000 | AA100: 58451
W101: 0010 | X101: CONTRIBUICAO A ASSOCIACAO NACIONAL DE POS-GRADUACAO E PESQUISA EM EDUCACAO (ANPED) | Y101: 1000 | Z101: 2800 | AA101: 2800 | AB101: 1149.8 | AC101: 1149.8
W102: 0011 | X102: CONTRIBUICAO A ASSOCIACAO NACIONAL DE POS-GRADUACAO E PESQUISA EM LETRAS E LINGUISTICA (ANPOLL) | Y102: 1000 | Z102: 8000 | AA102: 8000
W103: 0013 | X103: CONTRIBUICAO A ASSOCIACAO NACIONAL DE POS-GRADUACAO E PESQUISA EM CIENCIAS SOCIAIS (ANPOCS) | Y103: 1000 | Z103: 5500 | AA103: 10084 | AB103: 5500
W104: 0014 | X104: CONTRIBUICAO A ASSOCIACAO NACIONAL DE POS-GRADUACAO E PESQUISA EM ADMINISTRACAO (ANPAD) | Y104: 1000 | Z104: 4230 | AA104: 4653 | AB104: 4653 | AC104: 4653
W105: 0017 | X105: CONTRIBUICAO A ASSOCIACAO NACIONAL DE PROGRAMAS DE POS-GRADUACAO EM CIENCIAS CONTABEIS (ANPCONT) | Y105: 1000 | Z105: 4000 | AA105: 4000 | AB105: 4000
W106: 0018 | X106: CONTRIBUICAO A ASSOCIACAO BRASILEIRA DE EDUCACAO EM CIENCIA DA INFORMACAO (ABECIN) | Y106: 1000 | Z106: 774 | AA106: 774
W107: 0028 | X107: CONTRIBUICAO A ASSOCIACAO BRASILEIRA DE EDITORES CIENTIFICOS (ABEC) | Y107: 1000 | Z107: 950 | AA107: 950
W108: 0029 | X108: CONTRIBUICAO A ASSOCIACAO NACIONAL DE PESQUISA E POS-GRADUACAO EM PSICOLOGIA (ANPEPP) | Y108: 1000 | Z108: 8472 | AA108: 8472 | AB108: 3035.8
W109: 0035 | X109: CONTRIBUICAO A ASSOCIACAO NACIONAL DE POS-GRADUACAO EM FILOSOFIA (ANPOF) | Y109: 1000 | Z109: 1500 | AA109: 1500
W110: 0038 | X110: CONTRIBUICAO A ASSOCIACAO BRASILEIRA DE ENSINO DE ARQUITETURA E URBANISMO (ABEA) | Y110: 1000 | Z110: 1800 | AA110: 1800
W111: 0039 | X111: CONTRIBUICAO A ASSOCIACAO NACIONAL DOS CURSOS DE GRADUACAO EM ADMINISTRACAO (ANGRAD) | Y111: 1000 | Z111: 1714 | AA111: 1714
W112: 0040 | X112: CONTRIBUICAO A ASSOCIACAO NACIONAL DE POS-GRADUACAO EM PESQUISA EM GEOGRAFIA (ANPEGE) | Y112: 1000 | Z112: 3500 | AA112: 3500 | AB112: 1150 | AC112: 1150
W113: 0044 | X113: CONTRIBUICAO AO CONSELHO DE REITORES DAS UNIVERSIDADES BRASILEIRAS (CRUB) | Y113: 1000 | Z113: 0 | AA113: 13690 | AB113: 13690 | AC113: 13690
W114: 0046 | X114: CONTRIBUIÇÃO A ASSOCIAÇÃO BRASILEIRA DE TELEVISÃO ABTU | Y114: 1000 | Z114: 0 | AA114: 7415 | AB114: 7414.3 | AC114: 7414.3
W115: 0064 | X115: CONTRIBUIÇÃO A ASSOCIAÇÃO NACIONAL DE PÓS GRADUAÇÃO E PESQUISA EM AMBIENTE E SOCIEDADE ANPPAS | Y115: 1000 | Z115: 0 | AA115: 3200 | AB115: 3200 | AC115: 3200
W116: 0065 | X116: CONTRIBUICAO A ASSOCIACAO NACIONAL DE PESQUISA E POS-GRADUACAO EM CIENCIA DA INFORMACAO (ANCIB) | Y116: 1000 | Z116: 1000 | AA116: 1100
W117: 0067 | X117: CONTRIBUICAO A ASSOCIACAO NACIONAL DE ENSINO E PESQUISA DO CAMPO DE PUBLICAS (ANEPCP) | Y117: 1000 | Z117: 0 | AA117: 600 | AB117: 600
W118: 0085 | X118: CONTRIBUICAO AO FORUM BRASILEIRO DE ENSINO DE CINEMA E AUDIOVISUAL (FORCINE) | Y118: 1000 | Z118: 850 | AA118: 850
W119: 0101 | X119: CONTRIBUICAO A FEDERACAO DO ESPORTE UNIVERSITARIO DO DISTRITO FEDERAL (FESU) | Y119: 1000 | Z119: 8472 | AA119: 14800 | AB119: 7740 | AC119: 7740
V120: 00UU | W120: 0001 | X120: CONTRIBUICAO A AGENCIA UNIVERSITARIA DA FRANCOFONIA (AUF) | Y120: 1000 | Z120: 15600 | AA120: 14375
W121: 0002 | X121: CONTRIBUICAO A ASSOCIACAO DAS UNIVERSIDADES DE LINGUA PORTUGUESA (AULP) | Y121: 1000 | Z121: 9000 | AA121: 10380 | AB121: 9600 | AC121: 9600
W122: 0003 | X122: CONTRIBUICAO A ASSOCIACAO GRUPO DE TORDESILHAS DE UNIVERSIDADES | Y122: 1000 | Z122: 9800 | AA122: 9800
W123: 0005 | X123: CONTRIBUICAO A ASSOCIACAO DE UNIVERSIDADES GRUPO MONTEVIDEO (AUGM) | Y123: 1000 | Z123: 49380 | AA123: 27139
W124: 0024 | X124: CONTRIBUICAO AO CONSELHO LATINO-AMERICANO DE CIENCIAS SOCIAIS (CLACSO) | Y124: 1000 | Z124: 5200 | AA124: 8758 | AB124: 4386.75 | AC124: 4386.75
W125: 0045 | X125: CONTRIBUICAO AO INTERNATIONAL SEISMOLOGICAL CENTRE (ISC) | Y125: 1000 | Z125: 19274 | AA125: 19274
W126: 0051 | X126: CONTRIBUICAO A ASSOCIACAO FORUM DA GESTAO DO ENSINO SUPERIOR NOS PAISES E REGIOES DE LINGUA PORTUGUESA (FORGES) | Y126: 1000 | Z126: 2100 | AA126: 2100
W127: 0052 | X127: CONTRIBUICAO A NETWORK OF INTERNATIONAL BUSINESS SCHOOLS (NIBS) | Y127: 1000 | Z127: 0 | AA127: 5340 | AB127: 4441.05 | AC127: 4441.05
W128: 0054 | X128: CONTRIBUICAO A INTERNATIONAL PUBLIC POLICY ASSOCIATION (IPPA) | Y128: 1000 | Z128: 0 | AA128: 13188 | AB128: 11520 | AC128: 11520
V129: 20GK | W129: 0000 | X129: FOMENTO AS ACOES DE GRADUACAO, POS-GRADUACAO, ENSINO, PESQUISA E EXTENSAO - DESPESAS DIVERSAS | Y129: 1000 | Z129: 1370663 | AA129: 1845997 | AB129: 1484497 | AC129: 545384.5
W130: 0001 | X130: CONCESSAO DE BOLSAS DE PESQUISA, EXTENSAO E MONITORIA AOS ESTUDANTES | Y130: 1000 | Z130: 475334 | AA130: 237667 | AB130: 237667 | AC130: 100800
W131: 000A | X131: FOMENTO A INTEGRACAO DA EXTENSAO AOS CURRICULOS | Y131: 1000 | Z131: 475334 | AA131: 237667 | AB131: 237667 | AC131: 194178.92
V132: 20RK | W132: 0000 | X132: FUNCIONAMENTO DE INSTITUICOES FEDERAIS DE ENSINO SUPERIOR - DESPESAS DIVERSAS | Y132: 1000 | Z132: 153807483 | AA132: 158842654 | AB132: 1.4334438e+08 | AC132: 1.0123485e+08
Y133: 1050 | Z133: 57356817 | AA133: 57356817 | AB133: 37254518 | AC133: 31418780
Y134: 3050 | AA134: 10067173
W135: 0002 | X135: FUNCIONAMENTO DOS HOSPITAIS VETERINARIOS | Y135: 1000 | Z135: 484811 | AA135: 484811 | AB135: 464965.24 | AC135: 330010.65
V136: 21D7 | W136: 0000 | X136: APOIO A EDUCACAO A DISTANCIA | Y136: 1000 | Z136: 92202 | AA136: 92202
V137: 21GS | W137: 0000 | X137: INTERNACIONALIZACAO DA EDUCACAO SUPERIOR - DESPESAS DIVERSAS | Y137: 1000 | Z137: 268498 | AA137: 268498 | AB137: 171177.81 | AC137: 144598.23
W138: 0002 | X138: IDIOMAS SEM FRONTEIRAS | Y138: 1000 | Z138: 149918 | AA138: 149918 | AB138: 145918
V139: 4002 | W139: 0001 | X139: PROGRAMA INCLUIR - ACESSIBILIDADE NA EDUCACAO SUPERIOR | Y139: 1000 | Z139: 576738 | AA139: 576738 | AB139: 576738
W140: 0002 | X140: PNAES - DECRETO N. 7.234/2010 - DESPESAS DIVERSAS | Y140: 1000 | Z140: 15781090 | AA140: 18781090 | AB140: 15781090 | AC140: 9297657.2
W141: 0003 | X141: PNAES - DECRETO N. 7.234/2010 - AUXILIO FINANCEIRO A ESTUDANTE | Y141: 1000 | Z141: 23434100 | AA141: 20767387 | AB141: 20434100 | AC141: 6276577.4
W142: 0004 | X142: PROMISAES - PORTARIA MEC N. 745/2012 - AUXILIO FINANCEIRO A ESTUDANTE ESTRANGEIRO BENEFICIARIO DO PEC-G | Y142: 1000 | Z142: 443287 | AA142: 110000
V143: 4572 | W143: 0000 | X143: CAPACITACAO DE SERVIDORES PUBLICOS FEDERAIS EM PROCESSO DE QUALIFICACAO E REQUALIFICACAO | Y143: 1000 | Z143: 1083763 | AA143: 1083763 | AB143: 516512.68 | AC143: 90715.91
...

Sheet Receitas
A1: Receita Realizada da UnB | T1: 4
A2: =UO_26271!B6 -> Atualizado: 20/10/2025
A3: Unidade Orçamentária | B3: Fonte SOF | C3: Item Informação | E3: RECEITA ORCAMENTARIA (LIQUIDA) | F3: RECEITA ORCAMENTARIA (LIQUIDA) | G3: RECEITA ORCAMENTARIA (LIQUIDA) | H3: RECEITA ORCAMENTARIA (LIQUIDA) | I3: RECEITA ORCAMENTARIA (LIQUIDA) | J3: RECEITA ORCAMENTARIA (LIQUIDA) | K3: RECEITA ORCAMENTARIA (LIQUIDA) | L3: RECEITA ORCAMENTARIA (LIQUIDA) | M3: RECEITA ORCAMENTARIA (LIQUIDA) | N3: RECEITA ORCAMENTARIA (LIQUIDA) | O3: Total | P3: Total receita (fev - jul + set) | Q3: Média | R3: Estimativa de Total anual (média)
C4: Natureza Receita | E4: JAN/2025 | F4: FEV/2025 | G4: MAR/2025 | H4: 45748 | I4: 45778 | J4: 45809 | K4: 45839 | L4: 45870 | M4: 45901 | N4: 45931
A5: 26271 | B5: 1050 | C5: 13110111 | D5: ALUGUEIS E ARRENDAMENTOS-PRINCIPAL | E5: 4507417.2 | F5: 3271619.4 | G5: 3102071.4 | H5: 3610312.1 | I5: 3122817.8 | J5: 3132812.9 | K5: 3128487.3 | L5: 909371.33 | M5: 3089481.3 | N5: 1688906.6 | O5: =SUM(E5:N5) -> 29563297 | P5: =SUM(F5:K5)+M5 -> 22457602 | Q5: =P5/7 -> 3208228.9 | R5: =Q5*12 -> 38498747
C6: 13110112 | D6: ALUGUEIS E ARRENDAMENTOS-MULTAS E JUROS | E6: 6782 | F6: 5590.38 | G6: 5902.78 | H6: 5761.22 | I6: 5487.27 | J6: 6712.04 | K6: 5697.69 | L6: 2383.8 | M6: 7471.07 | N6: 5412.03 | O6: =SUM(E6:N6) -> 57200.28 | P6: =SUM(F6:K6)+M6 -> 42622.45 | Q6: =P6/7 -> 6088.9214 | R6: =Q6*12 -> 73067.057
C7: 13210101 | D7: REMUNERACAO DE DEPOSITOS BANCARIOS-PRINCIPAL | E7: 38997.15 | F7: 42125.58 | G7: 49916.99 | H7: 44316.98 | I7: 43149.15 | J7: 45413.58 | K7: 41943.55 | L7: 48448.51 | M7: 41848.03 | N7: 29728.8 | O7: =SUM(E7:N7) -> 425888.32 | P7: =SUM(F7:K7)+M7 -> 308713.86 | Q7: =P7/7 -> 44101.98 | R7: =Q7*12 -> 529223.76
C8: 13999901 | D8: OUTRAS RECEITAS PATRIMONIAIS-PRINCIPAL | E8: 422068.37 | F8: 292530.28 | G8: 295538.11 | H8: 298167.78 | I8: 305680.45 | J8: 304776.01 | K8: 310888.86 | L8: 53832.58 | M8: 310410.76 | O8: =SUM(E8:N8) -> 2593893.2 | P8: =SUM(F8:K8)+M8 -> 2117992.2 | Q8: =P8/7 -> 302570.32 | R8: =Q8*12 -> 3630843.9
C9: 14110101 | D9: RECEITA AGROPECUARIA-PRINCIPAL | F9: 31053.75 | J9: 31370.15 | K9: 90198.45 | L9: 142943.6 | M9: 45601.8 | N9: 10629.6 | O9: =SUM(E9:N9) -> 351797.35 | P9: =SUM(F9:K9)+M9 -> 198224.15 | Q9: =P9/7 -> 28317.736 | R9: =Q9*12 -> 339812.83
C10: 16110101 | D10: SERV.ADMINISTRAT.E COMERCIAIS GERAIS-PRINC. | E10: 9806918.1 | F10: 1575534.8 | G10: 3115206.4 | H10: 2781284.9 | I10: 1669985.8 | J10: 2277080.9 | K10: 1182395.6 | L10: 1994467.8 | M10: 1150101.1 | N10: 1031764.8 | O10: =SUM(E10:N10) -> 26584740 | P10: =SUM(F10:K10)+M10 -> 13751590 | Q10: =P10/7 -> 1964512.8 | R10: =(Q10*12)+Q24 -> 31416559
C11: 16110102 | D11: SERV.ADMINISTRAT.E COMERCIAIS GERAIS-MUL.JUR. | E11: 17.2 | F11: 458.5 | G11: 258.4 | H11: 452 | I11: 204.5 | J11: 325.59 | K11: 3.6 | L11: 707 | M11: 491.65 | N11: 4.5 | O11: =SUM(E11:N11) -> 2922.94 | P11: =SUM(F11:K11)+M11 -> 2194.24 | Q11: =P11/7 -> 313.46286 | R11: =Q11*12 -> 3761.5543
C12: 16110201 | D12: INSCR.EM CONCURSOS E PROC.SELETIVOS-PRINCIPAL | E12: 20102.4 | F12: 14712.6 | G12: 2142.4 | H12: 100 | I12: 9916 | J12: 9558 | K12: 1450 | L12: 810 | M12: 440 | N12: 2813.6 | O12: =SUM(E12:N12) -> 62045 | P12: =SUM(F12:K12)+M12 -> 38319 | Q12: =P12/7 -> 5474.1429 | R12: =Q12*12 -> 65689.714
C13: 16999901 | D13: OUTROS SERVICOS-PRINCIPAL | E13: 11.7 | F13: 79 | G13: 11.7 | J13: 50 | L13: 531 | O13: =SUM(E13:N13) -> 683.4 | P13: =SUM(F13:K13)+M13 -> 140.7 | Q13: =P13/7 -> 20.1 | R13: =Q13*12 -> 241.2
C14: 19110901 | D14: MULTAS E JUROS PREVISTOS EM CONTRATOS-PRINC. | E14: 341.4 | F14: 9186.01 | G14: 12526.43 | H14: 4963.26 | I14: 11564.11 | J14: 12380.78 | K14: 12745.37 | L14: 11275.47 | M14: 5640.85 | N14: 13590.27 | O14: =SUM(E14:N14) -> 94213.95 | P14: =SUM(F14:K14)+M14 -> 69006.81 | Q14: =P14/7 -> 9858.1157 | R14: =Q14*12 -> 118297.39
C15: 19110902 | D15: MULTAS E JUROS PREVISTOS EM CONTRATOS-MUL.JUR | N15: 9.49 | O15: =SUM(E15:N15) -> 9.49 | P15: =SUM(F15:K15)+M15 -> 0 | Q15: =P15/7 -> 0 | R15: =Q15*12 -> 0
C16: 19220631 | D16: RESTIT.DESP.PRIMARIAS EX.ANTERIORES-PRINC. | J16: 380 | O16: =SUM(E16:N16) -> 380 | P16: =SUM(F16:K16)+M16 -> 380 | Q16: =P16/7 -> 54.285714 | R16: =Q16*12 -> 651.42857
C17: 19229901 | D17: OUTRAS RESTITUICOES-PRINCIPAL | E17: -9846.9 | F17: 73461.32 | G17: 351691.69 | H17: 245089.34 | I17: 152858.12 | J17: 181259.01 | K17: 508211.75 | L17: 52854.8 | M17: 46857.73 | N17: 98663.58 | O17: =SUM(E17:N17) -> 1701100.4 | P17: =SUM(F17:K17)+M17 -> 1559429 | Q17: =P17/7 -> 222775.57 | R17: =Q17*12 -> 2673306.8
C18: 76110201 | D18: INSC.CONCURSOS E PROC.SELETIVOS-PRINC.-INTRA | G18: 60 | O18: =SUM(E18:N18) -> 60 | P18: =SUM(F18:K18)+M18 -> 60 | Q18: =P18/7 -> 8.5714286 | R18: =Q18*12 -> 102.85714
B19: 1051 | C19: 22130101 | D19: ALIENACAO DE BENS MOVEIS E SEMOVENTES-PRINC. | J19: 538270 | N19: 0 | O19: =SUM(E19:N19) -> 538270 | P19: =SUM(F19:K19)+M19 -> 538270 | Q19: =P19/7 -> 76895.714 | R19: =Q19*12 -> 922748.57
A20: Total | E20: =SUM(E5:E19) -> 14792809 | F20: =SUM(F5:F19) -> 5316351.7 | G20: =SUM(G5:G19) -> 6935326.3 | H20: =SUM(H5:H19) -> 6990447.6 | I20: =SUM(I5:I19) -> 5321663.3 | J20: =SUM(J5:J19) -> 6540389 | K20: =SUM(K5:K19) -> 5282022.2 | L20: =SUM(L5:L19) -> 3217625.9 | ... R20: =SUM(R5:R19) -> 78273053
A21: Fonte: Tesouro Gerencial.
A22: Conta Contábil: 899910802
J23: Mês exceto 1051 | K23: =(SUM(E5:K18)/7)*12 -> 86812695
J24: LOA | K24: 77856818 | Q24: =E10-Q10 -> 7842405.3
H25: receitas cebraspe | K25: =K23-K24 -> 8955876.8
H26: 8765876.4
H27: 1174337 | M27: 1149
H28: 2209000.7 | M28: 904
H29: 1913213.7 | M29: 20.7
H30: 1276164.6 | M30: 400
H31: 1188864 | M31: 170
H32: 209635.95 | I32: =SUM(H27:H31)/5 -> 1552316 | M32: =-8279.23 -> -8279.23
H33: previsão 2 semestre | M33: 405
H34: 7655247.2 | M34: 2862
M35: 50
M36: 452
M37: 3144
M38: 220
M39: 1585
M40: 452
M41: 97.2
M42: 79
M43: 1183
M44: 1020
M45: 1732.2
M46: 896
... M86: 100
M87: =SUM(M27:M86) -> 261395.98
