Workbook
Name _xlcn.WorksheetConnection_II.SituaçãoAtualA2AA90: 'Estudo de Crédito'!$A$3:$P$29
Name _xlcn.WorksheetConnection_II.SituaçãoAtualA2AA90: 'Prog 03.06'!$A$3:$F$38
Name _xlcn.WorksheetConnection_II.SituaçãoAtualA2AA90: 'Prog 07.04'!$A$3:$P$25
Name _xlcn.WorksheetConnection_II.SituaçãoAtualA2AA90: 'Prog-08.07'!$A$3:$P$35
Name _xlcn.WorksheetConnection_II.SituaçãoAtualA2AA90: 'Prog-09.10'!$A$3:$F$30
Name _xlcn.WorksheetConnection_II.SituaçãoAtualA2AA90: 'Prog-12.03'!$B$3:$G$18
Name _xlcn.WorksheetConnection_II.SituaçãoAtualA2AA90: 'Prog-16.09'!$A$3:$L$14
Name _xlcn.WorksheetConnection_II.SituaçãoAtualA2AA90: 'Prog-17.03 PRC'!$B$3:$G$6
Name _xlcn.WorksheetConnection_II.SituaçãoAtualA2AA90: 'Prog-18.08'!$A$3:$E$38
Name _xlcn.WorksheetConnection_II.SituaçãoAtualA2AA90: 'Prog-25.02'!$A$3:$P$46
Name _xlcn.WorksheetConnection_II.SituaçãoAtualA2AA90: 'Programação 17.11'!$A$3:$O$35
Name _xlcn.WorksheetConnection_II.SituaçãoAtualA2AA90: 'Variáveis fixas'!$A$1:$L$89
Name _xlcn.WorksheetConnection_II.SituaçãoAtualA2AA90: 'I. Situação Atual'!$A$3:$O$91
Name _xlcn.WorksheetConnection_II.SituaçãoAtualA2AA93: 'Estudo de Crédito'!$A$3:$P$29
Name _xlcn.WorksheetConnection_II.SituaçãoAtualA2AA93: 'Prog 03.06'!$A$3:$F$38
Name _xlcn.WorksheetConnection_II.SituaçãoAtualA2AA93: 'Prog 07.04'!$A$3:$P$25
Name _xlcn.WorksheetConnection_II.SituaçãoAtualA2AA93: 'Prog-08.07'!$A$3:$P$35
Name _xlcn.WorksheetConnection_II.SituaçãoAtualA2AA93: 'Prog-09.10'!$A$3:$F$30
Name _xlcn.WorksheetConnection_II.SituaçãoAtualA2AA93: 'Prog-12.03'!$B$3:$G$18
Name _xlcn.WorksheetConnection_II.SituaçãoAtualA2AA93: 'Prog-16.09'!$A$3:$L$14
Name _xlcn.WorksheetConnection_II.SituaçãoAtualA2AA93: 'Prog-17.03 PRC'!$B$3:$G$6
Name _xlcn.WorksheetConnection_II.SituaçãoAtualA2AA93: 'Prog-18.08'!$A$3:$E$38
Name _xlcn.WorksheetConnection_II.SituaçãoAtualA2AA93: 'Prog-25.02'!$A$3:$P$46
Name _xlcn.WorksheetConnection_II.SituaçãoAtualA2AA93: 'Programação 17.11'!$A$3:$O$35
Name _xlcn.WorksheetConnection_II.SituaçãoAtualA2AA93: 'Variáveis fixas'!$A$1:$L$89
Name _xlcn.WorksheetConnection_II.SituaçãoAtualA2AA93: 'I. Situação Atual'!$A$3:$O$91
Name Área_impressão_IM: [1]FLUXO98!$A$1:$N$68
Name PRINT_AREA_MI: [1]FLUXO98!$A$1:$N$69
Name SegmentaçãodeDados_Classificação: #N/A
Name SegmentaçãodeDados_Classificação1: #N/A
Name SegmentaçãodeDados_Descrição_das_despesas: #N/A
Name SegmentaçãodeDados_Descrição_das_despesas1: #N/A

Sheet I. Situação Atual
A1: Acompanhamento de Contratos* | AA1: continuados | AB1: =AB4+AB5+AB6+AB7+AB10+AB11+AB14+AB17+SUM(AB37:AB48)+AB52+AB55+AB56+AB58+AB81+AB83 -> 6498237.3 | AC1: spi | AE1: ver observação | AH1: =SUM(AB59:AB70) -> 350001.99
A2: Data de Atualização: 10/11/2025 | AB2: =AB7+AB14+AB17+AB37+AB38+AB39+AB41+AB43+AB44+AB45+AB46+AB47+AB48+AB52+AB55+AB56+AB58+AB81+AB83 -> 6487949.3 | AC2: por demanda | AE2: NÃO ANULAR | AH2: =AB10+AB11+AB12+AB18+AB23+AB24+AB25+AB26+AB27+#REF!+AB28+AB29+AB30+AB31+AB36+AB32+AB33+AB53+AB54+AB57+AB77+AB78+AB80+AB86+AB87+AB88+AB89+AB90+AB91 -> #REF!
A3: Descrição das despesas | B3: UGR | C3: PI 2025 | D3: CNPJ | E3: Processo | F3: Vigência | G3: Status do Contrato | H3: Situação da prorrogação | I3: nº Contrato | J3: Valor Contrato Média mensal | K3: Valor Cont Continuado Mensal | L3: Total estimado Anual | M3: Saldo Empenhos 2025 | N3: Saldo de Empenhos RAP | O3: Total RAP + Empenho | P3: 45658 | Q3: 45689 | R3: 45717 | S3: 45748 | T3: 45778 | U3: 45809 | V3: 45839 | W3: 45870 | X3: 45901 | Y3: 45931 | Z3: 45962 | AA3: 45992 | AB3: Total necessário | AC3: Causas Judiciais | AD3: OUT-NOV (2024) | AE3: Saldo passivel de Anulação | AF3: Necessidade de Empenho até Novembro | AG3: Necessidade Janeiro | AH3: =AB74+AB75+AB76 -> 0
A4: - Estagiários UnB (novo PI - estagiários) | B4: DGP/ folha | C4: VGM01N01N2N | J4: 161000 | L4: =J4*12 -> 1932000 | M4: 659623.24 | N4: 20575.19 | O4: =SUM(M4:N4) -> 680198.43 | AB4: =SUM(Y4:AA4) -> 0 | AC4: Energia e água | AD4: =SUM(J4:K4)*2 -> 322000 | AE4: =O4-AD4 -> 358198.43 | AG4: =(SUM(J4:K4)*2)-O4 -> -358198.43 | AH4: =AB8+AB9 -> 0
A5: Estagiários - auxílio transporte | B5: DGP/ folha | C5: VGM01N01N7N | J5: 36375 | M5: 216315.33 | N5: 7160.7 | O5: =SUM(M5:N5) -> 223476.03 | AB5: =SUM(Y5:AA5) -> 0 | AC5: Contratos MPE e Poli | AH5: =AB50+AB49+AB51 -> 5086454.7
A6: Pasep - HUB | B6: HUB | C6: VGM01N01N1N | J6: 49000 | L6: =48891*13.33 -> 651717.03 | M6: 90145.45 | O6: =SUM(M6:N6) -> 90145.45 | AA6: =J6*2-O6 -> 7854.55 | AB6: =SUM(Y6:AA6) -> 7854.55 | AC6: RU | AH6: =AB71 -> 1571668.7
A7: Pasep - UnB | B7: DGP/ folha | C7: VGM01N01N1N | J7: 810000 | L7: =J7*12 -> 9720000 | M7: 1492474.5 | N7: 0 | O7: =SUM(M7:N7) -> 1492474.5 | T7: =810000-556810 -> 253190 | U7: =J7 -> 810000 | V7: =J7 -> 810000 | AA7: =J7*2-O7 -> 127525.53 | AB7: =SUM(Y7:AA7) -> 127525.53 | AD7: =SUM(J7:K7)*2 -> 1620000 | AE7: =O7-AD7 -> -127525.53 | AG7: =(SUM(J7:K7)*2)-O7 -> 127525.53 | AH7: =AB2+AH1+AH2+AH3+AH4+AH5+AH6 -> #REF!
A8: '- Serviços de Energia Elétrica (PRC) – já com CI | C8: VGM01N01I2N | D8: 075522669/000192 | J8: 1361927.6 | L8: =J8*12 -> 16343131 | M8: =45872.52+983974.29 -> 1029846.8 | N8: =5031931.32+4476318.75 -> 9508250.1 | O8: =SUM(M8:N8) -> 10538097 | AB8: =SUM(Y8:AA8) -> 0
A9: - Serviços de Água e Esgoto (PRC) | B9: INFRA | C9: VGM01N01I3N | D9: 82024000137 | J9: 700000 | L9: =J9*12 -> 8400000 | M9: =257146.6+2437295.23 -> 2694441.8 | N9: =249401.4 -> 249401.4 | O9: =SUM(M9:N9) -> 2943843.2 | U9: =J9-354401 -> 345599 | AB9: =SUM(Y9:AA9) -> 0 | AD9: =SUM(J9:K9)*2 -> 1400000 | AE9: =O9-AD9 -> 1543843.2 | AF9: =O9-Y9-Z9 -> 2943843.2 | AG9: =(SUM(J9:K9)*2)-O9 -> -1543843.2
A10: SANEAGO - Água e esgoto UnB Cerrado (corrigir a média) | B10: UnB Cerrado | C10: VGM01N01I3N | D10: 01616929000102 | J10: 333 | L10: =J10*12 -> 3996 | M10: 999 | N10: 1332 | O10: =SUM(M10:N10) -> 2331 | W10: 333 | AB10: =SUM(Y10:AA10) -> 0 | AE10: =O10-AD10 -> 2331
A11: Energia Elétrica UnB Cerrado - CONTRATO CCER - ENEL N. 36/2020 e CELG DISTRIBUIÇÃO S.A - CELG D, Equatorial Goiás Distribuidora de Energia S/A | B11: UnB Cerrado | C11: VGM01N01I2N | D11: 1543032000104 | E11: 23106.044802/2020-09 23106.083937/2023-24 | I11: 36/2020 | J11: 1585.03 | L11: =J11*12 -> 19020.36 | M11: =570.63+124.47 -> 695.1 | N11: 41.48 | O11: =SUM(M11:N11) -> 736.58 | U11: =J11-324 -> 1261.03 | W11: =1585-1230 -> 355 | Z11: =J11-O11 -> 848.45 | AA11: =J11 -> 1585.03 | AB11: =SUM(Y11:AA11) -> 2433.48 | AD11: =SUM(J11:K11)*2 -> 3170.06 | AE11: =O11-AD11 -> -2433.48 | AG11: =(SUM(J11:K11)*2)-O11 -> 2433.48
A12: OI SA recuperação judicial | B12: STI | C12: VGM01N01I4N | D12: 76535764000143 | E12: 23106.012727/2018-94 | F12: 46247 | G12: =IF((F12-TODAY())<0,"EXPIRADO", IF((F12-TODAY())<=60,"EM BREVE","NO PRAZO")) -> NO PRAZO | I12: 515/2021 | J12: 60000 | L12: =J12*12 -> 720000 | M12: 105024.66 | N12: 0 | O12: =SUM(M12:N12) -> 105024.66 | R12: =J12 -> 60000 | S12: =J12 -> 60000 | T12: =J12 -> 60000 | AA12: =J12*2-O12 -> 14975.34 | AB12: =SUM(Y12:AA12) -> 14975.34 | AD12: =SUM(J12:K12)*2 -> 120000 | AE12: =O12-AD12 -> -14975.34 | AF12: =-Y12-Z12 -> 0 | AG12: =(SUM(J12:K12)*2)-O12 -> 14975.34
A13: Novo contrato (serviço de manutenção preventiva programada e corretiva da sala cofre instalada na STI/UnB) | B13: STI | C13: VGM01N01A2N | E13: 23106.020472/2024-81 | H13: Ultimo despacho DPO informa certificação orçamentária apenas, a licitação está correndo em outro SEI. | AB13: =SUM(Y13:AA13) -> 0 | AG13: =(SUM(J13:K13)*2)-O13 -> 0
A14: - Central IT - Suporte TI (Serviços de Manutenção dos Computadores da UnB) | B14: STI | C14: VGM01N01A3N | D14: 07171299000196 | E14: 23106.007549/2018-80 | F14: 45836 | G14: =IF((F14-TODAY())<0,"EXPIRADO", IF((F14-TODAY())<=60,"EM BREVE","NO PRAZO")) -> EXPIRADO | I14: 507/2019 | K14: =L14/12 -> 369702.92 | L14: =4436435.04 -> 4436435 | M14: 0 | N14: 0 | O14: =SUM(M14:N14) -> 0 | R14: =K14-O14 -> 369702.92 | AB14: =SUM(Y14:AA14) -> 0 | AD14: =SUM(J14:K14)*2 -> 739405.84 | AE14: =O14-AD14 -> -739405.84 | AG14: =(SUM(J14:K14)*2)-O14 -> 739405.84
A15: QUALIFICAR - Suporte TI (Serviços de Manutenção dos Computadores da UnB) | B15: STI | C15: VGM01N01A3N | D15: 04.752.792/0001-01 | E15: 23106.016945/2023-65 | F15: 46147 | G15: =IF((F15-TODAY())<0,"EXPIRADO", IF((F15-TODAY())<=60,"EM BREVE","NO PRAZO")) -> NO PRAZO | I15: 512/2025 | K15: =L15/12 -> 182288 | L15: 2187456 | M15: 323045.17 | N15: 0 | O15: =SUM(M15:N15) -> 323045.17 | U15: 182288 | AA15: =K15*2-O15 -> 41530.83 | AB15: =SUM(Y15:AA15) -> 41530.83 | AG15: =(SUM(J15:K15)*2)-O15 -> 41530.83
A16: - Rede Gigacandanga - Convênio FUB/ RNT | B16: STI | C16: VGM01N01K8N | D16: 30814920000104 | E16: 23106.032698/2019-68 23106.108762/2019-99 23106.027099/2024-90 | F16: 47457 | G16: =IF((F16-TODAY())<0,"EXPIRADO", IF((F16-TODAY())<=60,"EM BREVE","NO PRAZO")) -> NO PRAZO | L16: 752926 | N16: 0 | O16: =SUM(M16:N16) -> 0 | AB16: =SUM(Y16:AA16) -> 0 | AD16: =SUM(J16:K16)*2 -> 0 | AF16: -752926 | AG16: =(SUM(J16:K16)*2)-O16 -> 0
A17: -SIG SOFTWARE & CONSULTORIA EM TECNOLOGIA DA I (Serviço de apoio especializado nas atividades necessárias ao suporte negocial, customização e sustentação do Sistemas Institucionais Integrados de Gestão (SIG)) | B17: STI | C17: VGM01N01Q4N | D17: 13.406.686/0001-67 | E17: 23106.125254/2022-71 | F17: 46082 | G17: =IF((F17-TODAY())<0,"EXPIRADO", IF((F17-TODAY())<=60,"EM BREVE","NO PRAZO")) -> NO PRAZO | I17: 505/2024 | J17: =L17/12 -> 236095 | K17: ainda sem histórico de liquidação | L17: 2833140 | M17: 0 | N17: 0 | O17: =SUM(M17:N17) -> 0 | S17: =236037-202037 -> 34000 | Z17: =J17 -> 236095 | AA17: =J17 -> 236095 | AB17: =SUM(Y17:AA17) -> 472190 | AD17: =SUM(J17:K17)*2 -> 472190 | AF17: -99075 | AG17: =(SUM(J17:K17)*2)-O17 -> 472190
A18: Inframérica - Agenciamento de Carga Internacional (conforme demanda) | B18: Contratos DCO | C18: VGM01N01L3N | D18: 15559082000186 | E18: 23106.011.137/2014-11 23106.086385/2019-20 | F18: 45743 | G18: =IF((F18-TODAY())<0,"EXPIRADO", IF((F18-TODAY())<=60,"EM BREVE","NO PRAZO")) -> EXPIRADO | I18: 026/2020 | M18: 0 | N18: 0 | O18: =SUM(M18:N18) -> 0 | AB18: =SUM(Y18:AA18) -> 0 | AD18: =SUM(J18:K18)*2 -> 0 | AE18: =O18-AD18 -> 0
A19: Inframérica - prestação de serviços de armazenagem e capatazia de cargas importadas (conforme demanda) | B19: Contratos DCO | C19: VGM01N01L3N | D19: 15.559.082/0001-86 | E19: 23106.010064/2025-01 | F19: 47682 | G19: =IF((F19-TODAY())<0,"EXPIRADO", IF((F19-TODAY())<=60,"EM BREVE","NO PRAZO")) -> NO PRAZO | I19: 1203/2025 | J19: 4000 | L19: =J19*12 -> 48000 | M19: 42484.67 | O19: =SUM(M19:N19) -> 42484.67 | AB19: =SUM(Y19:AA19) -> 0
A20: Agenciamento de Transportes de Cargas Internacionais WeghLogística (Aéreos e Marítimos) (conforme demanda) não será prorrogado, licitação em andamento | B20: Contratos DCO/ DIMEX | C20: VGM01N01L3N | D20: 65494742000166 | E20: 23106.099324/2016-80 | F20: 45106 | G20: =IF((F20-TODAY())<0,"EXPIRADO", IF((F20-TODAY())<=60,"EM BREVE","NO PRAZO")) -> EXPIRADO | I20: 081/2017 | L20: 225342 | N20: =17567.67 -> 17567.67 | O20: =SUM(M20:N20) -> 17567.67 | AB20: =SUM(Y20:AA20) -> 0
A21: WEGH Assessoria e Logística Internacional Ltda, Agenciamento de Transportes de Cargas Internacionais WeghLogística | B21: Contratos DCO | C21: VGM01N01L3N | D21: 65494742000166 | E21: 23106.019323/2023-99 23106.087339/2024-13 (importação/ressarcimento) | F21: 46221 | G21: =IF((F21-TODAY())<0,"EXPIRADO", IF((F21-TODAY())<=60,"EM BREVE","NO PRAZO")) -> NO PRAZO | I21: 142/2023 | J21: 4000 | L21: =J21*12 -> 48000 | M21: 11897.6 | N21: 102.4 | O21: =SUM(M21:N21) -> 12000 | AB21: =SUM(Y21:AA21) -> 0 | AD21: =SUM(J21:K21)*2 -> 8000
A22: NK LOGISTICA E TRANSPORTES LTDA (serviços de transporte de cargas por via aérea) | B22: Contratos DCO | C22: VGM01N01P2N | D22: 32270711000172 | E22: 23106.068904/2022-73 | F22: 45989 | G22: =IF((F22-TODAY())<0,"EXPIRADO", IF((F22-TODAY())<=60,"EM BREVE","NO PRAZO")) -> EM BREVE | H22: em renovação | I22: 130/2022 | J22: 500 | L22: =J22*12 -> 6000 | N22: 57249.08 | O22: =SUM(M22:N22) -> 57249.08 | AB22: =SUM(Y22:AA22) -> 0
A23: - Seguro de aluno/ estagiário (MBM Seguradora S.A) | B23: Contratos DCO | C23: VGM01N01N7N | D23: 87883807000106 | E23: 23106.085902/2019-43 | F23: 46086 | G23: =IF((F23-TODAY())<0,"EXPIRADO", IF((F23-TODAY())<=60,"EM BREVE","NO PRAZO")) -> NO PRAZO | I23: 024/2020 | J23: 3870 | L23: 48000 | M23: 18060.8 | N23: 0 | O23: =SUM(M23:N23) -> 18060.8 | AB23: =SUM(Y23:AA23) -> 0 | AD23: =SUM(J23:K23)*2 -> 7740
A24: BELFORT GERENCIAMENTO DE RESIDUOS LTDA - empresa especializada nos serviços continuados de coleta, transporte, tratamento e disposição final de resíduos de serviços de saúde (RSS) | B24: Contratos DCA | C24: VGM01N01E4N | D24: 10865146000153 | E24: 23106.065223/2022-53 | F24: 46039 | G24: =IF((F24-TODAY())<0,"EXPIRADO", IF((F24-TODAY())<=60,"EM BREVE","NO PRAZO")) -> EM BREVE | I24: 1204/2023 | J24: 4000 | L24: =J24*12 -> 48000 | M24: 6981.19 | N24: 0 | O24: =SUM(M24:N24) -> 6981.19 | R24: =J24-O24 -> -2981.19 | S24: =J24-1948 -> 2052 | AA24: =J24*2-O24 -> 1018.81 | AB24: =SUM(Y24:AA24) -> 1018.81 | AD24: =SUM(J24:K24)*2 -> 8000 | AE24: =O24-AD24 -> -1018.81
A25: - NORESA NOVO RIO ENERGIA E SERVICOS AMBIENTAIS (empresa especializada na prestação de serviços de coleta, transporte, triagem e destinação final de resíduos sólidos orgânicos) | B25: PRC | C25: VGM01N01E4N | D25: 7044248000101 | E25: 23106.076421/2022-42 | F25: 45824 | G25: =IF((F25-TODAY())<0,"EXPIRADO", IF((F25-TODAY())<=60,"EM BREVE","NO PRAZO")) -> EXPIRADO | H25: DCA 12646146 Não será prorrogado, veirificar se há novo processo | I25: 1213/2023 | J25: 7000 | L25: =J25*12 -> 84000 | M25: 3179.7 | O25: =SUM(M25:N25) -> 3179.7 | R25: =J25 -> 7000 | AB25: =SUM(Y25:AA25) -> 0 | AD25: =SUM(J25:K25)*2 -> 14000 | AF25: =-Z25 -> 0 | AG25: =(SUM(J25:K25)*2)-O25 -> 10820.3
A26: PRIME EXTINTORES EIRELI – ME – recarga de extintores | B26: PRC | C26: VGM01N01I6N | D26: 09.098.197/0001-18 | E26: 23106.101317/2023-84 | F26: 46137 | G26: =IF((F26-TODAY())<0,"EXPIRADO", IF((F26-TODAY())<=60,"EM BREVE","NO PRAZO")) -> NO PRAZO | I26: 618/2024 | J26: 10000 | L26: 187401.54 | M26: 159010.09 | N26: 38595.64 | O26: =SUM(M26:N26) -> 197605.73 | AB26: =SUM(Y26:AA26) -> 0 | AD26: =SUM(J26:K26)*2 -> 20000 | AE26: =O26-AD26 -> 177605.73
A27: - Fornecimento de combustível (Novo fornecer para 2019 - Ticket soluções HDFGT S/A) (NÃO DEVE SER ANULADO) | B27: PRC | C27: VGM01N01I5N | D27: 3506307000157 | E27: 23106.116807/2021-13 | F27: 46270 | G27: =IF((F27-TODAY())<0,"EXPIRADO", IF((F27-TODAY())<=60,"EM BREVE","NO PRAZO")) -> NO PRAZO | I27: 1222/2022 | J27: 80000 | L27: =J27*12 -> 960000 | M27: 435769.35 | N27: 0 | O27: =SUM(M27:N27) -> 435769.35 | W27: =80000-12226 -> 67774 | AB27: =SUM(Y27:AA27) -> 0 | AD27: =SUM(J27:K27)*2 -> 160000 | AF27: =O27-AD27 -> 275769.35
A28: CRUZEIRO CONTROLE DE PRAGAS E DESENTUPIMENTO | B28: PRC | C28: VGM01N01D3N | D28: 22.575.793/0001-00 | E28: 23106.058637/2021-45 | F28: 45980 | G28: =IF((F28-TODAY())<0,"EXPIRADO", IF((F28-TODAY())<=60,"EM BREVE","NO PRAZO")) -> EM BREVE | H28: Em fase de prorrogação | I28: 1222/2024 | J28: =L28/12 -> 65625.02 | L28: 787500.24 | M28: 110567.4 | N28: 0 | O28: =SUM(M28:N28) -> 110567.4 | T28: =J28-O28 -> -44942.38 | U28: =J28-60820 -> 4805.02 | V28: =J28-60820 -> 4805.02 | AA28: =J28 -> 65625.02 | AB28: =SUM(Y28:AA28) -> 65625.02 | AG28: =(SUM(J28:K28)*2)-O28 -> 20682.64
A29: VILELA SERVIÇO DE PAISAGISMO, PARQUES E JARDINS LTDA (jardinagem) | B29: PRC | C29: VGM01N01A5N | D29: 32.751.565/0001-05 | E29: 23106.028705/2019-27 | F29: 46231 | G29: =IF((F29-TODAY())<0,"EXPIRADO", IF((F29-TODAY())<=60,"EM BREVE","NO PRAZO")) -> NO PRAZO | I29: 1217/2023 | J29: 298000 | L29: 3119907.7 | M29: 656695.86 | N29: 0 | O29: =SUM(M29:N29) -> 656695.86 | S29: =291576.42-21573 -> 270003.42 | T29: =J29-O29 -> -358695.86 | U29: =J29 -> 298000 | V29: =J29-271060 -> 26940 | AB29: =SUM(Y29:AA29) -> 0 | AD29: =SUM(J29:K29)*2 -> 596000 | AE29: =O29-AD29 -> 60695.86 | AG29: =(SUM(J29:K29)*2)-O29 -> -60695.86
A30: - TRANSMONICI TRANSPORTE E TURISMO (ônibus rodoviário executivo) | B30: PRC | C30: VGM01N01K1N | D30: 09169349000126 | E30: 23106.000890/2021-18 | F30: 46062 | G30: =IF((F30-TODAY())<0,"EXPIRADO", IF((F30-TODAY())<=60,"EM BREVE","NO PRAZO")) -> NO PRAZO | I30: 604/2022 | J30: 90000 | L30: =J30*12 -> 1080000 | M30: 286227.56 | N30: 0 | O30: =SUM(M30:N30) -> 286227.56 | AB30: =SUM(Y30:AA30) -> 0 | AD30: =SUM(J30:K30)*2 -> 180000 | AG30: =(SUM(J30:K30)*2)-O30 -> -106227.56
A31: Tafa Engenharia (serviços continuados de manutenção preventiva e corretiva de equipamentos e sistemas de ar condicionado, com fornecimento de peças e materiais) | B31: PRC | C31: VGM01N01F1N | D31: 12859652000165 | E31: 23106.056117/2023-60 | F31: 46123 | G31: =IF((F31-TODAY())<0,"EXPIRADO", IF((F31-TODAY())<=60,"EM BREVE","NO PRAZO")) -> NO PRAZO | I31: 616/2024 | K31: 95000 | L31: 1173817 | M31: 193101.91 | N31: 0 | O31: =SUM(M31:N31) -> 193101.91 | S31: =95000-46623 -> 48377 | AB31: =SUM(Y31:AA31) -> 0 | AD31: =SUM(J31:K31)*2 -> 190000 | AF31: -143541.49
A32: - Taxigov (demanda) - VIP service | B32: PRC | C32: VGM01N01A4N | D32: 02605452000122 | E32: 23106.010532/2020-24 | F32: 46094 | G32: =IF((F32-TODAY())<0,"EXPIRADO", IF((F32-TODAY())<=60,"EM BREVE","NO PRAZO")) -> NO PRAZO | I32: 036/2020 | J32: 6000 | L32: =J32*12 -> 72000 | M32: 47621.01 | N32: 0 | O32: =SUM(M32:N32) -> 47621.01 | AB32: =SUM(Y32:AA32) -> 0 | AD32: =SUM(J32:K32)*2 -> 12000 | AF32: -2000
A33: 3P HGM solução visual (serviços de comunicação visual) | B33: PRC | C33: VGM01N01O7N | D33: 34.998.513/0001-55 | E33: 23106.089249/2019-91 | F33: 46224 | G33: =IF((F33-TODAY())<0,"EXPIRADO", IF((F33-TODAY())<=60,"EM BREVE","NO PRAZO")) -> NO PRAZO | I33: 1217/2022 | J33: 500000 | L33: =J33*12 -> 6000000 | M33: 950140.51 | N33: 0 | O33: =SUM(M33:N33) -> 950140.51 | R33: =500000-83593 -> 416407 | S33: =500000-83593 -> 416407 | T33: 500000 | W33: =500000-208156 -> 291844 | AA33: =J33*2-O33 -> 49859.49 | AB33: =SUM(Y33:AA33) -> 49859.49 | AD33: =SUM(J33:K33)*2 -> 1000000 | AE33: =O33-AD33 -> -49859.49 | AG33: =(SUM(J33:K33)*2)-O33 -> 49859.49
A34: NP TECNOLOGIA E GESTAO DE DADOS LTDA - ferramenta de pesquisa e comparação de preços praticados pela Administração Pública | B34: PRC | C34: VGM01N01P6N | D34: 07.797.967/0001-95 | E34: 23106.108257/2021-69 | F34: 46098 | G34: =IF((F34-TODAY())<0,"EXPIRADO", IF((F34-TODAY())<=60,"EM BREVE","NO PRAZO")) -> NO PRAZO | H34: contrato anual | I34: 605/2022 | L34: 11456.99 | M34: 0 | O34: =SUM(M34:N34) -> 0 | AB34: =SUM(Y34:AA34) -> 0
A35: contratação de empresa especializada na prestação de serviços continuados, sem dedicação exclusiva de mão de obra, para realização de serviços de acondicionamento, coleta, transporte, tratamento e disposição final de resíduos químicos perigosos | C35: VGM01N01B8 | E35: 23106.043884/2024-90 | AB35: =SUM(Y35:AA35) -> 0
A36: ARTES GRÁFICA COMÉRCIO E REPRESENTAÇÕES EIRELI (serviços continuados de Designer Gráfico) - foi solicitada prorrogação por 20 meses | B36: Contratos DCA | C36: VGM01N01P4N | D36: 05606994000108 | E36: 23106.148085/2022-47 | F36: 46127 | G36: =IF((F36-TODAY())<0,"EXPIRADO", IF((F36-TODAY())<=60,"EM BREVE","NO PRAZO")) -> NO PRAZO | I36: 147/2022 | K36: =12640.77 -> 12640.77 | L36: =K36*12 -> 151689.24 | M36: 25281.54 | N36: 0 | O36: =SUM(M36:N36) -> 25281.54 | T36: =K36-536 -> 12104.77 | V36: =K36 -> 12640.77 | AB36: =SUM(Y36:AA36) -> 0 | AD36: =SUM(J36:K36)*2 -> 25281.54 | AE36: =O36-AD36 -> 0 | AG36: =(SUM(J36:K36)*2)-O36 -> 0
A37: ELYON BRASIL - ESPLANADA SERVICOS TERCEIRIZADOS EIRELI - serviços continuados de pessoal - coletores de resíduos de serviços de saúde | B37: Contratos DCA | C37: VGM01N01E4N | D37: 01099686000182 | E37: 23106.031888/2020-00 | F37: 46219 | G37: =IF((F37-TODAY())<0,"EXPIRADO", IF((F37-TODAY())<=60,"EM BREVE","NO PRAZO")) -> NO PRAZO | I37: 111/2020 | K37: =L37/12 -> 22669.34 | L37: 272032.08 | M37: 63344.59 | N37: 0 | O37: =SUM(M37:N37) -> 63344.59 | T37: =22669-1831.59 -> 20837.41 | W37: =K37-1000 -> 21669.34 | AB37: =SUM(Y37:AA37) -> 0 | AD37: =SUM(J37:K37)*2 -> 45338.68 | AE37: =O37-AD37 -> 18005.91 | AG37: =(SUM(J37:K37)*2)-O37 -> -18005.91
A38: - ALFA E OMEGA Apoio Técnico EDU | B38: Contratos DCA | C38: VGM01N01D5N | D38: 16650774000106 | E38: 23106.011967/2019-52 | F38: 46131 | G38: =IF((F38-TODAY())<0,"EXPIRADO", IF((F38-TODAY())<=60,"EM BREVE","NO PRAZO")) -> NO PRAZO | I38: 022/2021 | K38: =L38/12 -> 24316.78 | L38: 291801.36 | M38: 52521.99 | N38: 0 | O38: =SUM(M38:N38) -> 52521.99 | R38: 865.66 | S38: =K38-2497 -> 21819.78 | T38: =K38-22360 -> 1956.78 | U38: =K38 -> 24316.78 | AB38: =SUM(Y38:AA38) -> 0 | AD38: =SUM(J38:K38)*2 -> 48633.56 | AE38: =O38-AD38 -> 3888.43 | AG38: =(SUM(J38:K38)*2)-O38 -> -3888.43
A39: RCS Tecnologia LTDA - copeiragem | B39: Contratos DCA | C39: VGM01N01O2N | D39: 8220952000122 | E39: 23106.125355/2019-46 23106.035022/2021-41 | F39: 45929 | G39: =IF((F39-TODAY())<0,"EXPIRADO", IF((F39-TODAY())<=60,"EM BREVE","NO PRAZO")) -> EXPIRADO | H39: Não será renovado | I39: 07/2021 | K39: 131667.49 | L39: =K39*12 -> 1580009.9 | M39: 61444.83 | N39: 0 | O39: =SUM(M39:N39) -> 61444.83 | S39: 131667 | U39: =K39 -> 131667.49 | Z39: =K39-O39 -> 70222.66 | AA39: =K39 -> 131667.49 | AB39: =SUM(Y39:AA39) -> 201890.15 | AD39: =SUM(J39:K39)*2 -> 263334.98 | AE39: =O39-AD39 -> -201890.15 | AG39: =(SUM(J39:K39)*2)-O39 -> 201890.15
A40: OBJETIVA SERVIÇOS TERCEIRIZADOS LTDA - copeiragem | B40: Contratos DCA | C40: VGM01N01O2N | D40: 10.874.523/0001-10 | E40: 23106.030343/2024-00 23106.093628/2025-24 | F40: 46660 | G40: =IF((F40-TODAY())<0,"EXPIRADO", IF((F40-TODAY())<=60,"EM BREVE","NO PRAZO")) -> NO PRAZO | I40: 24/2025 | K40: 155277.21 | L40: =K40*12 -> 1863326.5 | M40: 465831.63 | O40: =SUM(M40:N40) -> 465831.63 | AB40: =SUM(Y40:AA40) -> 0
A41: T&S Engenharia Telemática e Sistemas LTDA - contínuo | B41: Contratos DCA | C41: VGM01N01B7N | D41: 00712411000100 | E41: 23106.034924/2021-60 | F41: 45929 | G41: =IF((F41-TODAY())<0,"EXPIRADO", IF((F41-TODAY())<=60,"EM BREVE","NO PRAZO")) -> EXPIRADO | H41: Não será renovado | I41: 006/2021 | K41: 183316.03 | L41: =K41*12 -> 2199792.4 | M41: 0 | N41: 0 | O41: =SUM(M41:N41) -> 0 | R41: =K41-O41 -> 183316.03 | S41: =K41 -> 183316.03 | AB41: =SUM(Y41:AA41) -> 0 | AD41: =SUM(J41:K41)*2 -> 366632.06 | AE41: =O41-AD41 -> -366632.06 | AG41: =(SUM(J41:K41)*2)-O41 -> 366632.06
A42: OBJETIVA SERVIÇOS TERCEIRIZADOS LTDA - contínuo | B42: Contratos DCA | C42: VGM01N01B7N | D42: 10.874.523/0001-10 | E42: 23106.030343/2024-00 23106.093627/2025-80 | F42: 46660 | G42: =IF((F42-TODAY())<0,"EXPIRADO", IF((F42-TODAY())<=60,"EM BREVE","NO PRAZO")) -> NO PRAZO | I42: 23/2025 | K42: 258893.8 | L42: =K42*12 -> 3106725.6 | M42: 776619.27 | O42: =SUM(M42:N42) -> 776619.27 | AB42: =SUM(Y42:AA42) -> 0
A43: Phoenix Comércio e Serviços de Limpeza LTDA - Almoxarifado e de transporte interno de móveis e materiais | B43: Contratos DCA | C43: VGM01N01F7N | D43: 12978051000171 | E43: 23106.001099/2022-06 | F43: 46267 | G43: =IF((F43-TODAY())<0,"EXPIRADO", IF((F43-TODAY())<=60,"EM BREVE","NO PRAZO")) -> NO PRAZO | I43: 111/2022 | K43: 116248.37 | L43: =K43*12 -> 1394980.4 | M43: 392151.9 | N43: 0 | O43: =SUM(M43:N43) -> 392151.9 | S43: =117871-49371 -> 68500 | T43: =K43-O43 -> -275903.53 | U43: =K43 -> 116248.37 | AB43: =SUM(Y43:AA43) -> 0 | AD43: =SUM(J43:K43)*2 -> 232496.74 | AF43: -212997.86 | AG43: =(SUM(J43:K43)*2)-O43 -> -159655.16
A44: - RCA (Limpeza e Conservação) | B44: Contratos DCA | C44: VGM01N01A7N | D44: 69.207.850/0001-61 | E44: 23106.057738/2021-07 | F44: 46402 | G44: =IF((F44-TODAY())<0,"EXPIRADO", IF((F44-TODAY())<=60,"EM BREVE","NO PRAZO")) -> NO PRAZO | I44: 02/2022 | K44: 1918496.1 | L44: =K44*12 -> 23021953 | M44: 213422.1 | N44: 0 | O44: =SUM(M44:N44) -> 213422.1 | S44: =1882331-116567 -> 1765764 | T44: =1882331-116567 -> 1765764 | U44: =1882331-116567 -> 1765764 | V44: =1882331-116567 -> 1765764 | W44: =1882331-116567 -> 1765764 | X44: =1882331-116567 -> 1765764 | Z44: =K44-O44 -> 1705074 | AA44: =K44 -> 1918496.1 | AB44: =SUM(Y44:AA44) -> 3623570.1 | AD44: =SUM(J44:K44)*2 -> 3836992.2 | AF44: =O44-AD44 -> -3623570.1
A45: Life Defense (Segurança) | B45: Contratos DCA | C45: VGM01N01A8N | D45: 02674687000176 | E45: 23106.016977/2013-99 23106.083943/2018-14 23106.047642/2024-75 | F45: 46097 | G45: =IF((F45-TODAY())<0,"EXPIRADO", IF((F45-TODAY())<=60,"EM BREVE","NO PRAZO")) -> NO PRAZO | I45: 011/2020 | K45: 1617878.6 | L45: =K45*12 -> 19414543 | M45: 3235757.2 | N45: 0 | O45: =SUM(M45:N45) -> 3235757.2 | S45: =K45 -> 1617878.6 | U45: =K45 -> 1617878.6 | AB45: =SUM(Y45:AA45) -> 0 | AD45: =SUM(J45:K45)*2 -> 3235757.2 | AF45: =O45-AD45 -> 0 | AG45: =(SUM(J45:K45)*2)-O45 -> 0
A46: G&E SERVICOS TERCEIRIZADOS LTDA (PORTARIA) | B46: Contratos DCA | C46: VGM01N01A9N | D46: 08744139000151 | E46: 23106.085840/2022-75 23106.005560/2022-91 23106.046596/2024-97 | F46: 46020 | G46: =IF((F46-TODAY())<0,"EXPIRADO", IF((F46-TODAY())<=60,"EM BREVE","NO PRAZO")) -> EM BREVE | I46: 081/2022 | K46: =1412211.24 -> 1412211.2 | L46: =K46*12 -> 16946535 | M46: 1022222.7 | N46: 0 | O46: =SUM(M46:N46) -> 1022222.7 | R46: =K46-N46 -> 1412211.2 | S46: =1238299-555 -> 1237744 | U46: =K46 -> 1412211.2 | Z46: =K46-O46 -> 389988.51 | AA46: =K46 -> 1412211.2 | AB46: =SUM(Y46:AA46) -> 1802199.8 | AD46: =SUM(J46:K46)*2 -> 2824422.5 | AF46: =O46-AD46 -> -1802199.8 | AG46: =(SUM(J46:K46)*2)-O46 -> 1802199.8
A47: G&E SERVICOS TERCEIRIZADOS LTDA - serviços continuados de motorista | B47: Contratos DCA | C47: VGM01N01P5N | D47: 08744139000151 | E47: 23106.038810/2022-70 | F47: 46166 | G47: =IF((F47-TODAY())<0,"EXPIRADO", IF((F47-TODAY())<=60,"EM BREVE","NO PRAZO")) -> NO PRAZO | I47: 001/2023 | K47: 236438.33 | L47: =K47*12 -> 2837260 | M47: 489644.02 | N47: 0 | O47: =SUM(M47:N47) -> 489644.02 | S47: 190000 | U47: =K47-171405 -> 65033.331 | AB47: =SUM(Y47:AA47) -> 0 | AD47: =SUM(J47:K47)*2 -> 472876.66 | AE47: =O47-AD47 -> 16767.358 | AG47: =(SUM(J47:K47)*2)-O47 -> -16767.358
A48: GRIFFO (recepcionista) | B48: Contratos DCA | C48: VGM01N01B3N | D48: 26426650000197 | E48: 23106.127519/2018-99; 23106.069857/2019-80 23106.070409/2023-13 | F48: 46221 | G48: =IF((F48-TODAY())<0,"EXPIRADO", IF((F48-TODAY())<=60,"EM BREVE","NO PRAZO")) -> NO PRAZO | I48: 071/2024 | K48: 163496.8 | L48: =K48*12 -> 1961961.6 | M48: 163496.8 | N48: 0 | O48: =SUM(M48:N48) -> 163496.8 | V48: =K48 -> 163496.8 | W48: =K48 -> 163496.8 | AA48: =K48 -> 163496.8 | AB48: =SUM(Y48:AA48) -> 163496.8 | AD48: =SUM(J48:K48)*2 -> 326993.6 | AE48: =O48-AD48 -> -163496.8 | AG48: =(SUM(J48:K48)*2)-O48 -> 163496.8
A49: MPE ENGENHARIA E SERVICOS S/A (serviços comuns de engenharia, incluindo manutenção, conservação, adaptação, reparação e instalação de infraestruturas prediais e imobiliárias) - (exceto DAC) | B49: Contratos DCA | C49: VGM01N01H3N | D49: 04743858000105 | E49: 23106.149436/2022-37 | F49: 46114 | G49: =IF((F49-TODAY())<0,"EXPIRADO", IF((F49-TODAY())<=60,"EM BREVE","NO PRAZO")) -> NO PRAZO | I49: 1201/2023 | J49: 1600000 | L49: =J49*12 -> 19200000 | M49: 435887.47 | N49: 0 | O49: =SUM(M49:N49) -> 435887.47 | U49: =J49-836351 -> 763649 | V49: =J49-1393762 -> 206238 | W49: =J49-460192 -> 1139808 | Z49: =J49-O49 -> 1164112.5 | AA49: 1998000 | AB49: =SUM(Y49:AA49) -> 3162112.5 | AD49: =SUM(J49:K49)*2 -> 3200000 | AF49: -419070 | AG49: =(SUM(J49:K49)*2)-O49 -> 2764112.5
A50: MPE - Adequação e impermeabilização | B50: Contratos DCA | C50: VGA02N43E3N | D50: 04743858000105 | E50: 23106.149228/2022-38 | F50: 46022 | G50: =IF((F50-TODAY())<0,"EXPIRADO", IF((F50-TODAY())<=60,"EM BREVE","NO PRAZO")) -> EM BREVE | H50: em fase de renovação | I50: 1110/2024 | J50: =L50/12 -> 1924342.1 | L50: =8383552.34+14708553.16 -> 23092106 | M50: 33.64 | O50: =SUM(M50:N50) -> 33.64 | U50: =J50-O50 -> 1924308.5 | W50: =1924342-1832108 -> 92234 | Z50: =J50 -> 1924342.1 | AB50: =SUM(Y50:AA50) -> 1924342.1 | AD50: =SUM(J50:K50)*2 -> 3848684.2 | AF50: =-AB50 -> -1924342.1 | AG50: =(SUM(J50:K50)*2)-O50 -> 3848650.6
A51: POLI ENGENHARIA LTDA (serviços comuns de engenharia, incluindo manutenção, conservação, adaptação, reparação e instalação de infraestruturas prediais e imobiliárias) | B51: Contratos DCA | C51: VGM01N01H3N | D51: 00700518000138 | E51: 23106.117479/2022-53 | F51: 46146 | G51: =IF((F51-TODAY())<0,"EXPIRADO", IF((F51-TODAY())<=60,"EM BREVE","NO PRAZO")) -> NO PRAZO | I51: 1226/2022 | J51: 145000 | L51: =J51*12 -> 1740000 | M51: 297407.39 | O51: =SUM(M51:N51) -> 297407.39 | AB51: =SUM(Y51:AA51) -> 0 | AD51: =SUM(J51:K51)*2 -> 290000 | AE51: =O51-AD51 -> 7407.39
A52: Ágil (Serviços Agropecuários) | B52: Contratos DCA | C52: VGM01N01C5N | D52: 72620735000129 | E52: 23106.076196/2018-68 23106.030688/2022-93 | F52: 46097 | G52: =IF((F52-TODAY())<0,"EXPIRADO", IF((F52-TODAY())<=60,"EM BREVE","NO PRAZO")) -> NO PRAZO | I52: 25/2020 | K52: 484202.15 | L52: =K52*12 -> 5810425.8 | M52: 917231.82 | O52: =SUM(M52:N52) -> 917231.82 | R52: =K52-N52 -> 484202.15 | U52: =K52 -> 484202.15 | AA52: =K52*2-O52 -> 51172.48 | AB52: =SUM(Y52:AA52) -> 51172.48 | AD52: =SUM(J52:K52)*2 -> 968404.3 | AE52: =O52-AD52 -> -51172.48 | AG52: =(SUM(J52:K52)*2)-O52 -> 51172.48
A53: RB GRÁFICA DIGITAL LTDA | B53: Contratos DCA | C53: VGM01N01Q1N | D53: 16.951.665/0001-10 | E53: 23106.041918/2022-40 | F53: 46266 | G53: =IF((F53-TODAY())<0,"EXPIRADO", IF((F53-TODAY())<=60,"EM BREVE","NO PRAZO")) -> NO PRAZO | I53: 104/2023 | J53: 100 | L53: =J53*12 -> 1200 | M53: 7572 | N53: 139 | O53: =SUM(M53:N53) -> 7711 | R53: =J53 -> 100 | AB53: =SUM(Y53:AA53) -> 0 | AD53: =SUM(J53:K53)*2 -> 200 | AG53: =(SUM(J53:K53)*2)-O53 -> -7511
A54: ARTECOR GRÁFICO E EDITORA LTDA | B54: Contratos DCA | C54: VGM01N01Q1N | D54: 38.013.991/0001-10 | E54: 23106.041918/2022-40 | F54: 46266 | G54: =IF((F54-TODAY())<0,"EXPIRADO", IF((F54-TODAY())<=60,"EM BREVE","NO PRAZO")) -> NO PRAZO | I54: 105/2023 | J54: 15000 | L54: =J54*12 -> 180000 | M54: 31000 | N54: 0 | O54: =SUM(M54:N54) -> 31000 | R54: =J54 -> 15000 | AB54: =SUM(Y54:AA54) -> 0 | AD54: =SUM(J54:K54)*2 -> 30000
A55: Contrato de Limpeza - UnB Cerrado (AP PISCINAS EIRELI) | B55: UnB Cerrado | C55: VGM01N01A7N (VGM01N1F2N-PI indevido) | D55: 08475822000130 | E55: 23106.116355/2019-55 | F55: 46254 | G55: =IF((F55-TODAY())<0,"EXPIRADO", IF((F55-TODAY())<=60,"EM BREVE","NO PRAZO")) -> NO PRAZO | I55: 112/2020 | K55: 5954.2 | L55: 63975.84 | M55: 16913.07 | N55: 0 | O55: =SUM(M55:N55) -> 16913.07 | R55: =K55-O55 -> -10958.87 | S55: =K55-4688 -> 1266.2 | U55: =5331-O55 -> -11582.07 | V55: =K55-4396 -> 1558.2 | W55: =K55 -> 5954.2 | AB55: =SUM(Y55:AA55) -> 0 | AD55: =SUM(J55:K55)*2 -> 11908.4 | AF55: -643.35 | AG55: =(SUM(J55:K55)*2)-O55 -> -5004.67
A56: - Segurança - ULTRASEG Segurança Patrimonial Ltda | B56: UnB Cerrado | C56: VGM01N01A8N | D56: 09151154000159 | E56: 23106.020717/2022-17 | F56: 46303 | G56: =IF((F56-TODAY())<0,"EXPIRADO", IF((F56-TODAY())<=60,"EM BREVE","NO PRAZO")) -> NO PRAZO | I56: 1207/2022 | K56: 23452.22 | L56: =K56*12 -> 281426.64 | M56: 1000 | N56: 0 | O56: =SUM(M56:N56) -> 1000 | U56: =K56 -> 23452.22 | Z56: =K56-O56 -> 22452.22 | AA56: =K56 -> 23452.22 | AB56: =SUM(Y56:AA56) -> 45904.44 | AD56: =SUM(J56:K56)*2 -> 46904.44 | AF56: -46904.36 | AG56: =(SUM(J56:K56)*2)-O56 -> 45904.44
A57: Jardinagem - UnB Cerrado - AMBIENTAL DO BRASIL ESTUDOS E PROJETOS AMBIENTAIS LTDA | B57: UnB Cerrado | C57: VGM01N01A5N | D57: 09150575000165 | E57: 23106.092536/2018-06 | F57: 46309 | G57: =IF((F57-TODAY())<0,"EXPIRADO", IF((F57-TODAY())<=60,"EM BREVE","NO PRAZO")) -> NO PRAZO | I57: 659/2020 | J57: =L57/12 -> 4106.25 | L57: 49275 | M57: 7891.86 | N57: 0 | O57: =SUM(M57:N57) -> 7891.86 | AA57: =J57*2-O57 -> 320.64 | AB57: =SUM(Y57:AA57) -> 320.64 | AD57: =SUM(J57:K57)*2 -> 8212.5 | AF57: =-Y57*2 -> 0
A58: Recepcionista – AMR LIMPEZA E LOCACAO DE AUTOMOVEIS LTDA | B58: UnB Cerrado | C58: VGM01N01B3N | D58: 10.258.826/0001-09 | E58: 23106.100112/2023-81 | F58: 46068 | G58: =IF((F58-TODAY())<0,"EXPIRADO", IF((F58-TODAY())<=60,"EM BREVE","NO PRAZO")) -> NO PRAZO | H58: Contrato Encerrado / ver saldo de empenho | I58: 12/2024 | K58: =L58/12 -> 4290.91 | L58: 51490.92 | M58: =30036.37+4537.93 -> 34574.3 | N58: 0 | O58: =SUM(M58:N58) -> 34574.3 | U58: =K58 -> 4290.91 | AB58: =SUM(Y58:AA58) -> 0 | AD58: =SUM(J58:K58)*2 -> 8581.82 | AE58: =O58-AD58 -> 25992.48 | AG58: =(SUM(J58:K58)*2)-O58 -> -25992.48
A59: '- GESTOR SERVICOS EMPRESARIAIS (Portaria - SPI) | B59: Contratos SPI | C59: VGM01N01E8N | D59: 02.685.728/0001-20 | E59: 23106.047067/2021-68 | F59: 46434 | G59: =IF((F59-TODAY())<0,"EXPIRADO", IF((F59-TODAY())<=60,"EM BREVE","NO PRAZO")) -> NO PRAZO | I59: 001/2022 | K59: 382896.8 | L59: =K59*12 -> 4594761.6 | M59: 767128.85 | N59: 0 | O59: =SUM(M59:N59) -> 767128.85 | R59: =K59-O59 -> -384232.05 | U59: =K59-O59 -> -384232.05 | AB59: =SUM(Y59:AA59) -> 0 | AD59: =SUM(J59:K59)*2 -> 765793.6 | AE59: =O59-AD59 -> 1335.25 | AG59: =(SUM(J59:K59)*2)-O59 -> -1335.25
A60: - SEFIX (Limpeza e Conservação - SPI) | B60: Contratos SPI | C60: VGM01N01E9N | D60: 13258899000199 | E60: 23106.047036/2021-15 | F60: 46462 | G60: =IF((F60-TODAY())<0,"EXPIRADO", IF((F60-TODAY())<=60,"EM BREVE","NO PRAZO")) -> NO PRAZO | I60: 033/2022 | K60: 193823.77 | L60: =K60*12 -> 2325885.2 | M60: 388647.54 | N60: 0 | O60: =SUM(M60:N60) -> 388647.54 | S60: =K60 -> 193823.77 | U60: =K60 -> 193823.77 | AB60: =SUM(Y60:AA60) -> 0 | AD60: =SUM(J60:K60)*2 -> 387647.54 | AE60: =O60-AD60 -> 1000 | AG60: =(SUM(J60:K60)*2)-O60 -> -1000
A61: Engemega - (Manutenção de Imóveis gerenciados pela Secretaria de Patrimônio Imobiliário (SPI)) – contrato 1 (contrato antigo) | B61: Contratos SPI | C61: VGM01N01D4N | D61: 33480104/0001-08 | E61: 23106.059077/2021-46 | F61: 46035 | G61: =IF((F61-TODAY())<0,"EXPIRADO", IF((F61-TODAY())<=60,"EM BREVE","NO PRAZO")) -> EM BREVE | I61: 1223/2022 | J61: 309551 | L61: 6773742 | M61: 590994.48 | O61: =SUM(M61:N62) -> 590994.48 | R61: =J61-M61 -> -281443.48 | AA61: =J61*2-O61 -> 28107.52 | AB61: =SUM(Y61:AA61) -> 28107.52 | AD61: =J61*2 -> 619102 | AE61: =O61-AD61 -> -28107.52 | AG61: =(SUM(J61:K61)*2)-O61 -> 28107.52
A62: Engemega - (Manutenção de Imóveis gerenciados pela Secretaria de Patrimônio Imobiliário (SPI)) – contrato 2 (novo contrato) | B62: Contratos SPI | C62: VGM01N01D4N | D62: 33480104/0001-08 | E62: 23106.066341/2023-60 | F62: 46079 | G62: =IF((F62-TODAY())<0,"EXPIRADO", IF((F62-TODAY())<=60,"EM BREVE","NO PRAZO")) -> NO PRAZO | I62: 1206/2024 | L62: 5164500 | M62: 0 | AB62: =SUM(Y62:AA62) -> 0 | AG62: =(SUM(J62:K62)*2)-O62 -> 0
A63: FORMIGA ENGENHARIA E ARQUITETURA LTDA, especializada na prestação de serviços continuados, sem dedicação exclusiva de mão de obra, para realização de vistorias de entrada e saída nos imóveis de propriedade da Universidade de Brasília | B63: Contratos SPI | C63: VGM01N01D2N | D63: 22.352.353/0001-93 | E63: 23106.013588/2024-64 | F63: 46340 | G63: =IF((F63-TODAY())<0,"EXPIRADO", IF((F63-TODAY())<=60,"EM BREVE","NO PRAZO")) -> NO PRAZO | I63: 93/2024 | J63: =L63/12 -> 7018 | L63: 84216 | M63: 4754 | N63: 726 | O63: =SUM(M63:N63) -> 5480 | Z63: =J63-O63 -> 1538 | AA63: =J63 -> 7018 | AB63: =SUM(Y63:AA63) -> 8556 | AG63: =(SUM(J63:K63)*2)-O63 -> 8556
A64: QUANTUM SOLUÇÕES E INOVAÇÕES LTDA - emissão de laudos técnicos de avaliação de valores imobiliários | B64: Contratos SPI | C64: VGM01N01Q7N | D64: 43.946.228/0001-81 | E64: 23106.019008/2024-42 | F64: 46331 | G64: =IF((F64-TODAY())<0,"EXPIRADO", IF((F64-TODAY())<=60,"EM BREVE","NO PRAZO")) -> NO PRAZO | I64: 1221/2024 | J64: =L64/12 -> 1241.6667 | L64: 14900 | M64: 3725 | N64: 0 | O64: =SUM(M64:N64) -> 3725 | AB64: =SUM(Y64:AA64) -> 0
A65: SILVA EDIFICAÇÕES LTDA - emissão de laudos técnicos de avaliação de valores imobiliários | B65: Contratos SPI | C65: VGM01N01Q7N | D65: 44.532.592/0001-68 | E65: 23106.103034/2024-58 | F65: 46327 | G65: =IF((F65-TODAY())<0,"EXPIRADO", IF((F65-TODAY())<=60,"EM BREVE","NO PRAZO")) -> NO PRAZO | I65: 1220/2024 | J65: =L65/12 -> 832.5 | L65: 9990 | M65: 1638 | N65: 0 | O65: =SUM(M65:N65) -> 1638 | R65: =J65-O65 -> -805.5 | S65: =J65-27 -> 805.5 | T65: =J65 -> 832.5 | AA65: =J65*2-O65 -> 27 | AB65: =SUM(Y65:AA65) -> 27
A66: HONIX (elevadores) (01 de um mês a 30 do mesmo mês) | B66: Contratos SPI | C66: VGM01N01I7N | D66: 21051130000123 | E66: 23106.053280/2018-11 | F66: 45920 | G66: =IF((F66-TODAY())<0,"EXPIRADO", IF((F66-TODAY())<=60,"EM BREVE","NO PRAZO")) -> EXPIRADO | H66: Não será renovado | I66: 090/2019 | K66: =L66/12 -> 39124.22 | L66: 469490.64 | M66: 34750.02 | O66: =SUM(M66:N66) -> 34750.02 | Z66: =K66-O66 -> 4374.2 | AA66: =K66 -> 39124.22 | AB66: =SUM(Y66:AA66) -> 43498.42 | AD66: =SUM(J66:K66)*2 -> 78248.44 | AE66: =O66-AD66 -> -43498.42 | AG66: =(SUM(J66:K66)*2)-O66 -> 43498.42
A67: ONE ELEVADORES DF LTDA | B67: Contratos SPI | C67: VGM01N01I7N | D67: 02.633.335/0001-72 | E67: 23106.077388/2024-30 | F67: 47436 | G67: =IF((F67-TODAY())<0,"EXPIRADO", IF((F67-TODAY())<=60,"EM BREVE","NO PRAZO")) -> NO PRAZO | I67: 94/2024 | J67: =L67/12 -> 339678 | L67: =20380680/5 -> 4076136 | N67: 2995835 | O67: =SUM(M67:N67) -> 2995835 | AB67: =SUM(Y67:AA67) -> 0
A68: - ENERGIA ELÉTRICA - SPI | B68: Contratos SPI | C68: VGM01N01I2N | D68: 07522669000192 | J68: 40000 | L68: =J68*12 -> 480000 | M68: 88000.42 | N68: 2965.4 | O68: =SUM(M68:N68) -> 90965.82 | S68: =40000-12743 -> 27257 | U68: =J68-23261 -> 16739 | AB68: =SUM(Y68:AA68) -> 0 | AD68: =J68*2 -> 80000 | AE68: =O68-AD68 -> 10965.82 | AG68: =(SUM(J68:K68)*2)-O68 -> -10965.82
A69: - CAESB - SPI | B69: Contratos SPI | C69: VGM01N01I3N | D69: 00082024000137 | J69: 136350 | L69: =J69*12 -> 1636200 | M69: 251998.44 | N69: 0 | O69: =SUM(M69:N69) -> 251998.44 | R69: =J69-O69 -> -115648.44 | S69: =J69 -> 136350 | V69: =J69-1163 -> 135187 | AA69: =J69*2-O69 -> 20701.56 | AB69: =SUM(Y69:AA69) -> 20701.56 | AD69: =J69*2 -> 272700 | AE69: =O69-AD69 -> -20701.56
A70: - Despesas de Condomínio | B70: Contratos SPI | C70: VGM01N01K6N | E70: 23106.134844/2020-22 | J70: 245000 | L70: =J70*12 -> 2940000 | M70: 240888.51 | N70: 0 | O70: =SUM(M70:N70) -> 240888.51 | R70: =J70-O70 -> 4111.49 | T70: =J70-8976 -> 236024 | U70: =J70-49349 -> 195651 | Z70: =J70-O70 -> 4111.49 | AA70: =J70 -> 245000 | AB70: =SUM(Y70:AA70) -> 249111.49 | AD70: =J70*2 -> 490000 | AE70: =O70-AD70 -> -249111.49 | AG70: =(SUM(J70:K70)*2)-O70 -> 249111.49
A71: Restaurante ISM EIRELI (diretoria RU) - Ação 20RK planilha DRU | B71: Contrato DAC/RU | C71: VGM01N01B5N | D71: 04228626001263 | E71: 23106.013653/2020-28 | F71: 46274 | G71: =IF((F71-TODAY())<0,"EXPIRADO", IF((F71-TODAY())<=60,"EM BREVE","NO PRAZO")) -> NO PRAZO | I71: 31/2021 | J71: =L71/12 -> 1500933.6 | L71: 18011203 | M71: 1726196.1 | N71: 0 | O71: =SUM(M71:N71) -> 1726196.1 | U71: ='DRU 25'!J10 -> 1791326.9 | Z71: =1791326.86-O71 -> 65130.77 | AA71: 1506537.9 | AB71: =SUM(Y71:AA71) -> 1571668.7 | AD71: =Y71+Z71 -> 65130.77 | AG71: =(SUM(J71:K71)*2)-O71 -> 1275671
A72: - Serviço manutenção piscinas Casa Niemeyer | B72: Contratos Diversos | C72: VGM01N01N5N | O72: =SUM(M72:N72) -> 0 | AB72: =SUM(Y72:AA72) -> 0 | AG72: =(SUM(J72:K72)*2)-O72 -> 0
A73: Auxílio Moradia - Processos judiciais residentes médicos | B73: Contratos Diversos | C73: VEP01S19A1N | E73: 00424.086713/2023-76 00424.187663/2022-62 00424.084224/2023-80 00424.158540/2022-14 00424.092166/2023-68 00424.081691/2024-39 00424.126909/2024-91 00424.190315/2023-53 00424.124332/2024-83 | J73: 73000 | L73: =11086.47+11086.47+11086.47+11086.47+8622.81+8622.81+3695.49+3695.49+2463.66 -> 71446.14 | M73: 0 | O73: =SUM(M73:N73) -> 0 | AB73: =SUM(Y73:AA73) -> 0 | AG73: =(SUM(J73:K73)*2)-O73 -> 146000
A74: PGFN: 1° ATI, negociação conta n°: 7300348 ( Consulta Acordo n°1 - Conta da Negociação 7300348 (SEI nº 10575553) SEI origem: 23106.094258/2021-19 SEI pagamento em 2023: 23106.005996/2023-61 Despacho que contém explicação: 10567234 do SEI 23106.132563/2023-88 Acordo de Transação Individual (ATI), referente à dívida ativa tributária junto à PGFN -débitos previdenciários Empenho atual: 2024NE000285 | B74: Contratos Diversos | C74: VGH01N0112N | E74: 23106.094258/2021-19 23106.001775/2022-33 23106.005996/2023-61 23106.044758/2024-52 23106.132563/2023-88 | F74: 60 parcelas (já pagou 20/60) | J74: 285000 | L74: =J74*12 -> 3420000 | M74: =569765.43+50000 -> 619765.43 | N74: 0 | O74: =SUM(M74:N74) -> 619765.43 | U74: =285000-O74 -> -334765.43 | AB74: =SUM(Y74:AA74) -> 0 | AG74: =(SUM(J74:K74)*2)-O74 -> -49765.43
A75: PGFN: 2° ATI, negociação conta n°: 8815031 (Consulta Acordo n°2 - Conta da Negociação 8815031 (SEI nº 10576277)) SEI origem: 23106.059565/2023-15 SEI pagamento 2023:23106.123083/2023-26 que foi realizado o pagamento da entrada e no 23106.128684/2023-25 constará os demais pagamentos. Despacho que contém explicação: 10567234 do SEI 23106.132563/2023-88 Guias de Recolhimento de FGTS e Informações à Previdência Social (GFIP) das competências de janeiro/2011, fevereiro/2011, abril/2011, junho/2011 e novembro/2011 Empenho atual: 2023NE003705; 2024NE000487 | B75: Contratos Diversos | C75: VGH01N0112N | E75: 23106.059565/2023-15 23106.128684/2023-25 23106.044758/2024-52 23106.132563/2023-88 | F75: 60 parcelas (já pagou 10/60) | J75: 28500 | L75: =J75*12 -> 342000 | M75: =62424.84+28500+24893 -> 115817.84 | N75: 0 | O75: =SUM(M75:N75) -> 115817.84 | U75: =28500-24893 -> 3607 | AB75: =SUM(Y75:AA75) -> 0 | AG75: =(SUM(J75:K75)*2)-O75 -> -58817.84
A76: RFB: Conta da Negociação 0211000120 (Consulta Parcelamento n°1 - Conta da Negociação 0211000120 (SEI nº 10580261)) SEI origem: 23106.059634/2023-91 SEI pagamento em 2023: 23106.087581/2023-06 Despacho que contém explicação: 10567234 do SEI 23106.132563/2023-88 Atraso das Guias de Recolhimento de FGTS e Informações à Previdência Social (GFIP) das competências de julho/2010, outubro/2010, novembro/2010, dezembro/2011 e 13°/2011 Empenho atual: 2023NE003850 e 2024NE000284 | B76: Contratos Diversos | C76: VGH01N0112N | E76: 23106.059634/2023-91 23106.087581/2023-06 23106.044758/2024-52 23106.132563/2023-88 | F76: 60 parcelas (já pagou 13/60) | J76: 22500 | L76: =J76*12 -> 270000 | M76: =45348.61+74289.29+7373 -> 127010.9 | N76: 0 | O76: =SUM(M76:N76) -> 127010.9 | AB76: =SUM(Y76:AA76) -> 0 | AG76: =(SUM(J76:K76)*2)-O76 -> -82010.9
A77: - Ajuda de custo (Redistribuição de servidores) | B77: Contratos Diversos | C77: VGH01N0111N | J77: 20000 | L77: =J77*12 -> 240000 | M77: 0 | N77: 0 | O77: =SUM(M77:N77) -> 0 | R77: =J77 -> 20000 | S77: =J77 -> 20000 | T77: =J77 -> 20000 | U77: =J77 -> 20000 | V77: =J77 -> 20000 | W77: =J77 -> 20000 | Z77: =J77 -> 20000 | AA77: =J77 -> 20000 | AB77: =SUM(Y77:AA77) -> 40000 | AG77: =(SUM(J77:K77)*2)-O77 -> 40000
A78: Cespe (despesas diversas) | B78: CESPE | C78: VGR02N01A1N | E78: 23106.019902/2017-93 | J78: 70000 | L78: =J78*12 -> 840000 | M78: 101505.99 | N78: 25585.25 | O78: =SUM(M78:N78) -> 127091.24 | T78: =J78-7000 -> 63000 | U78: =J78 -> 70000 | AA78: =J78*2-N78 -> 114414.75 | AB78: =SUM(Y78:AA78) -> 114414.75 | AD78: =J78*2 -> 140000 | AE78: =O78-AD78-N78 -> -38494.01
A79: Contrato de serviços especializados com vistas à realização de estudos técnicos, de planejamentos, projetos básicos ou executivos, assessoria técnica e apoio técnico nas áreas de Tecnologia da Informação (TI) e Logística, entre a UnB e o CEBRASPE | B79: DEG | C79: VGR02N01A2N | D79: 18284407000153 | E79: 23106.040707/2022-90 (60 parcelas) | F79: 46441 | G79: =IF((F79-TODAY())<0,"EXPIRADO", IF((F79-TODAY())<=60,"EM BREVE","NO PRAZO")) -> NO PRAZO | I79: 1205/2022 | J79: 44033.82 | L79: =J79*12 -> 528405.84 | M79: 447943.29 | N79: 0 | O79: =SUM(M79:N79) -> 447943.29 | AB79: =SUM(Y79:AA79) -> 0 | AD79: =J79*2 -> 88067.64 | AF79: -88067.64 | AG79: =(SUM(J79:K79)*2)-O79 -> -359875.65
A80: CEBRASPE (Processos seletivos UnB) | B80: DEG | C80: VGM01N01J5N | D80: 18284407000153 | E80: 23106.098851/2020-53 23106.018871/2022-11 23106.093468/2021-90 23106.065413/2023-51 23106.065557/2023-16 23106.035963/2024-27 | F80: 46734 | G80: =IF((F80-TODAY())<0,"EXPIRADO", IF((F80-TODAY())<=60,"EM BREVE","NO PRAZO")) -> NO PRAZO | I80: diversos | J80: 280000 | L80: =J80*12 -> 3360000 | M80: 42971.08 | N80: 320755.17 | O80: =SUM(M80:N80) -> 363726.25 | AA80: =J80*2-O80 -> 196273.75 | AB80: =SUM(Y80:AA80) -> 196273.75 | AD80: =J80*2 -> 560000
A81: CONCEIÇÃO Aparecida Braga 67186920691 ME (análise e levantamento de conjuntos documentais do arquivo do Cespe/UnB) | B81: Contratos Diversos | C81: VGM01N01P1N | D81: 41423145000182 | E81: 23106.059346/2020-93 | F81: 46327 | G81: =IF((F81-TODAY())<0,"EXPIRADO", IF((F81-TODAY())<=60,"EM BREVE","NO PRAZO")) -> NO PRAZO | I81: 1230/2022 | J81: 17000 | L81: =J81*12 -> 204000 | M81: 37677.33 | N81: 0 | O81: =SUM(M81:N81) -> 37677.33 | T81: 17000 | U81: =J81 -> 17000 | V81: =J81-14992 -> 2008 | W81: =J81-14992 -> 2008 | AB81: =SUM(Y81:AA81) -> 0 | AD81: =J81*2 -> 34000 | AF81: -31532.95 | AG81: =(SUM(J81:K81)*2)-O81 -> -3677.33
A82: - Prisma SYS/ DCF (Licença de Uso e suporte técnico Consiafi) - parcela única | B82: Contratos Diversos | C82: VGM01N01L7N | D82: 38068664000165 | E82: 23106.009.366/2016-37 23106.050235/2020-11 | F82: 45682 | G82: =IF((F82-TODAY())<0,"EXPIRADO", IF((F82-TODAY())<=60,"EM BREVE","NO PRAZO")) -> EXPIRADO | H82: Não Pode ser renovado 11559576 | I82: 504/2020 | L82: 45000 | M82: 0 | N82: 0 | O82: =SUM(M82:N82) -> 0 | AB82: =SUM(Y82:AA82) -> 0 | AG82: =(SUM(J82:K82)*2)-O82 -> 0
A83: Tratador de Piscinas CO e casa Oscar Niemayer - (AP Piscinas EIRELI) | B83: Contratos Diversos | C83: VGM01N01E2N | D83: 08475822000130 | E83: 23106.013349/2019-47 | F83: 45844 | G83: =IF((F83-TODAY())<0,"EXPIRADO", IF((F83-TODAY())<=60,"EM BREVE","NO PRAZO")) -> EXPIRADO | H83: não será renovado | I83: 93/2020 | K83: =L83/12 -> 5039.3475 | L83: 60472.17 | M83: 23684.51 | N83: 0 | O83: =SUM(M83:N83) -> 23684.51 | T83: =K83-166.38 -> 4872.9675 | U83: =K83 -> 5039.3475 | W83: =K83-1512 -> 3527.3475 | AB83: =SUM(Y83:AA83) -> 0 | AD83: =K83*2 -> 10078.695 | AG83: =(SUM(J83:K83)*2)-O83 -> -13605.815
A84: PLUS TERCEIRIZACAO LTDA (serviços continuados de tratador de piscina) | B84: Contratos Diversos | C84: VGM01N01E2N | D84: 27072369000166 | E84: 23106.062907/2024-65 | F84: 46331 | G84: =IF((F84-TODAY())<0,"EXPIRADO", IF((F84-TODAY())<=60,"EM BREVE","NO PRAZO")) -> NO PRAZO | I84: 25/2025 | K84: =L84/12 -> 5901.275 | L84: 70815.3 | M84: 999.2 | O84: =SUM(M84:N84) -> 999.2 | Z84: =K84-O84 -> 4902.075 | AA84: =K84 -> 5901.275
A85: - STI UFRN/ GRE (5 parcelas) | B85: Contratos Diversos | C85: VGM01N01M5N | E85: 23106.073966/2017-30 23106.091209/2020-43 | G85: =IF((F85-TODAY())<0,"EXPIRADO", IF((F85-TODAY())<=60,"EM BREVE","NO PRAZO")) -> EXPIRADO | I85: TED nº 8444.12.0820/2021 | L85: 561085.01 | O85: =SUM(M85:N85) -> 0 | AB85: =SUM(Y85:AA85) -> 0 | AF85: -561085.01
A86: - Correios - ECT -reduziu porque não temos mais contrato de encomendas | B86: Comunicação | C86: VGM01N01J1N | D86: 34028316000707 | E86: 23106.137850/2017-36; 23106.070712/2018-41 23106.015565/2023-11 | F86: 46792 | G86: =IF((F86-TODAY())<0,"EXPIRADO", IF((F86-TODAY())<=60,"EM BREVE","NO PRAZO")) -> NO PRAZO | I86: 1207/2023 | J86: 3000 | L86: =J86*12 -> 36000 | M86: 12684.44 | N86: 0 | O86: =SUM(M86:N86) -> 12684.44 | AB86: =SUM(Y86:AA86) -> 0 | AD86: =J86*2 -> 6000 | AF86: -642 | AG86: =(SUM(J86:K86)*2)-O86 -> -6684.44
A87: - Empresa Brasil de Comunicação (EBC) | B87: Comunicação | C87: VGM01N01I9N | E87: 23106.048294/2020-20 | F87: 46001 | G87: =IF((F87-TODAY())<0,"EXPIRADO", IF((F87-TODAY())<=60,"EM BREVE","NO PRAZO")) -> EM BREVE | I87: 213/2020 | J87: 2000 | L87: =J87*12 -> 24000 | M87: 5227.45 | N87: 0 | O87: =SUM(M87:N87) -> 5227.45 | T87: =J87-307 -> 1693 | AB87: =SUM(Y87:AA87) -> 0 | AD87: =J87*2 -> 4000 | AE87: =O87-AD87 -> 1227.45 | AG87: =(SUM(J87:K87)*2)-O87 -> -1227.45
A88: - Andromeda (serviços de becário e brigadista nas cerimônias de colação de grau) | B88: Cerimonial | C88: VGM01N01B9N | D88: 20882119000142 | E88: 23106.072605/2019-38 | F88: 45638 | G88: =IF((F88-TODAY())<0,"EXPIRADO", IF((F88-TODAY())<=60,"EM BREVE","NO PRAZO")) -> EXPIRADO | H88: Não Pode ser renovado 10809034 Verificar saldo de Empenho | I88: 135/2019 | J88: 33000 | L88: =J88*12 -> 396000 | N88: 4308.48 | O88: =SUM(M88:N88) -> 4308.48 | R88: =J88-O88 -> 28691.52 | S88: =J88-4308 -> 28692 | T88: =J88 -> 33000 | U88: =J88-4308 -> 28692 | V88: =J88-4308 -> 28692 | W88: 30000 | Z88: =J88-O88 -> 28691.52 | AA88: =J88 -> 33000 | AB88: =SUM(Y88:AA88) -> 61691.52 | AD88: =J88*2 -> 66000 | AE88: =O88-AD88 -> -61691.52
A89: Casablanca (Serviço de Mobiliário (Cadeiras) - manifestação de interesse de prorrogação ( Ofício 24-2024 (10948905) | B89: Cerimonial | C89: VGM01N01B9N | D89: 03370903000152 | E89: 23106.138096/2020-57 23106.042068/2025-40 23106.105637/2024-94 (novo contrato) | F89: 46311 | G89: =IF((F89-TODAY())<0,"EXPIRADO", IF((F89-TODAY())<=60,"EM BREVE","NO PRAZO")) -> NO PRAZO | I89: 083/2024 | J89: 10500 | L89: =J89*12 -> 126000 | M89: 121064.37 | N89: 797 | O89: =SUM(M89:N89) -> 121861.37 | T89: =J89-3210 -> 7290 | AB89: =SUM(Y89:AA89) -> 0 | AD89: =J89*2 -> 21000 | AE89: =O89-AD89-N89 -> 100064.37
A90: Lavanderia Cristal Serviços Expressos Ltda (higienização e passadoria de becas) | B90: Cerimonial | C90: VGM01N01B9N | D90: 01319181000186 | E90: 23106.001918/2023-98 | F90: 46136 | G90: =IF((F90-TODAY())<0,"EXPIRADO", IF((F90-TODAY())<=60,"EM BREVE","NO PRAZO")) -> NO PRAZO | I90: Dispensa. Nº 10002/2023 | J90: 500 | L90: =J90*12 -> 6000 | M90: 11233.4 | N90: 0 | O90: =SUM(M90:N90) -> 11233.4 | AB90: =SUM(Y90:AA90) -> 0 | AD90: =J90*2 -> 1000 | AE90: =O90-AD90-N90 -> 10233.4
A91: - SIMPRESS - Outsourcing de serviços de impressão | B91: Contratos custeados pelas Unidades (STI) | C91: VGM01N01M8N | D91: 07432517000107 | E91: 23106.000978/2016-64 23106.010988/2019-51 | F91: 46022 | G91: =IF((F91-TODAY())<0,"EXPIRADO", IF((F91-TODAY())<=60,"EM BREVE","NO PRAZO")) -> EM BREVE | I91: 512/2021 | J91: =62000*104.4% -> 64728 | L91: =J91*12 -> 776736 | M91: 33015.44 | N91: 0 | O91: =SUM(M91:N91) -> 33015.44 | Z91: =J91-O91 -> 31712.56 | AA91: =J91 -> 64728 | AB91: =SUM(Y91:AA91) -> 96440.56 | AD91: =J91*2 -> 129456 | AF91: -60500.4 | AG91: =(SUM(J91:K91)*2)-O91 -> 96440.56
AG92: =(SUM(J92:K92)*3)-O92 -> 0
A93: Total da despesa | J93: =SUM(J4:J91) -> 11712226 | K93: =SUM(K4:K91) -> 8045226.7 | L93: =SUM(L4:L91) -> 2.4537074e+08 | M93: =SUM(M4:M91) -> 24044921 | N93: =SUM(N4:N91) -> 13251387 | O93: =SUM(O4:O91) -> 37296308 | P93: =SUM(P4:P91) -> 0 | Q93: =SUM(Q4:Q91) -> 0 | ... AB93: =SUM(AB4:AB91) -> 14188513 | AD93: =SUM(AD4:AD91) -> 30782386 | AE93: =SUM(AE4:AE91) -> 179547.61 | AF93: =SUM(AF4:AF91) -> -6549485.5 | AG93: =SUM(AG4:AG91) -> 9716111.3
AF95: =AF50 -> -1924342.1
AF96: -6000000
AF97: -1280820.9
AF99: =SUM(AF95:AF96) -> -7924342.1
AF100: =AF99+#REF! -> #REF!

Sheet Programação 17.11
A1: Acompanhamento de Contratos* | AA1: continuados | AB1: =#REF!+#REF!+AB4+AB5+#REF!+AB6+#REF!+AB9+SUM(AB14:AB18)+AB21+#REF!+AB22+#REF!+#REF!+#REF! -> #REF! | AC1: spi | AE1: ver observação | AH1: =SUM(AB24:AB29) -> 350001.99
A2: Data de Atualização: 10/11/2025 | AB2: =AB5+#REF!+AB9+#REF!+#REF!+AB14+#REF!+#REF!+AB15+AB16+AB17+#REF!+AB18+AB21+#REF!+AB22+#REF!+#REF!+#REF! -> #REF! | AC2: por demanda | AE2: NÃO ANULAR | AH2: =#REF!+AB6+AB7+AB10+#REF!+AB11+#REF!+#REF!+#REF!+#REF!+AB12+#REF!+#REF!+#REF!+#REF!+#REF!+AB13+#REF!+#REF!+AB23+AB32+AB33+AB34+#REF!+#REF!+#REF!+#REF!+#REF!+AB35 -> #REF!
A3: Descrição das despesas | B3: UGR | C3: PI 2025 | D3: CNPJ | E3: Processo | F3: Vigência | G3: Status do Contrato | H3: Situação da prorrogação | I3: nº Contrato | J3: Valor Contrato Média mensal | K3: Valor Cont Continuado Mensal | L3: Total estimado Anual | M3: Saldo Empenhos 2025 | N3: Saldo de Empenhos RAP | O3: Total RAP + Empenho | P3: 45658 | Q3: 45689 | R3: 45717 | S3: 45748 | T3: 45778 | U3: 45809 | V3: 45839 | W3: 45870 | X3: 45901 | Y3: 45931 | Z3: 45962 | AA3: 45992 | AB3: Total necessário | AC3: Causas Judiciais | AD3: OUT-NOV (2024) | AE3: Saldo passivel de Anulação | AF3: Necessidade de Empenho até Novembro | AG3: Necessidade Janeiro | AH3: =#REF!+#REF!+#REF! -> #REF!
A4: Pasep - HUB | B4: HUB | C4: VGM01N01N1N | J4: 49000 | L4: =48891*13.33 -> 651717.03 | M4: 90145.45 | O4: =SUM(M4:N4) -> 90145.45 | AA4: =J4*2-O4 -> 7854.55 | AB4: =SUM(Y4:AA4) -> 7854.55 | AC4: RU | AH4: =AB30 -> 1571668.7
A5: Pasep - UnB | B5: DGP/ folha | C5: VGM01N01N1N | J5: 810000 | L5: =J5*12 -> 9720000 | M5: 1492474.5 | N5: 0 | O5: =SUM(M5:N5) -> 1492474.5 | T5: =810000-556810 -> 253190 | U5: =J5 -> 810000 | V5: =J5 -> 810000 | AA5: =J5*2-O5 -> 127525.53 | AB5: =SUM(Y5:AA5) -> 127525.53 | AD5: =SUM(J5:K5)*2 -> 1620000 | AE5: =O5-AD5 -> -127525.53 | AG5: =(SUM(J5:K5)*2)-O5 -> 127525.53 | AH5: =AB2+AH1+AH2+AH3+#REF!+#REF!+AH4 -> #REF!
A6: Energia Elétrica UnB Cerrado - CONTRATO CCER - ENEL N. 36/2020 e CELG DISTRIBUIÇÃO S.A - CELG D, Equatorial Goiás Distribuidora de Energia S/A | B6: UnB Cerrado | C6: VGM01N01I2N | D6: 1543032000104 | E6: 23106.044802/2020-09 23106.083937/2023-24 | I6: 36/2020 | J6: 1585.03 | L6: =J6*12 -> 19020.36 | M6: =570.63+124.47 -> 695.1 | N6: 41.48 | O6: =SUM(M6:N6) -> 736.58 | U6: =J6-324 -> 1261.03 | W6: =1585-1230 -> 355 | Z6: =J6-O6 -> 848.45 | AA6: =J6 -> 1585.03 | AB6: =SUM(Y6:AA6) -> 2433.48 | AD6: =SUM(J6:K6)*2 -> 3170.06 | AE6: =O6-AD6 -> -2433.48 | AG6: =(SUM(J6:K6)*2)-O6 -> 2433.48
A7: OI SA recuperação judicial | B7: STI | C7: VGM01N01I4N | D7: 76535764000143 | E7: 23106.012727/2018-94 | F7: 46247 | G7: =IF((F7-TODAY())<0,"EXPIRADO", IF((F7-TODAY())<=60,"EM BREVE","NO PRAZO")) -> NO PRAZO | I7: 515/2021 | J7: 60000 | L7: =J7*12 -> 720000 | M7: 105024.66 | N7: 0 | O7: =SUM(M7:N7) -> 105024.66 | R7: =J7 -> 60000 | S7: =J7 -> 60000 | T7: =J7 -> 60000 | AA7: =J7*2-O7 -> 14975.34 | AB7: =SUM(Y7:AA7) -> 14975.34 | AD7: =SUM(J7:K7)*2 -> 120000 | AE7: =O7-AD7 -> -14975.34 | AF7: =-Y7-Z7 -> 0 | AG7: =(SUM(J7:K7)*2)-O7 -> 14975.34
A8: QUALIFICAR - Suporte TI (Serviços de Manutenção dos Computadores da UnB) | B8: STI | C8: VGM01N01A3N | D8: 04.752.792/0001-01 | E8: 23106.016945/2023-65 | F8: 46147 | G8: =IF((F8-TODAY())<0,"EXPIRADO", IF((F8-TODAY())<=60,"EM BREVE","NO PRAZO")) -> NO PRAZO | I8: 512/2025 | K8: =L8/12 -> 182288 | L8: 2187456 | M8: 323045.17 | N8: 0 | O8: =SUM(M8:N8) -> 323045.17 | U8: 182288 | AA8: =K8*2-O8 -> 41530.83 | AB8: =SUM(Y8:AA8) -> 41530.83 | AG8: =(SUM(J8:K8)*2)-O8 -> 41530.83
A9: -SIG SOFTWARE & CONSULTORIA EM TECNOLOGIA DA I (Serviço de apoio especializado nas atividades necessárias ao suporte negocial, customização e sustentação do Sistemas Institucionais Integrados de Gestão (SIG)) | B9: STI | C9: VGM01N01Q4N | D9: 13.406.686/0001-67 | E9: 23106.125254/2022-71 | F9: 46082 | G9: =IF((F9-TODAY())<0,"EXPIRADO", IF((F9-TODAY())<=60,"EM BREVE","NO PRAZO")) -> NO PRAZO | I9: 505/2024 | J9: =L9/12 -> 236095 | K9: ainda sem histórico de liquidação | L9: 2833140 | M9: 0 | N9: 0 | O9: =SUM(M9:N9) -> 0 | S9: =236037-202037 -> 34000 | Z9: =J9 -> 236095 | AA9: =J9 -> 236095 | AB9: =SUM(Y9:AA9) -> 472190 | AD9: =SUM(J9:K9)*2 -> 472190 | AF9: -99075 | AG9: =(SUM(J9:K9)*2)-O9 -> 472190
A10: Inframérica - Agenciamento de Carga Internacional (conforme demanda) | B10: Contratos DCO | C10: VGM01N01L3N | D10: 15559082000186 | E10: 23106.011.137/2014-11 23106.086385/2019-20 | F10: 45743 | G10: =IF((F10-TODAY())<0,"EXPIRADO", IF((F10-TODAY())<=60,"EM BREVE","NO PRAZO")) -> EXPIRADO | I10: 026/2020 | M10: 0 | N10: 0 | O10: =SUM(M10:N10) -> 0 | AB10: =SUM(Y10:AA10) -> 0 | AD10: =SUM(J10:K10)*2 -> 0 | AE10: =O10-AD10 -> 0
A11: BELFORT GERENCIAMENTO DE RESIDUOS LTDA - empresa especializada nos serviços continuados de coleta, transporte, tratamento e disposição final de resíduos de serviços de saúde (RSS) | B11: Contratos DCA | C11: VGM01N01E4N | D11: 10865146000153 | E11: 23106.065223/2022-53 | F11: 46039 | G11: =IF((F11-TODAY())<0,"EXPIRADO", IF((F11-TODAY())<=60,"EM BREVE","NO PRAZO")) -> EM BREVE | I11: 1204/2023 | J11: 4000 | L11: =J11*12 -> 48000 | M11: 6981.19 | N11: 0 | O11: =SUM(M11:N11) -> 6981.19 | R11: =J11-O11 -> -2981.19 | S11: =J11-1948 -> 2052 | AA11: =J11*2-O11 -> 1018.81 | AB11: =SUM(Y11:AA11) -> 1018.81 | AD11: =SUM(J11:K11)*2 -> 8000 | AE11: =O11-AD11 -> -1018.81
A12: CRUZEIRO CONTROLE DE PRAGAS E DESENTUPIMENTO | B12: PRC | C12: VGM01N01D3N | D12: 22.575.793/0001-00 | E12: 23106.058637/2021-45 | F12: 45980 | G12: =IF((F12-TODAY())<0,"EXPIRADO", IF((F12-TODAY())<=60,"EM BREVE","NO PRAZO")) -> EM BREVE | H12: Em fase de prorrogação | I12: 1222/2024 | J12: =L12/12 -> 65625.02 | L12: 787500.24 | M12: 110567.4 | N12: 0 | O12: =SUM(M12:N12) -> 110567.4 | T12: =J12-O12 -> -44942.38 | U12: =J12-60820 -> 4805.02 | V12: =J12-60820 -> 4805.02 | AA12: =J12 -> 65625.02 | AB12: =SUM(Y12:AA12) -> 65625.02 | AG12: =(SUM(J12:K12)*2)-O12 -> 20682.64
A13: 3P HGM solução visual (serviços de comunicação visual) | B13: PRC | C13: VGM01N01O7N | D13: 34.998.513/0001-55 | E13: 23106.089249/2019-91 | F13: 46224 | G13: =IF((F13-TODAY())<0,"EXPIRADO", IF((F13-TODAY())<=60,"EM BREVE","NO PRAZO")) -> NO PRAZO | I13: 1217/2022 | J13: 500000 | L13: =J13*12 -> 6000000 | M13: 950140.51 | N13: 0 | O13: =SUM(M13:N13) -> 950140.51 | R13: =500000-83593 -> 416407 | S13: =500000-83593 -> 416407 | T13: 500000 | W13: =500000-208156 -> 291844 | AA13: =J13*2-O13 -> 49859.49 | AB13: =SUM(Y13:AA13) -> 49859.49 | AD13: =SUM(J13:K13)*2 -> 1000000 | AE13: =O13-AD13 -> -49859.49 | AG13: =(SUM(J13:K13)*2)-O13 -> 49859.49
A14: RCS Tecnologia LTDA - copeiragem | B14: Contratos DCA | C14: VGM01N01O2N | D14: 8220952000122 | E14: 23106.125355/2019-46 23106.035022/2021-41 | F14: 45929 | G14: =IF((F14-TODAY())<0,"EXPIRADO", IF((F14-TODAY())<=60,"EM BREVE","NO PRAZO")) -> EXPIRADO | H14: Não será renovado | I14: 07/2021 | K14: 131667.49 | L14: =K14*12 -> 1580009.9 | M14: 61444.83 | N14: 0 | O14: =SUM(M14:N14) -> 61444.83 | S14: 131667 | U14: =K14 -> 131667.49 | Z14: =K14-O14 -> 70222.66 | AA14: =K14 -> 131667.49 | AB14: =SUM(Y14:AA14) -> 201890.15 | AD14: =SUM(J14:K14)*2 -> 263334.98 | AE14: =O14-AD14 -> -201890.15 | AG14: =(SUM(J14:K14)*2)-O14 -> 201890.15
A15: - RCA (Limpeza e Conservação) | B15: Contratos DCA | C15: VGM01N01A7N | D15: 69.207.850/0001-61 | E15: 23106.057738/2021-07 | F15: 46402 | G15: =IF((F15-TODAY())<0,"EXPIRADO", IF((F15-TODAY())<=60,"EM BREVE","NO PRAZO")) -> NO PRAZO | I15: 02/2022 | K15: 1918496.1 | L15: =K15*12 -> 23021953 | M15: 213422.1 | N15: 0 | O15: =SUM(M15:N15) -> 213422.1 | S15: =1882331-116567 -> 1765764 | T15: =1882331-116567 -> 1765764 | U15: =1882331-116567 -> 1765764 | V15: =1882331-116567 -> 1765764 | W15: =1882331-116567 -> 1765764 | X15: =1882331-116567 -> 1765764 | Z15: =K15-O15 -> 1705074 | AA15: =K15 -> 1918496.1 | AB15: =SUM(Y15:AA15) -> 3623570.1 | AD15: =SUM(J15:K15)*2 -> 3836992.2 | AF15: =O15-AD15 -> -3623570.1
A16: Life Defense (Segurança) | B16: Contratos DCA | C16: VGM01N01A8N | D16: 02674687000176 | E16: 23106.016977/2013-99 23106.083943/2018-14 23106.047642/2024-75 | F16: 46097 | G16: =IF((F16-TODAY())<0,"EXPIRADO", IF((F16-TODAY())<=60,"EM BREVE","NO PRAZO")) -> NO PRAZO | I16: 011/2020 | K16: 1617878.6 | L16: =K16*12 -> 19414543 | M16: 3235757.2 | N16: 0 | O16: =SUM(M16:N16) -> 3235757.2 | S16: =K16 -> 1617878.6 | U16: =K16 -> 1617878.6 | AB16: =SUM(Y16:AA16) -> 0 | AD16: =SUM(J16:K16)*2 -> 3235757.2 | AF16: =O16-AD16 -> 0 | AG16: =(SUM(J16:K16)*2)-O16 -> 0
A17: G&E SERVICOS TERCEIRIZADOS LTDA (PORTARIA) | B17: Contratos DCA | C17: VGM01N01A9N | D17: 08744139000151 | E17: 23106.085840/2022-75 23106.005560/2022-91 23106.046596/2024-97 | F17: 46020 | G17: =IF((F17-TODAY())<0,"EXPIRADO", IF((F17-TODAY())<=60,"EM BREVE","NO PRAZO")) -> EM BREVE | I17: 081/2022 | K17: =1412211.24 -> 1412211.2 | L17: =K17*12 -> 16946535 | M17: 1022222.7 | N17: 0 | O17: =SUM(M17:N17) -> 1022222.7 | R17: =K17-N17 -> 1412211.2 | S17: =1238299-555 -> 1237744 | U17: =K17 -> 1412211.2 | Z17: =K17-O17 -> 389988.51 | AA17: =K17 -> 1412211.2 | AB17: =SUM(Y17:AA17) -> 1802199.8 | AD17: =SUM(J17:K17)*2 -> 2824422.5 | AF17: =O17-AD17 -> -1802199.8 | AG17: =(SUM(J17:K17)*2)-O17 -> 1802199.8
A18: GRIFFO (recepcionista) | B18: Contratos DCA | C18: VGM01N01B3N | D18: 26426650000197 | E18: 23106.127519/2018-99; 23106.069857/2019-80 23106.070409/2023-13 | F18: 46221 | G18: =IF((F18-TODAY())<0,"EXPIRADO", IF((F18-TODAY())<=60,"EM BREVE","NO PRAZO")) -> NO PRAZO | I18: 071/2024 | K18: 163496.8 | L18: =K18*12 -> 1961961.6 | M18: 163496.8 | N18: 0 | O18: =SUM(M18:N18) -> 163496.8 | V18: =K18 -> 163496.8 | W18: =K18 -> 163496.8 | AA18: =K18 -> 163496.8 | AB18: =SUM(Y18:AA18) -> 163496.8 | AD18: =SUM(J18:K18)*2 -> 326993.6 | AE18: =O18-AD18 -> -163496.8 | AG18: =(SUM(J18:K18)*2)-O18 -> 163496.8
A19: MPE ENGENHARIA E SERVICOS S/A (serviços comuns de engenharia, incluindo manutenção, conservação, adaptação, reparação e instalação de infraestruturas prediais e imobiliárias) - (exceto DAC) | B19: Contratos DCA | C19: VGM01N01H3N | D19: 04743858000105 | E19: 23106.149436/2022-37 | F19: 46114 | G19: =IF((F19-TODAY())<0,"EXPIRADO", IF((F19-TODAY())<=60,"EM BREVE","NO PRAZO")) -> NO PRAZO | I19: 1201/2023 | J19: 1600000 | L19: =J19*12 -> 19200000 | M19: 435887.47 | N19: 0 | O19: =SUM(M19:N19) -> 435887.47 | U19: =J19-836351 -> 763649 | V19: =J19-1393762 -> 206238 | W19: =J19-460192 -> 1139808 | Z19: =J19-O19 -> 1164112.5 | AA19: 1998000 | AB19: =SUM(Y19:AA19) -> 3162112.5 | AD19: =SUM(J19:K19)*2 -> 3200000 | AF19: -419070 | AG19: =(SUM(J19:K19)*2)-O19 -> 2764112.5
A20: MPE - Adequação e impermeabilização | B20: Contratos DCA | C20: VGA02N43E3N | D20: 04743858000105 | E20: 23106.149228/2022-38 | F20: 46022 | G20: =IF((F20-TODAY())<0,"EXPIRADO", IF((F20-TODAY())<=60,"EM BREVE","NO PRAZO")) -> EM BREVE | H20: em fase de renovação | I20: 1110/2024 | J20: =L20/12 -> 1924342.1 | L20: =8383552.34+14708553.16 -> 23092106 | M20: 33.64 | O20: =SUM(M20:N20) -> 33.64 | U20: =J20-O20 -> 1924308.5 | W20: =1924342-1832108 -> 92234 | Z20: =J20 -> 1924342.1 | AB20: =SUM(Y20:AA20) -> 1924342.1 | AD20: =SUM(J20:K20)*2 -> 3848684.2 | AF20: =-AB20 -> -1924342.1 | AG20: =(SUM(J20:K20)*2)-O20 -> 3848650.6
A21: Ágil (Serviços Agropecuários) | B21: Contratos DCA | C21: VGM01N01C5N | D21: 72620735000129 | E21: 23106.076196/2018-68 23106.030688/2022-93 | F21: 46097 | G21: =IF((F21-TODAY())<0,"EXPIRADO", IF((F21-TODAY())<=60,"EM BREVE","NO PRAZO")) -> NO PRAZO | I21: 25/2020 | K21: 484202.15 | L21: =K21*12 -> 5810425.8 | M21: 917231.82 | O21: =SUM(M21:N21) -> 917231.82 | R21: =K21-N21 -> 484202.15 | U21: =K21 -> 484202.15 | AA21: =K21*2-O21 -> 51172.48 | AB21: =SUM(Y21:AA21) -> 51172.48 | AD21: =SUM(J21:K21)*2 -> 968404.3 | AE21: =O21-AD21 -> -51172.48 | AG21: =(SUM(J21:K21)*2)-O21 -> 51172.48
A22: - Segurança - ULTRASEG Segurança Patrimonial Ltda | B22: UnB Cerrado | C22: VGM01N01A8N | D22: 09151154000159 | E22: 23106.020717/2022-17 | F22: 46303 | G22: =IF((F22-TODAY())<0,"EXPIRADO", IF((F22-TODAY())<=60,"EM BREVE","NO PRAZO")) -> NO PRAZO | I22: 1207/2022 | K22: 23452.22 | L22: =K22*12 -> 281426.64 | M22: 1000 | N22: 0 | O22: =SUM(M22:N22) -> 1000 | U22: =K22 -> 23452.22 | Z22: =K22-O22 -> 22452.22 | AA22: =K22 -> 23452.22 | AB22: =SUM(Y22:AA22) -> 45904.44 | AD22: =SUM(J22:K22)*2 -> 46904.44 | AF22: -46904.36 | AG22: =(SUM(J22:K22)*2)-O22 -> 45904.44
A23: Jardinagem - UnB Cerrado - AMBIENTAL DO BRASIL ESTUDOS E PROJETOS AMBIENTAIS LTDA | B23: UnB Cerrado | C23: VGM01N01A5N | D23: 09150575000165 | E23: 23106.092536/2018-06 | F23: 46309 | G23: =IF((F23-TODAY())<0,"EXPIRADO", IF((F23-TODAY())<=60,"EM BREVE","NO PRAZO")) -> NO PRAZO | I23: 659/2020 | J23: =L23/12 -> 4106.25 | L23: 49275 | M23: 7891.86 | N23: 0 | O23: =SUM(M23:N23) -> 7891.86 | AA23: =J23*2-O23 -> 320.64 | AB23: =SUM(Y23:AA23) -> 320.64 | AD23: =SUM(J23:K23)*2 -> 8212.5 | AF23: =-Y23*2 -> 0
A24: Engemega - (Manutenção de Imóveis gerenciados pela Secretaria de Patrimônio Imobiliário (SPI)) – contrato 1 (contrato antigo) | B24: Contratos SPI | C24: VGM01N01D4N | D24: 33480104/0001-08 | E24: 23106.059077/2021-46 | F24: 46035 | G24: =IF((F24-TODAY())<0,"EXPIRADO", IF((F24-TODAY())<=60,"EM BREVE","NO PRAZO")) -> EM BREVE | I24: 1223/2022 | J24: 309551 | L24: 6773742 | M24: 590994.48 | O24: =SUM(M24:N24) -> 590994.48 | R24: =J24-M24 -> -281443.48 | AA24: =J24*2-O24 -> 28107.52 | AB24: =SUM(Y24:AA24) -> 28107.52 | AD24: =J24*2 -> 619102 | AE24: =O24-AD24 -> -28107.52 | AG24: =(SUM(J24:K24)*2)-O24 -> 28107.52
A25: FORMIGA ENGENHARIA E ARQUITETURA LTDA, especializada na prestação de serviços continuados, sem dedicação exclusiva de mão de obra, para realização de vistorias de entrada e saída nos imóveis de propriedade da Universidade de Brasília | B25: Contratos SPI | C25: VGM01N01D2N | D25: 22.352.353/0001-93 | E25: 23106.013588/2024-64 | F25: 46340 | G25: =IF((F25-TODAY())<0,"EXPIRADO", IF((F25-TODAY())<=60,"EM BREVE","NO PRAZO")) -> NO PRAZO | I25: 93/2024 | J25: =L25/12 -> 7018 | L25: 84216 | M25: 4754 | N25: 726 | O25: =SUM(M25:N25) -> 5480 | Z25: =J25-O25 -> 1538 | AA25: =J25 -> 7018 | AB25: =SUM(Y25:AA25) -> 8556 | AG25: =(SUM(J25:K25)*2)-O25 -> 8556
A26: SILVA EDIFICAÇÕES LTDA - emissão de laudos técnicos de avaliação de valores imobiliários | B26: Contratos SPI | C26: VGM01N01Q7N | D26: 44.532.592/0001-68 | E26: 23106.103034/2024-58 | F26: 46327 | G26: =IF((F26-TODAY())<0,"EXPIRADO", IF((F26-TODAY())<=60,"EM BREVE","NO PRAZO")) -> NO PRAZO | I26: 1220/2024 | J26: =L26/12 -> 832.5 | L26: 9990 | M26: 1638 | N26: 0 | O26: =SUM(M26:N26) -> 1638 | R26: =J26-O26 -> -805.5 | S26: =J26-27 -> 805.5 | T26: =J26 -> 832.5 | AA26: =J26*2-O26 -> 27 | AB26: =SUM(Y26:AA26) -> 27
A27: HONIX (elevadores) (01 de um mês a 30 do mesmo mês) | B27: Contratos SPI | C27: VGM01N01I7N | D27: 21051130000123 | E27: 23106.053280/2018-11 | F27: 45920 | G27: =IF((F27-TODAY())<0,"EXPIRADO", IF((F27-TODAY())<=60,"EM BREVE","NO PRAZO")) -> EXPIRADO | H27: Não será renovado | I27: 090/2019 | K27: =L27/12 -> 39124.22 | L27: 469490.64 | M27: 34750.02 | O27: =SUM(M27:N27) -> 34750.02 | Z27: =K27-O27 -> 4374.2 | AA27: =K27 -> 39124.22 | AB27: =SUM(Y27:AA27) -> 43498.42 | AD27: =SUM(J27:K27)*2 -> 78248.44 | AE27: =O27-AD27 -> -43498.42 | AG27: =(SUM(J27:K27)*2)-O27 -> 43498.42
A28: - CAESB - SPI | B28: Contratos SPI | C28: VGM01N01I3N | D28: 00082024000137 | J28: 136350 | L28: =J28*12 -> 1636200 | M28: 251998.44 | N28: 0 | O28: =SUM(M28:N28) -> 251998.44 | R28: =J28-O28 -> -115648.44 | S28: =J28 -> 136350 | V28: =J28-1163 -> 135187 | AA28: =J28*2-O28 -> 20701.56 | AB28: =SUM(Y28:AA28) -> 20701.56 | AD28: =J28*2 -> 272700 | AE28: =O28-AD28 -> -20701.56
A29: - Despesas de Condomínio | B29: Contratos SPI | C29: VGM01N01K6N | E29: 23106.134844/2020-22 | J29: 245000 | L29: =J29*12 -> 2940000 | M29: 240888.51 | N29: 0 | O29: =SUM(M29:N29) -> 240888.51 | R29: =J29-O29 -> 4111.49 | T29: =J29-8976 -> 236024 | U29: =J29-49349 -> 195651 | Z29: =J29-O29 -> 4111.49 | AA29: =J29 -> 245000 | AB29: =SUM(Y29:AA29) -> 249111.49 | AD29: =J29*2 -> 490000 | AE29: =O29-AD29 -> -249111.49 | AG29: =(SUM(J29:K29)*2)-O29 -> 249111.49
A30: Restaurante ISM EIRELI (diretoria RU) - Ação 20RK planilha DRU | B30: Contrato DAC/RU | C30: VGM01N01B5N | D30: 04228626001263 | E30: 23106.013653/2020-28 | F30: 46274 | G30: =IF((F30-TODAY())<0,"EXPIRADO", IF((F30-TODAY())<=60,"EM BREVE","NO PRAZO")) -> NO PRAZO | I30: 31/2021 | J30: =L30/12 -> 1500933.6 | L30: 18011203 | M30: 1726196.1 | N30: 0 | O30: =SUM(M30:N30) -> 1726196.1 | U30: ='DRU 25'!J10 -> 1791326.9 | Z30: =1791326.86-O30 -> 65130.77 | AA30: 1506537.9 | AB30: =SUM(Y30:AA30) -> 1571668.7 | AD30: =Y30+Z30 -> 65130.77 | AG30: =(SUM(J30:K30)*2)-O30 -> 1275671
A31: - Serviço manutenção piscinas Casa Niemeyer | B31: Contratos Diversos | C31: VGM01N01N5N | O31: =SUM(M31:N31) -> 0 | AB31: =SUM(Y31:AA31) -> 0 | AG31: =(SUM(J31:K31)*2)-O31 -> 0
A32: - Ajuda de custo (Redistribuição de servidores) | B32: Contratos Diversos | C32: VGH01N0111N | J32: 20000 | L32: =J32*12 -> 240000 | M32: 0 | N32: 0 | O32: =SUM(M32:N32) -> 0 | R32: =J32 -> 20000 | S32: =J32 -> 20000 | T32: =J32 -> 20000 | U32: =J32 -> 20000 | V32: =J32 -> 20000 | W32: =J32 -> 20000 | Z32: =J32 -> 20000 | AA32: =J32 -> 20000 | AB32: =SUM(Y32:AA32) -> 40000 | AG32: =(SUM(J32:K32)*2)-O32 -> 40000
A33: Cespe (despesas diversas) | B33: CESPE | C33: VGR02N01A1N | E33: 23106.019902/2017-93 | J33: 70000 | L33: =J33*12 -> 840000 | M33: 101505.99 | N33: 25585.25 | O33: =SUM(M33:N33) -> 127091.24 | T33: =J33-7000 -> 63000 | U33: =J33 -> 70000 | AA33: =J33*2-N33 -> 114414.75 | AB33: =SUM(Y33:AA33) -> 114414.75 | AD33: =J33*2 -> 140000 | AE33: =O33-AD33-N33 -> -38494.01
A34: CEBRASPE (Processos seletivos UnB) | B34: DEG | C34: VGM01N01J5N | D34: 18284407000153 | E34: 23106.098851/2020-53 23106.018871/2022-11 23106.093468/2021-90 23106.065413/2023-51 23106.065557/2023-16 23106.035963/2024-27 | F34: 46734 | G34: =IF((F34-TODAY())<0,"EXPIRADO", IF((F34-TODAY())<=60,"EM BREVE","NO PRAZO")) -> NO PRAZO | I34: diversos | J34: 280000 | L34: =J34*12 -> 3360000 | M34: 42971.08 | N34: 320755.17 | O34: =SUM(M34:N34) -> 363726.25 | AA34: =J34*2-O34 -> 196273.75 | AB34: =SUM(Y34:AA34) -> 196273.75 | AD34: =J34*2 -> 560000
A35: - SIMPRESS - Outsourcing de serviços de impressão | B35: Contratos custeados pelas Unidades (STI) | C35: VGM01N01M8N | D35: 07432517000107 | E35: 23106.000978/2016-64 23106.010988/2019-51 | F35: 46022 | G35: =IF((F35-TODAY())<0,"EXPIRADO", IF((F35-TODAY())<=60,"EM BREVE","NO PRAZO")) -> EM BREVE | I35: 512/2021 | J35: =62000*104.4% -> 64728 | L35: =J35*12 -> 776736 | M35: 33015.44 | N35: 0 | O35: =SUM(M35:N35) -> 33015.44 | Z35: =J35-O35 -> 31712.56 | AA35: =J35 -> 64728 | AB35: =SUM(Y35:AA35) -> 96440.56 | AD35: =J35*2 -> 129456 | AF35: -60500.4 | AG35: =(SUM(J35:K35)*2)-O35 -> 96440.56
AG36: =(SUM(J36:K36)*3)-O36 -> 0
A37: Total da despesa | J37: =SUM(J4:J35) -> 7889166.5 | K37: =SUM(K4:K35) -> 5972816.8 | L37: =SUM(L4:L35) -> 1.6946665e+08 | M37: =SUM(M4:M35) -> 12166174 | N37: =SUM(N4:N35) -> 347107.9 | O37: =SUM(O4:O35) -> 12513282 | P37: =SUM(P4:P35) -> 0 | Q37: =SUM(Q4:Q35) -> 0 | ... AB37: =SUM(AB4:AB35) -> 14126822 | AD37: =SUM(AD4:AD35) -> 24137703 | AE37: =SUM(AE4:AE35) -> -992285.08 | AF37: =SUM(AF4:AF35) -> -7975661.7 | AG37: =SUM(AG4:AG35) -> 11348009
AF39: =AF20 -> -1924342.1
AF40: -6000000
AF41: -1280820.9
AF43: =SUM(AF39:AF40) -> -7924342.1
AF44: =AF43+#REF! -> #REF!

Sheet Bolsas
A2: Descrição das despesas | B2: Prioridade | C2: PI 2024 | D2: Saldo Empenhos 2024 | E2: Saldo de Empenhos RAP
A3: Auxílio financeiro a estudantes - DEX | C3: VXX01N21C3N | D3: 282726.47 | E3: 59839
A4: Auxílio financeiro a estudantes - DEX | C4: VGY01N0106N | D4: 316300
A5: Auxílio financeiro a estudantes - DEG | C5: MEG01G55B8N | D5: 58250 | E5: 0
A6: Auxílio financeiro a estudantes - DEG | C6: VGY01N0106N | D6: 168955.15 | E6: 48690.66
A7: Auxílio financeiro a estudantes - DPI | C7: MEG01G55B9N | E7: 61000
A8: Auxílio financeiro a estudantes - DPI | C8: VGY01N0106N
A9: Auxílio financeiro a estudantes - DPG | C9: OEP01O55A4N | E9: 392100
A10: Auxílio financeiro a estudantes - DPG | C10: VGY01N0106N | D10: 2100 | E10: 794.54
A11: AUXILIO SOCIOECONOMICO - DAC | C11: MGU01N23A1N
A12: BOLSA INCLUSAO DIGITAL - DAC | C12: MGU01N23B4N | E12: 102850
A13: - Bolsas PIBIC (DPG) - faz parte do PROIC | C13: NEG01G19A5N NEG03G19A5N
A14: - Bolsas PROIC (DPG) | C14: NQQ01G20A1N | D14: 252700
A15: - Bolsa estudante de graduação CEAD | C15: MEG01G19B5N | E15: 122246.09
A16: - Bolsa estudante de pós-graduação CEAD | C16: MEG01G19B5N
A17: - Auxílio financeiro a professor CEAD | C17: MEG01G19B5N
A18: Bolsas de Extensão (DEX) | C18: VGM01N01M3N
A19: - Bolsas concedidas pela CAPES | C19: OGP01O19A1N
A20: - Auxílio Financeiro a Pesquisador (DPI) | C20: NQQ01N55C5N | D20: 1018895.1 | E20: 973046.26
A21: Auxílio Financeiro a Pesquisador (DEG) | C21: NQQ01N55C5N VGY01N0106N
A22: - Auxílio Financeiro a Pesquisador (DEX) | C22: VXX01N21C2N VGY01N0106N
A23: - Auxílio Financeiro a Pesquisador (DPI) | C23: VGY01N0106N
A24: - Auxílio Financeiro a Pesquisador (DPG) | C24: VGY01N0106N

Sheet Estudo de Crédito
A1: Acompanhamento de Contratos*
A2: Data de Atualização: 14/10/2025
A3: Descrição das despesas | B3: UGR | C3: Prioridade | D3: PI 2025 | E3: CNPJ | F3: Processo | G3: Vigência | H3: Status do Contrato | I3: Situação da prorrogação | J3: nº Contrato | K3: Valor Contrato Média mensal | L3: Valor Cont Continuado Mensal | M3: Total estimado Anual | N3: Saldo Empenhos 2025 | O3: Saldo de Empenhos RAP | P3: Total RAP + Empenho | Q3: 45658 | R3: 45689 | S3: 45717 | T3: 45748 | U3: 45778 | V3: 45809 | W3: 45839 | X3: 45870 | Y3: 45901 | Z3: 45931 | AA3: 45962 | AB3: 45992 | AC3: Credito em Excesso
A4: - Estagiários UnB (novo PI - estagiários) | B4: DGP/ folha | C4: 1 | D4: VGM01N01N2N | K4: 161000 | M4: =K4*12 -> 1932000 | N4: 788950.31 | O4: 20575.19 | P4: =SUM(N4:O4) -> 809525.5 | AC4: =P4-(3*K4) -> 326525.5
A5: Estagiários - auxílio transporte | B5: DGP/ folha | C5: 1 | D5: VGM01N01N7N | K5: 36375 | N5: 234275.33 | O5: 7160.7 | P5: =SUM(N5:O5) -> 241436.03 | AC5: =P5-(3*K5) -> 132311.03
A6: SANEAGO - Água e esgoto UnB Cerrado (corrigir a média) | B6: UnB Cerrado | C6: 3 | D6: VGM01N01I3N | E6: 01616929000102 | K6: 333 | M6: =K6*12 -> 3996 | N6: 999 | O6: 1332 | P6: =SUM(N6:O6) -> 2331 | X6: 333 | AC6: 999 | AF6: =P6-AE6 -> 2331
A7: Energia Elétrica UnB Cerrado - CONTRATO CCER - ENEL N. 36/2020 e CELG DISTRIBUIÇÃO S.A - CELG D, Equatorial Goiás Distribuidora de Energia S/A | B7: UnB Cerrado | C7: 3 | D7: VGM01N01I2N | E7: 1543032000104 | F7: 23106.044802/2020-09 23106.083937/2023-24 | J7: 36/2020 | K7: 1585.03 | M7: =K7*12 -> 19020.36 | N7: =3635.35+1573.77 -> 5209.12 | O7: 145.87 | P7: =SUM(N7:O7) -> 5354.99 | V7: =K7-324 -> 1261.03 | X7: =1585-1230 -> 355 | AC7: =P7-(3*K7) -> 599.9 | AE7: =SUM(K7:L7)*2 -> 3170.06 | AF7: =P7-AE7 -> 2184.93 | AH7: =(SUM(K7:L7)*2)-P7 -> -2184.93
A8: Inframérica - Agenciamento de Carga Internacional (conforme demanda) | B8: Contratos DCO | C8: 2 | D8: VGM01N01L3N | E8: 15559082000186 | F8: 23106.011.137/2014-11 23106.086385/2019-20 | G8: 45743 | H8: =IF((G8-TODAY())<0,"EXPIRADO", IF((G8-TODAY())<=60,"EM BREVE","NO PRAZO")) -> EXPIRADO | J8: 026/2020 | N8: 0 | O8: 0 | P8: =SUM(N8:O8) -> 0 | AC8: =SUM(Z8:AB8) -> 0 | AE8: =SUM(K8:L8)*2 -> 0 | AF8: =P8-AE8 -> 0
A9: Inframérica - prestação de serviços de armazenagem e capatazia de cargas importadas (conforme demanda) | B9: Contratos DCO | D9: VGM01N01L3N | E9: 15.559.082/0001-86 | F9: 23106.010064/2025-01 | G9: 47682 | H9: =IF((G9-TODAY())<0,"EXPIRADO", IF((G9-TODAY())<=60,"EM BREVE","NO PRAZO")) -> NO PRAZO | J9: 1203/2025 | K9: 4000 | M9: =K9*12 -> 48000 | N9: 42484.67 | P9: =SUM(N9:O9) -> 42484.67 | AC9: =P9-(3*K9) -> 30484.67
A10: NK LOGISTICA E TRANSPORTES LTDA (serviços de transporte de cargas por via aérea) | B10: Contratos DCO | C10: 2 | D10: VGM01N01P2N | E10: 32270711000172 | F10: 23106.068904/2022-73 | G10: 45989 | H10: =IF((G10-TODAY())<0,"EXPIRADO", IF((G10-TODAY())<=60,"EM BREVE","NO PRAZO")) -> EM BREVE | I10: em renovação | J10: 130/2022 | K10: 500 | M10: =K10*12 -> 6000 | O10: 57249.08 | P10: =SUM(N10:O10) -> 57249.08
A11: - Seguro de aluno/ estagiário (MBM Seguradora S.A) | B11: Contratos DCO | C11: 1 | D11: VGM01N01N7N | E11: 87883807000106 | F11: 23106.085902/2019-43 | G11: 46086 | H11: =IF((G11-TODAY())<0,"EXPIRADO", IF((G11-TODAY())<=60,"EM BREVE","NO PRAZO")) -> NO PRAZO | J11: 024/2020 | K11: 3870 | M11: 48000 | N11: 22306.96 | O11: 0 | P11: =SUM(N11:O11) -> 22306.96 | AC11: =P11-(3*K11) -> 10696.96 | AE11: =SUM(K11:L11)*2 -> 7740
A12: PRIME EXTINTORES EIRELI – ME – recarga de extintores | B12: PRC | C12: 2 | D12: VGM01N01I6N | E12: 09.098.197/0001-18 | F12: 23106.101317/2023-84 | G12: 46137 | H12: =IF((G12-TODAY())<0,"EXPIRADO", IF((G12-TODAY())<=60,"EM BREVE","NO PRAZO")) -> NO PRAZO | J12: 618/2024 | K12: 10000 | M12: 187401.54 | N12: 100 | O12: 38595.64 | P12: =SUM(N12:O12) -> 38695.64 | AC12: 100 | AE12: =SUM(K12:L12)*2 -> 20000 | AF12: =P12-AE12 -> 18695.64
A13: - Fornecimento de combustível (Novo fornecer para 2019 - Ticket soluções HDFGT S/A) (NÃO DEVE SER ANULADO) | B13: PRC | C13: 3 | D13: VGM01N01I5N | E13: 3506307000157 | F13: 23106.116807/2021-13 | G13: 46270 | H13: =IF((G13-TODAY())<0,"EXPIRADO", IF((G13-TODAY())<=60,"EM BREVE","NO PRAZO")) -> NO PRAZO | I13: em renovação | J13: 1222/2022 | K13: 80000 | M13: =K13*12 -> 960000 | N13: 380000.32 | O13: 0 | P13: =SUM(N13:O13) -> 380000.32 | X13: =80000-12226 -> 67774 | AC13: =P13-(3*K13) -> 140000.32 | AE13: =SUM(K13:L13)*2 -> 160000 | AG13: =P13-AE13 -> 220000.32
A14: - Taxigov (demanda) - VIP service | B14: PRC | C14: 3 | D14: VGM01N01A4N | E14: 02605452000122 | F14: 23106.010532/2020-24 | G14: 46094 | H14: =IF((G14-TODAY())<0,"EXPIRADO", IF((G14-TODAY())<=60,"EM BREVE","NO PRAZO")) -> NO PRAZO | J14: 036/2020 | K14: 6000 | M14: =K14*12 -> 72000 | N14: 18000.52 | O14: 0 | P14: =SUM(N14:O14) -> 18000.52 | AC14: =P14-(3*K14) -> 0.52 | AE14: =SUM(K14:L14)*2 -> 12000 | AG14: -2000
A15: ELYON BRASIL - ESPLANADA SERVICOS TERCEIRIZADOS EIRELI - serviços continuados de pessoal - coletores de resíduos de serviços de saúde | B15: Contratos DCA | C15: 1 | D15: VGM01N01E4N | E15: 01099686000182 | F15: 23106.031888/2020-00 | G15: 46219 | H15: =IF((G15-TODAY())<0,"EXPIRADO", IF((G15-TODAY())<=60,"EM BREVE","NO PRAZO")) -> NO PRAZO | I15: Em fase de prorrogação | J15: 111/2020 | L15: =M15/12 -> 22669.34 | M15: 272032.08 | N15: 87845.52 | O15: 0 | P15: =SUM(N15:O15) -> 87845.52 | U15: =22669-1831.59 -> 20837.41 | X15: =L15-1000 -> 21669.34 | AC15: =P15-(3*L15) -> 19837.5 | AE15: =SUM(K15:L15)*2 -> 45338.68 | AF15: =P15-AE15 -> 42506.84 | AH15: =(SUM(K15:L15)*2)-P15 -> -42506.84
A16: - ALFA E OMEGA Apoio Técnico EDU | B16: Contratos DCA | C16: 1 | D16: VGM01N01D5N | E16: 16650774000106 | F16: 23106.011967/2019-52 | G16: 46131 | H16: =IF((G16-TODAY())<0,"EXPIRADO", IF((G16-TODAY())<=60,"EM BREVE","NO PRAZO")) -> NO PRAZO | J16: 022/2021 | L16: =M16/12 -> 24316.78 | M16: 291801.36 | N16: 100930.13 | O16: 0 | P16: =SUM(N16:O16) -> 100930.13 | S16: 865.66 | T16: =L16-2497 -> 21819.78 | U16: =L16-22360 -> 1956.78 | V16: =L16 -> 24316.78 | AC16: =P16-(3*L16) -> 27979.79 | AE16: =SUM(K16:L16)*2 -> 48633.56 | AF16: =P16-AE16 -> 52296.57 | AH16: =(SUM(K16:L16)*2)-P16 -> -52296.57
A17: Phoenix Comércio e Serviços de Limpeza LTDA - Almoxarifado e de transporte interno de móveis e materiais | B17: Contratos DCA | C17: 1 | D17: VGM01N01F7N | E17: 12978051000171 | F17: 23106.001099/2022-06 | G17: 46267 | H17: =IF((G17-TODAY())<0,"EXPIRADO", IF((G17-TODAY())<=60,"EM BREVE","NO PRAZO")) -> NO PRAZO | J17: 111/2022 | L17: 116248.37 | M17: =L17*12 -> 1394980.4 | N17: 509265.92 | O17: 0 | P17: =SUM(N17:O17) -> 509265.92 | T17: =117871-49371 -> 68500 | U17: =L17-P17 -> -393017.55 | V17: =L17 -> 116248.37 | AC17: =P17-(3*L17) -> 160520.81 | AE17: =SUM(K17:L17)*2 -> 232496.74 | AG17: -212997.86 | AH17: =(SUM(K17:L17)*2)-P17 -> -276769.18
A18: RB GRÁFICA DIGITAL LTDA | B18: Contratos DCA | C18: 2 | D18: VGM01N01Q1N | E18: 16.951.665/0001-10 | F18: 23106.041918/2022-40 | G18: 46266 | H18: =IF((G18-TODAY())<0,"EXPIRADO", IF((G18-TODAY())<=60,"EM BREVE","NO PRAZO")) -> NO PRAZO | J18: 104/2023 | K18: 100 | M18: =K18*12 -> 1200 | N18: 1200 | O18: 139 | P18: =SUM(N18:O18) -> 1339 | S18: =K18 -> 100 | AC18: =P18-(3*K18) -> 1039 | AE18: =SUM(K18:L18)*2 -> 200 | AH18: =(SUM(K18:L18)*2)-P18 -> -1139
A19: Contrato de Limpeza - UnB Cerrado (AP PISCINAS EIRELI) | B19: UnB Cerrado | C19: 1 | D19: VGM01N01A7N (VGM01N1F2N-PI indevido) | E19: 08475822000130 | F19: 23106.116355/2019-55 | G19: 46254 | H19: =IF((G19-TODAY())<0,"EXPIRADO", IF((G19-TODAY())<=60,"EM BREVE","NO PRAZO")) -> NO PRAZO | J19: 112/2020 | L19: 5954.2 | M19: 63975.84 | N19: 22887.42 | O19: 0 | P19: =SUM(N19:O19) -> 22887.42 | S19: =L19-P19 -> -16933.22 | T19: =L19-4688 -> 1266.2 | V19: =5331-P19 -> -17556.42 | W19: =L19-4396 -> 1558.2 | X19: =L19 -> 5954.2 | AC19: =P19-(3*L19) -> 5024.82 | AE19: =SUM(K19:L19)*2 -> 11908.4 | AG19: -643.35 | AH19: =(SUM(K19:L19)*2)-P19 -> -10979.02
A20: Recepcionista – AMR LIMPEZA E LOCACAO DE AUTOMOVEIS LTDA | B20: UnB Cerrado | C20: 1 | D20: VGM01N01B3N | E20: 10.258.826/0001-09 | F20: 23106.100112/2023-81 | G20: 46068 | H20: =IF((G20-TODAY())<0,"EXPIRADO", IF((G20-TODAY())<=60,"EM BREVE","NO PRAZO")) -> NO PRAZO | J20: 12/2024 | L20: =M20/12 -> 4290.91 | M20: 51490.92 | N20: =30036.37+4537.93 -> 34574.3 | O20: 0 | P20: =SUM(N20:O20) -> 34574.3 | V20: =L20 -> 4290.91 | AC20: =P20-(3*L20) -> 21701.57 | AE20: =SUM(K20:L20)*2 -> 8581.82 | AF20: =P20-AE20 -> 25992.48 | AH20: =(SUM(K20:L20)*2)-P20 -> -25992.48
A21: ONE ELEVADORES DF LTDA | B21: Contratos SPI | C21: 2 | D21: VGM01N01I7N | E21: 02.633.335/0001-72 | F21: 23106.077388/2024-30 | G21: 47436 | H21: =IF((G21-TODAY())<0,"EXPIRADO", IF((G21-TODAY())<=60,"EM BREVE","NO PRAZO")) -> NO PRAZO | J21: 94/2024 | K21: =M21/12 -> 339678 | M21: =20380680/5 -> 4076136 | O21: 2995835 | P21: =SUM(N21:O21) -> 2995835
A22: - ENERGIA ELÉTRICA - SPI | B22: Contratos SPI | C22: 3 | D22: VGM01N01I2N | E22: 07522669000192 | K22: 40000 | M22: =K22*12 -> 480000 | N22: 121270.9 | O22: 2965.4 | P22: =SUM(N22:O22) -> 124236.3 | T22: =40000-12743 -> 27257 | V22: =K22-23261 -> 16739 | AC22: =P22-(3*K22) -> 4236.3 | AE22: =K22*2 -> 80000 | AF22: =P22-AE22 -> 44236.3 | AH22: =(SUM(K22:L22)*2)-P22 -> -44236.3
A23: PGFN: 2° ATI, negociação conta n°: 8815031 (Consulta Acordo n°2 - Conta da Negociação 8815031 (SEI nº 10576277)) SEI origem: 23106.059565/2023-15 SEI pagamento 2023:23106.123083/2023-26 que foi realizado o pagamento da entrada e no 23106.128684/2023-25 constará os demais pagamentos. Despacho que contém explicação: 10567234 do SEI 23106.132563/2023-88 Guias de Recolhimento de FGTS e Informações à Previdência Social (GFIP) das competências de janeiro/2011, fevereiro/2011, abril/2011, junho/2011 e novembro/2011 Empenho atual: 2023NE003705; 2024NE000487 | B23: Contratos Diversos | C23: 2 | D23: VGH01N0112N | F23: 23106.059565/2023-15 23106.128684/2023-25 23106.044758/2024-52 23106.132563/2023-88 | G23: 60 parcelas (já pagou 10/60) | K23: 28500 | M23: =K23*12 -> 342000 | N23: =89029.91+28500 -> 117529.91 | O23: 0 | P23: =SUM(N23:O23) -> 117529.91 | V23: =28500-24893 -> 3607 | AH23: =(SUM(K23:L23)*2)-P23 -> -60529.91
A24: RFB: Conta da Negociação 0211000120 (Consulta Parcelamento n°1 - Conta da Negociação 0211000120 (SEI nº 10580261)) SEI origem: 23106.059634/2023-91 SEI pagamento em 2023: 23106.087581/2023-06 Despacho que contém explicação: 10567234 do SEI 23106.132563/2023-88 Atraso das Guias de Recolhimento de FGTS e Informações à Previdência Social (GFIP) das competências de julho/2010, outubro/2010, novembro/2010, dezembro/2011 e 13°/2011 Empenho atual: 2023NE003850 e 2024NE000284 | B24: Contratos Diversos | C24: 2 | D24: VGH01N0112N | F24: 23106.059634/2023-91 23106.087581/2023-06 23106.044758/2024-52 23106.132563/2023-88 | G24: 60 parcelas (já pagou 13/60) | K24: 22500 | M24: =K24*12 -> 270000 | N24: =45348.61+95199.17 -> 140547.78 | O24: 0 | P24: =SUM(N24:O24) -> 140547.78 | AH24: =(SUM(K24:L24)*2)-P24 -> -95547.78
A25: Contrato de serviços especializados com vistas à realização de estudos técnicos, de planejamentos, projetos básicos ou executivos, assessoria técnica e apoio técnico nas áreas de Tecnologia da Informação (TI) e Logística, entre a UnB e o CEBRASPE | B25: DEG | C25: 3 | D25: VGR02N01A2N | E25: 18284407000153 | F25: 23106.040707/2022-90 (60 parcelas) | G25: 46441 | H25: =IF((G25-TODAY())<0,"EXPIRADO", IF((G25-TODAY())<=60,"EM BREVE","NO PRAZO")) -> NO PRAZO | J25: 1205/2022 | K25: 44033.82 | M25: =K25*12 -> 528405.84 | N25: 496006.57 | O25: 0 | P25: =SUM(N25:O25) -> 496006.57 | AE25: =K25*2 -> 88067.64 | AG25: -88067.64 | AH25: =(SUM(K25:L25)*2)-P25 -> -407938.93
A26: Tratador de Piscinas CO e casa Oscar Niemayer - (AP Piscinas EIRELI) - em fase de renovação | B26: Contratos Diversos | C26: 1 | D26: VGM01N01E2N | E26: 08475822000130 | F26: 23106.013349/2019-47 | G26: 45844 | H26: =IF((G26-TODAY())<0,"EXPIRADO", IF((G26-TODAY())<=60,"EM BREVE","NO PRAZO")) -> EXPIRADO | I26: não será renovado | J26: 93/2020 | L26: =M26/12 -> 5039.3475 | M26: 60472.17 | N26: 23684.51 | O26: 0 | P26: =SUM(N26:O26) -> 23684.51 | U26: =L26-166.38 -> 4872.9675 | V26: =L26 -> 5039.3475 | X26: =L26-1512 -> 3527.3475 | AC26: =P26-(3*L26) -> 8566.4675 | AE26: =L26*2 -> 10078.695 | AH26: =(SUM(K26:L26)*2)-P26 -> -13605.815
A27: - Correios - ECT -reduziu porque não temos mais contrato de encomendas | B27: Comunicação | C27: 2 | D27: VGM01N01J1N | E27: 34028316000707 | F27: 23106.137850/2017-36; 23106.070712/2018-41 23106.015565/2023-11 | G27: 46792 | H27: =IF((G27-TODAY())<0,"EXPIRADO", IF((G27-TODAY())<=60,"EM BREVE","NO PRAZO")) -> NO PRAZO | J27: 1207/2023 | K27: 3000 | M27: =K27*12 -> 36000 | N27: 12275.32 | O27: 0 | P27: =SUM(N27:O27) -> 12275.32 | AC27: =P27-(3*K27) -> 3275.32 | AE27: =K27*2 -> 6000 | AG27: -642 | AH27: =(SUM(K27:L27)*2)-P27 -> -6275.32
A28: - Empresa Brasil de Comunicação (EBC) | B28: Comunicação | C28: 2 | D28: VGM01N01I9N | F28: 23106.048294/2020-20 | G28: 46001 | H28: =IF((G28-TODAY())<0,"EXPIRADO", IF((G28-TODAY())<=60,"EM BREVE","NO PRAZO")) -> EM BREVE | J28: 213/2020 | K28: 2000 | M28: =K28*12 -> 24000 | N28: 6307.04 | O28: 0 | P28: =SUM(N28:O28) -> 6307.04 | U28: =K28-307 -> 1693 | AC28: =P28-(3*K28) -> 307.04 | AE28: =K28*2 -> 4000 | AF28: =P28-AE28 -> 2307.04 | AH28: =(SUM(K28:L28)*2)-P28 -> -2307.04
A29: Lavanderia Cristal Serviços Expressos Ltda (higienização e passadoria de becas) | B29: Cerimonial | C29: 3 | D29: VGM01N01B9N | E29: 01319181000186 | F29: 23106.001918/2023-98 | G29: 46136 | H29: =IF((G29-TODAY())<0,"EXPIRADO", IF((G29-TODAY())<=60,"EM BREVE","NO PRAZO")) -> NO PRAZO | J29: Dispensa. Nº 10002/2023 | K29: 500 | M29: =K29*12 -> 6000 | N29: 13933.9 | O29: 548.5 | P29: =SUM(N29:O29) -> 14482.4 | AC29: =P29-(3*K29) -> 12982.4 | AE29: =K29*2 -> 1000 | AF29: =P29-AE29-O29 -> 12933.9
AH30: =(SUM(K30:L30)*3)-P30 -> 0
A31: Total da despesa | K31: =SUM(K4:K29) -> 783974.85 | L31: =SUM(L4:L29) -> 178518.95 | M31: =SUM(M4:M29) -> 11174913 | N31: =SUM(N4:N29) -> 3180585.4 | O31: =SUM(O4:O29) -> 3124546.4 | P31: =SUM(P4:P29) -> 6305131.8 | Q31: =SUM(Q4:Q29) -> 0 | R31: =SUM(R4:R29) -> 0 | ... AC31: =SUM(AC4:AC29) -> 907188.92 | AE31: =SUM(AE4:AE29) -> 739215.59 | AF31: =SUM(AF4:AF29) -> 203484.7 | AG31: =SUM(AG4:AG29) -> -84350.53 | AH31: =SUM(AH4:AH29) -> -1042309.1
AG33: =#REF! -> #REF!
AG34: -6000000
AG35: -1280820.9
AG37: =SUM(AG33:AG34) -> #REF!
AG38: =AG37+#REF! -> #REF!

Sheet Prog-09.10
A1: Programação de Despesas
A2: Data de Atualização: 09/10/2025
A3: Descrição das despesas | B3: UGR | C3: Prioridade | D3: PI 2025 | E3: CNPJ | F3: nº Contrato | G3: 45931 | H3: 45962 | I3: 45992 | J3: Total necessário
A4: Pasep - HUB | B4: HUB | C4: 1 | D4: VGM01N01N1N | I4: 35300.26 | J4: =SUM(G4:I4) -> 35300.26
A5: Pasep - UnB | B5: DGP/ folha | C5: 1 | D5: VGM01N01N1N | H5: 186771.65 | I5: 810000 | J5: =SUM(G5:I5) -> 996771.65
A6: OI SA recuperação judicial | B6: STI | C6: 3 | D6: VGM01N01I4N | E6: 76535764000143 | F6: 515/2021 | G6: 4223.61 | H6: 60000 | I6: 60000 | J6: =SUM(G6:I6) -> 124223.61
A7: WEGH Assessoria e Logística Internacional Ltda, Agenciamento de Transportes de Cargas Internacionais WeghLogística | B7: Contratos DCO | C7: 2 | D7: VGM01N01L3N | E7: 65494742000166 | F7: 142/2023 | G7: 2427.07 | H7: 4000 | I7: 4000 | J7: =SUM(G7:I7) -> 10427.07
A8: VILELA SERVIÇO DE PAISAGISMO, PARQUES E JARDINS LTDA (jardinagem) | B8: PRC | C8: 2 | D8: VGM01N01A5N | E8: 32.751.565/0001-05 | F8: 1217/2023 | H8: 286247.78 | I8: 298000 | J8: =SUM(G8:I8) -> 584247.78
A9: - TRANSMONICI TRANSPORTE E TURISMO (ônibus rodoviário executivo) | B9: PRC | C9: 2 | D9: VGM01N01K1N | E9: 09169349000126 | F9: 604/2022 | G9: 84327.88 | H9: 90000 | I9: 90000 | J9: =G9+H9+I9 -> 264327.88
A10: Tafa Engenharia (serviços continuados de manutenção preventiva e corretiva de equipamentos e sistemas de ar condicionado, com fornecimento de peças e materiais) | B10: PRC | C10: 2 | D10: VGM01N01F1N | E10: 12859652000165 | F10: 616/2024 | H10: 66316.59 | I10: 95000 | J10: =SUM(G10:I10) -> 161316.59
A11: 3P HGM solução visual (serviços de comunicação visual) | B11: PRC | C11: 2 | D11: VGM01N01O7N | E11: 34.998.513/0001-55 | F11: 1217/2022 | H11: 5228.16 | I11: 231000 | J11: =SUM(G11:I11) -> 236228.16
A12: ARTES GRÁFICA COMÉRCIO E REPRESENTAÇÕES EIRELI (serviços continuados de Designer Gráfico) | B12: Contratos DCA | C12: 2 | D12: VGM01N01P4N | E12: 05606994000108 | F12: 147/2022 | H12: 12640.77 | I12: 12640.77 | J12: =SUM(G12:I12) -> 25281.54
A13: OBJETIVA SERVIÇOS TERCEIRIZADOS LTDA - copeiragem | B13: Contratos DCA | D13: VGM01N01O2N | E13: 10.874.523/0001-10 | F13: 24/2025 | G13: 62.11 | H13: 155277.21 | I13: 155277.21 | J13: =SUM(G13:I13) -> 310616.53
A14: OBJETIVA SERVIÇOS TERCEIRIZADOS LTDA - contínuo | B14: Contratos DCA | D14: VGM01N01B7N | E14: 10.874.523/0001-10 | F14: 23/2025 | G14: 165.8 | H14: 258893.8 | I14: 258893.8 | J14: =SUM(G14:I14) -> 517953.4
A15: - RCA (Limpeza e Conservação) | B15: Contratos DCA | C15: 1 | D15: VGM01N01A7N | E15: 69.207.850/0001-61 | F15: 02/2022 | H15: 439664.48 | I15: 1918496.1 | J15: =SUM(G15:I15) -> 2358160.6
A16: Life Defense (Segurança) | B16: Contratos DCA | C16: 1 | D16: VGM01N01A8N | E16: 02674687000176 | F16: 011/2020 | H16: 117878.29 | I16: 1617878.6 | J16: =SUM(G16:I16) -> 1735756.9
A17: G&E SERVICOS TERCEIRIZADOS LTDA (PORTARIA) | B17: Contratos DCA | C17: 1 | D17: VGM01N01A9N | E17: 08744139000151 | F17: 081/2022 | G17: 169805.09 | H17: 1412211.2 | J17: =SUM(G17:I17) -> 1582016.3
A18: G&E SERVICOS TERCEIRIZADOS LTDA - serviços continuados de motorista | B18: Contratos DCA | C18: 1 | D18: VGM01N01P5N | E18: 08744139000151 | F18: 001/2023 | H18: 183319.96 | I18: 236438.33 | J18: =SUM(G18:I18) -> 419758.29
A19: MPE ENGENHARIA E SERVICOS S/A (serviços comuns de engenharia, incluindo manutenção, conservação, adaptação, reparação e instalação de infraestruturas prediais e imobiliárias) - (exceto DAC) | B19: Contratos DCA | C19: 2 | D19: VGM01N01H3N | E19: 04743858000105 | F19: 1201/2023 | G19: 1828046.2 | H19: 1998000 | I19: 1998000 | J19: =SUM(G19:I19) -> 5824046.2
A20: POLI ENGENHARIA LTDA (serviços comuns de engenharia, incluindo manutenção, conservação, adaptação, reparação e instalação de infraestruturas prediais e imobiliárias) - contrato 20 meses | B20: Contratos DCA | C20: 2 | D20: VGM01N01H3N | E20: 00700518000138 | F20: 1226/2022 | G20: 102000 | H20: 102000 | I20: 102000 | J20: =SUM(G20:I20) -> 306000
A21: Ágil (Serviços Agropecuários) | B21: Contratos DCA | C21: 1 | D21: VGM01N01C5N | E21: 72620735000129 | F21: 25/2020 | H21: 458615.91 | I21: 458615.91 | J21: =SUM(G21:I21) -> 917231.82
A22: '- GESTOR SERVICOS EMPRESARIAIS (Portaria - SPI) | B22: Contratos SPI | C22: 1 | D22: VGM01N01E8N | E22: 02.685.728/0001-20 | F22: 001/2022 | H22: 376555.8 | I22: 382896.8 | J22: =SUM(G22:I22) -> 759452.6
A23: - SEFIX (Limpeza e Conservação - SPI) | B23: Contratos SPI | C23: 1 | D23: VGM01N01E9N | E23: 13258899000199 | F23: 033/2022 | H23: 193823.77 | I23: 193823.77 | J23: =SUM(G23:I23) -> 387647.54
A24: Engemega - (Manutenção de Imóveis gerenciados pela Secretaria de Patrimônio Imobiliário (SPI)) – contrato 1 (contrato antigo) | B24: Contratos SPI | C24: 2 | D24: VGM01N01D4N | E24: 33480104/0001-08 | F24: 1223/2022 | H24: 158335.89 | I24: 309551 | J24: =SUM(G24:I24) -> 467886.89
A25: QUANTUM SOLUÇÕES E INOVAÇÕES LTDA - emissão de laudos técnicos de avaliação de valores imobiliários | B25: Contratos SPI | C25: 2 | D25: VGM01N01Q7N | E25: 43.946.228/0001-81 | F25: 1221/2024 | G25: 1241.6667 | H25: 1241.6667 | I25: 1241.6667 | J25: =SUM(G25:I25) -> 3725
A26: - CAESB - SPI | B26: Contratos SPI | C26: 3 | D26: VGM01N01I3N | E26: 00082024000137 | G26: 10619.33 | H26: 136350 | I26: 136350 | J26: =SUM(G26:I26) -> 283319.33
A27: - Despesas de Condomínio | B27: Contratos SPI | C27: 1 | D27: VGM01N01K6N | G27: 231718.41 | H27: 245000 | I27: 245000 | J27: =SUM(G27:I27) -> 721718.41
A28: Restaurante ISM EIRELI (diretoria RU) - Ação 20RK planilha DRU | B28: Contrato DAC/RU | C28: 1 | D28: VGM01N01B5N | E28: 04228626001263 | F28: 31/2021 | G28: 1669256 | H28: 1791326.9 | J28: =SUM(G28:I28) -> 3460582.8
A29: PGFN: 1° ATI, negociação conta n°: 7300348 ( Consulta Acordo n°1 - Conta da Negociação 7300348 (SEI nº 10575553) SEI origem: 23106.094258/2021-19 SEI pagamento em 2023: 23106.005996/2023-61 Despacho que contém explicação: 10567234 do SEI 23106.132563/2023-88 Acordo de Transação Individual (ATI), referente à dívida ativa tributária junto à PGFN -débitos previdenciários Empenho atual: 2024NE000285 | B29: Contratos Diversos | C29: 2 | D29: VGH01N0112N | G29: ='I. Situação Atual'!Y74 -> 0 | H29: ='I. Situação Atual'!Z74 -> 0 | I29: ='I. Situação Atual'!AA74 -> 0 | J29: =SUM(G29:I29) -> 0
A30: CONCEIÇÃO Aparecida Braga 67186920691 ME (análise e levantamento de conjuntos documentais do arquivo do Cespe/UnB) | B30: Contratos Diversos | C30: 1 | D30: VGM01N01P1N | E30: 41423145000182 | F30: 1230/2022 | H30: 4082.45 | I30: 17000 | J30: =SUM(G30:I30) -> 21082.45
A31: Total da despesa | G31: =SUM(G4:G30) -> 4103893.2 | H31: =SUM(H4:H30) -> 8743782.3 | I31: =SUM(I4:I30) -> 9667404.2 | J31: =SUM(J4:J30) -> 22515080
A34: Descrição das despesas | B34: UGR | C34: Prioridade | D34: PI 2025 | E34: CNPJ | F34: nº Contrato | G34: 45931 | H34: 45962 | I34: 45992 | J34: Total necessário
A35: Pasep - HUB | B35: HUB | C35: 1 | D35: VGM01N01N1N | I35: 35300.26 | J35: =SUM(G35:I35) -> 35300.26
A36: Pasep - UnB | B36: DGP/ folha | C36: 1 | D36: VGM01N01N1N | H36: 186771.65 | I36: 810000 | J36: =SUM(G36:I36) -> 996771.65
A37: OI SA recuperação judicial | B37: STI | C37: 3 | D37: VGM01N01I4N | E37: 76535764000143 | F37: 515/2021 | G37: 4223.61 | H37: 60000 | I37: 60000 | J37: =SUM(G37:I37) -> 124223.61
A38: WEGH Assessoria e Logística Internacional Ltda, Agenciamento de Transportes de Cargas Internacionais WeghLogística | B38: Contratos DCO | C38: 2 | D38: VGM01N01L3N | E38: 65494742000166 | F38: 142/2023 | G38: 2427.07 | H38: 4000 | I38: 4000 | J38: =SUM(G38:I38) -> 10427.07
A39: VILELA SERVIÇO DE PAISAGISMO, PARQUES E JARDINS LTDA (jardinagem) | B39: PRC | C39: 2 | D39: VGM01N01A5N | E39: 32.751.565/0001-05 | F39: 1217/2023 | H39: 286247.78 | I39: 298000 | J39: =SUM(G39:I39) -> 584247.78
A40: - TRANSMONICI TRANSPORTE E TURISMO (ônibus rodoviário executivo) | B40: PRC | C40: 2 | D40: VGM01N01K1N | E40: 09169349000126 | F40: 604/2022 | G40: 84327.88 | H40: 90000 | I40: 90000 | J40: =G40+H40+I40 -> 264327.88
A41: Tafa Engenharia (serviços continuados de manutenção preventiva e corretiva de equipamentos e sistemas de ar condicionado, com fornecimento de peças e materiais) | B41: PRC | C41: 2 | D41: VGM01N01F1N | E41: 12859652000165 | F41: 616/2024 | H41: 66316.59 | I41: 95000 | J41: =SUM(G41:I41) -> 161316.59
A42: 3P HGM solução visual (serviços de comunicação visual) | B42: PRC | C42: 2 | D42: VGM01N01O7N | E42: 34.998.513/0001-55 | F42: 1217/2022 | H42: 5228.16 | I42: 231000 | J42: =SUM(G42:I42) -> 236228.16
A43: ARTES GRÁFICA COMÉRCIO E REPRESENTAÇÕES EIRELI (serviços continuados de Designer Gráfico) | B43: Contratos DCA | C43: 2 | D43: VGM01N01P4N | E43: 05606994000108 | F43: 147/2022 | H43: 12640.77 | I43: 12640.77 | J43: =SUM(G43:I43) -> 25281.54
A44: OBJETIVA SERVIÇOS TERCEIRIZADOS LTDA - copeiragem | B44: Contratos DCA | D44: VGM01N01O2N | E44: 10.874.523/0001-10 | F44: 24/2025 | G44: 62.11 | H44: 155277.21 | I44: 155277.21 | J44: =SUM(G44:I44) -> 310616.53
A45: OBJETIVA SERVIÇOS TERCEIRIZADOS LTDA - contínuo | B45: Contratos DCA | D45: VGM01N01B7N | E45: 10.874.523/0001-10 | F45: 23/2025 | G45: 165.8 | H45: 258893.8 | I45: 258893.8 | J45: =SUM(G45:I45) -> 517953.4
A46: - RCA (Limpeza e Conservação) | B46: Contratos DCA | C46: 1 | D46: VGM01N01A7N | E46: 69.207.850/0001-61 | F46: 02/2022 | H46: 439664.48 | I46: 1918496.1 | J46: =SUM(G46:I46) -> 2358160.6
A47: Life Defense (Segurança) | B47: Contratos DCA | C47: 1 | D47: VGM01N01A8N | E47: 02674687000176 | F47: 011/2020 | H47: 117878.29 | I47: 1617878.6 | J47: =SUM(G47:I47) -> 1735756.9
A48: G&E SERVICOS TERCEIRIZADOS LTDA (PORTARIA) | B48: Contratos DCA | C48: 1 | D48: VGM01N01A9N | E48: 08744139000151 | F48: 081/2022 | G48: 169805.09 | H48: 1412211.2 | J48: =SUM(G48:I48) -> 1582016.3
A49: G&E SERVICOS TERCEIRIZADOS LTDA - serviços continuados de motorista | B49: Contratos DCA | C49: 1 | D49: VGM01N01P5N | E49: 08744139000151 | F49: 001/2023 | H49: 183319.96 | I49: 236438.33 | J49: =SUM(G49:I49) -> 419758.29
A50: Total da despesa | G50: =SUM(G23:G49) -> 6323671.1 | H50: =SUM(H23:H49) -> 14598355 | I50: =SUM(I23:I49) -> 16439288 | J50: =SUM(J35:J49) -> 9362386.6
A53: Descrição das despesas | B53: UGR | C53: Prioridade | D53: PI 2025 | E53: CNPJ | F53: nº Contrato | G53: 45931 | H53: 45962 | I53: 45992 | J53: Total necessário
A54: MPE ENGENHARIA E SERVICOS S/A (serviços comuns de engenharia, incluindo manutenção, conservação, adaptação, reparação e instalação de infraestruturas prediais e imobiliárias) | B54: Contratos DCA | C54: 2 | D54: VGM01N01H3N | E54: 04743858000105 | F54: 1201/2023 | G54: 1828046.2 | H54: 1998000 | I54: 1998000 | J54: =SUM(G54:I54) -> 5824046.2
A55: POLI ENGENHARIA LTDA (serviços comuns de engenharia, incluindo manutenção, conservação, adaptação, reparação e instalação de infraestruturas prediais e imobiliárias) | B55: Contratos DCA | C55: 2 | D55: VGM01N01H3N | E55: 00700518000138 | F55: 1226/2022 | G55: 102000 | H55: 102000 | I55: 102000 | J55: =SUM(G55:I55) -> 306000
A56: Ágil (Serviços Agropecuários) | B56: Contratos DCA | C56: 1 | D56: VGM01N01C5N | E56: 72620735000129 | F56: 25/2020 | H56: 458615.91 | I56: 458615.91 | J56: =SUM(G56:I56) -> 917231.82
A57: '- GESTOR SERVICOS EMPRESARIAIS (Portaria - SPI) | B57: Contratos SPI | C57: 1 | D57: VGM01N01E8N | E57: 02.685.728/0001-20 | F57: 001/2022 | H57: 376555.8 | I57: 382896.8 | J57: =SUM(G57:I57) -> 759452.6
A58: - SEFIX (Limpeza e Conservação - SPI) | B58: Contratos SPI | C58: 1 | D58: VGM01N01E9N | E58: 13258899000199 | F58: 033/2022 | H58: 193823.77 | I58: 193823.77 | J58: =SUM(G58:I58) -> 387647.54
A59: Engemega - (Manutenção de Imóveis gerenciados pela Secretaria de Patrimônio Imobiliário (SPI)) – contrato 1 (contrato antigo) | B59: Contratos SPI | C59: 2 | D59: VGM01N01D4N | E59: 33480104/0001-08 | F59: 1223/2022 | H59: 158335.89 | I59: 309551 | J59: =SUM(G59:I59) -> 467886.89
A60: QUANTUM SOLUÇÕES E INOVAÇÕES LTDA - emissão de laudos técnicos de avaliação de valores imobiliários | B60: Contratos SPI | C60: 2 | D60: VGM01N01Q7N | E60: 43.946.228/0001-81 | F60: 1221/2024 | G60: 1241.6667 | H60: 1241.6667 | I60: 1241.6667 | J60: =SUM(G60:I60) -> 3725
A61: - CAESB - SPI | B61: Contratos SPI | C61: 3 | D61: VGM01N01I3N | E61: 00082024000137 | G61: 10619.33 | H61: 136350 | I61: 136350 | J61: =SUM(G61:I61) -> 283319.33
A62: - Despesas de Condomínio | B62: Contratos SPI | C62: 1 | D62: VGM01N01K6N | G62: 231718.41 | H62: 245000 | I62: 245000 | J62: =SUM(G62:I62) -> 721718.41
A63: Total da despesa | G63: =SUM(G36:G62) -> 8804239.3 | H63: =SUM(H36:H62) -> 21592690 | I63: =SUM(I36:I62) -> 26100384 | J63: =SUM(J54:J62) -> 9671027.8
P66: 14712194
P67: 9796183.1
A68: Descrição das despesas | B68: UGR | C68: Prioridade | D68: PI 2025 | E68: CNPJ | F68: nº Contrato | G68: 45931 | H68: 45962 | I68: 45992 | J68: Total necessário | P68: =P66+P67 -> 24508377
A69: Restaurante ISM EIRELI (diretoria RU) - Ação 20RK planilha DRU | B69: Contrato DAC/RU | C69: 1 | D69: VGM01N01B5N | E69: 04228626001263 | F69: 31/2021 | G69: 1669256 | H69: 1791326.9 | J69: =SUM(G69:I69) -> 3460582.8
A70: PGFN: 1° ATI, negociação conta n°: 7300348 ( Consulta Acordo n°1 - Conta da Negociação 7300348 (SEI nº 10575553) | B70: Contratos Diversos | C70: 2 | D70: VGH01N0112N | G70: ='I. Situação Atual'!Y116 -> 0 | H70: ='I. Situação Atual'!Z116 -> 0 | I70: ='I. Situação Atual'!AA116 -> 0 | J70: =J29 -> 0
A71: CONCEIÇÃO Aparecida Braga 67186920691 ME (análise e levantamento de conjuntos documentais do arquivo do Cespe/UnB) | B71: Contratos Diversos | C71: 1 | D71: VGM01N01P1N | E71: 41423145000182 | F71: 1230/2022 | H71: 4082.45 | I71: 17000 | J71: =SUM(G71:I71) -> 21082.45
A72: Total da despesa | G72: =SUM(G45:G71) -> 19232625 | H72: =SUM(H45:H71) -> 44160269 | I72: =SUM(I45:I71) -> 50507841 | J72: =SUM(J69:J71) -> 3481665.3
J76: =J72+J63+J50 -> 22515080

Sheet Prog-16.09
A1: Acompanhamento de Contratos* | X1: continuados
A2: Data de Atualização: 11/03/2025
A3: Descrição das despesas | B3: UGR | C3: Prioridade | D3: PI 2025 | E3: CNPJ | F3: nº Contrato | G3: Valor Contrato Média mensal | H3: Valor Cont Continuado Mensal | I3: Total estimado Anual | J3: Saldo Empenhos 2025 | K3: Saldo de Empenhos RAP | L3: Total RAP + Empenho | M3: 45658 | N3: 45689 | O3: 45717 | P3: 45748 | Q3: 45778 | R3: 45809 | S3: 45839 | T3: 45870 | U3: 45901 | V3: 45931 | W3: 45962 | X3: 45992 | Y3: Total necessário
A4: OI SA recuperação judicial | B4: STI | C4: 3 | D4: VGM01N01I4N | E4: 76535764000143 | F4: 515/2021 | G4: 60000 | I4: =G4*12 -> 720000 | J4: 116839.83 | K4: 0 | L4: =SUM(J4:K4) -> 116839.83 | O4: =G4 -> 60000 | P4: =G4 -> 60000 | Q4: =G4 -> 60000 | W4: =G4 -> 60000 | X4: =G4 -> 60000 | Y4: =SUM(T4:X4) -> 120000 | AA4: =SUM(G4:H4)*2 -> 120000 | AB4: =L4-AA4 -> -3160.17 | AC4: =-V4-W4 -> -60000 | AD4: =(SUM(G4:H4)*2)-L4 -> 3160.17
A5: - Fornecimento de combustível (Novo fornecer para 2019 - Ticket soluções HDFGT S/A) (NÃO DEVE SER ANULADO) | B5: PRC | C5: 3 | D5: VGM01N01I5N | E5: 3506307000157 | F5: 1222/2022 | G5: 80000 | I5: =G5*12 -> 960000 | J5: 80000.32 | K5: 0 | L5: =SUM(J5:K5) -> 80000.32 | T5: =80000-12226 -> 67774 | V5: 80000 | W5: =G5 -> 80000 | X5: =G5 -> 80000 | Y5: =SUM(T5:X5) -> 307774 | AA5: =SUM(G5:H5)*2 -> 160000 | AC5: =L5-AA5 -> -79999.68
A6: ELYON BRASIL - ESPLANADA SERVICOS TERCEIRIZADOS EIRELI - serviços continuados de pessoal - coletores de resíduos de serviços de saúde | B6: Contratos DCA | C6: 1 | D6: VGM01N01E4N | E6: 01099686000182 | F6: 111/2020 | H6: =I6/12 -> 22669.34 | I6: 272032.08 | J6: 43507.09 | K6: 0 | L6: =SUM(J6:K6) -> 43507.09 | Q6: =22669-1831.59 -> 20837.41 | T6: =H6-1000 -> 21669.34 | V6: =H6-20838 -> 1831.34 | W6: =H6 -> 22669.34 | X6: =H6 -> 22669.34 | Y6: =SUM(T6:X6) -> 68839.36 | AA6: =SUM(G6:H6)*2 -> 45338.68 | AB6: =L6-AA6 -> -1831.59 | AD6: =(SUM(G6:H6)*2)-L6 -> 1831.59
A7: - ALFA E OMEGA Apoio Técnico EDU | B7: Contratos DCA | C7: 1 | D7: VGM01N01D5N | E7: 16650774000106 | F7: 022/2021 | H7: =I7/12 -> 24316.78 | I7: 291801.36 | J7: 52296.57 | K7: 0 | L7: =SUM(J7:K7) -> 52296.57 | O7: 865.66 | P7: =H7-2497 -> 21819.78 | Q7: =H7-22360 -> 1956.78 | R7: =H7 -> 24316.78 | W7: =H7 -> 24316.78 | X7: =H7 -> 24316.78 | Y7: =SUM(T7:X7) -> 48633.56 | AA7: =SUM(G7:H7)*2 -> 48633.56 | AB7: =L7-AA7 -> 3663.01 | AD7: =(SUM(G7:H7)*2)-L7 -> -3663.01
A8: Phoenix Comércio e Serviços de Limpeza LTDA - Almoxarifado e de transporte interno de móveis e materiais | B8: Contratos DCA | C8: 1 | D8: VGM01N01F7N | E8: 12978051000171 | F8: 111/2022 | H8: 116248.37 | I8: =H8*12 -> 1394980.4 | J8: 118871.46 | K8: 0 | L8: =SUM(J8:K8) -> 118871.46 | P8: =117871-49371 -> 68500 | Q8: =H8-L8 -> -2623.09 | R8: =H8 -> 116248.37 | V8: =H8 -> 116248.37 | W8: =H8 -> 116248.37 | X8: =H8 -> 116248.37 | Y8: =SUM(T8:X8) -> 348745.11 | AA8: =SUM(G8:H8)*2 -> 232496.74 | AC8: -212997.86 | AD8: =(SUM(G8:H8)*2)-L8 -> 113625.28
A9: Contrato de Limpeza - UnB Cerrado (AP PISCINAS EIRELI) | B9: UnB Cerrado | C9: 1 | D9: VGM01N01A7N (VGM01N1F2N-PI indevido) | E9: 08475822000130 | F9: 112/2020 | H9: 5954.2 | I9: 63975.84 | J9: 5044.97 | K9: 0 | L9: =SUM(J9:K9) -> 5044.97 | O9: =H9-L9 -> 909.23 | P9: =H9-4688 -> 1266.2 | R9: =5331-L9 -> 286.03 | S9: =H9-4396 -> 1558.2 | T9: =H9 -> 5954.2 | V9: =H9 -> 5954.2 | W9: =H9 -> 5954.2 | X9: =H9 -> 5954.2 | Y9: =SUM(T9:X9) -> 23816.8 | AA9: =SUM(G9:H9)*2 -> 11908.4 | AC9: -643.35 | AD9: =(SUM(G9:H9)*2)-L9 -> 6863.43
A10: - ENERGIA ELÉTRICA - SPI | B10: Contratos SPI | C10: 3 | D10: VGM01N01I2N | E10: 07522669000192 | G10: 40000 | I10: =G10*12 -> 480000 | J10: 82840.02 | K10: 2965.4 | L10: =SUM(J10:K10) -> 85805.42 | P10: =40000-12743 -> 27257 | R10: =G10-23261 -> 16739 | W10: =G10-5805 -> 34195 | X10: =G10 -> 40000 | Y10: =SUM(T10:X10) -> 74195 | AA10: =G10*2 -> 80000 | AB10: =L10-AA10 -> 5805.42 | AD10: =(SUM(G10:H10)*2)-L10 -> -5805.42
A11: CONCEIÇÃO Aparecida Braga 67186920691 ME (análise e levantamento de conjuntos documentais do arquivo do Cespe/UnB) | B11: Contratos Diversos | C11: 1 | D11: VGM01N01P1N | E11: 41423145000182 | F11: 1230/2022 | G11: 17000 | I11: =G11*12 -> 204000 | J11: 26011.43 | K11: 0 | L11: =SUM(J11:K11) -> 26011.43 | Q11: 17000 | R11: =G11 -> 17000 | S11: =G11-14992 -> 2008 | T11: =G11-14992 -> 2008 | V11: 9011 | W11: =G11 -> 17000 | X11: =G11 -> 17000 | Y11: =SUM(T11:X11) -> 45019 | AA11: =G11*2 -> 34000 | AC11: -31532.95 | AD11: =(SUM(G11:H11)*2)-L11 -> 7988.57
A12: Tratador de Piscinas CO e casa Oscar Niemayer - (AP Piscinas EIRELI) - em fase de renovação | B12: Contratos Diversos | C12: 1 | D12: VGM01N01E2N | E12: 08475822000130 | F12: 93/2020 | H12: =I12/12 -> 5039.3475 | I12: 60472.17 | J12: 1511.77 | K12: 0 | L12: =SUM(J12:K12) -> 1511.77 | Q12: =H12-166.38 -> 4872.9675 | R12: =H12 -> 5039.3475 | T12: =H12-1512 -> 3527.3475 | U12: =H12-1512 -> 3527.3475 | V12: =H12 -> 5039.3475 | W12: =H12 -> 5039.3475 | X12: =H12 -> 5039.3475 | Y12: =SUM(T12:X12) -> 22172.737 | AA12: =H12*2 -> 10078.695 | AD12: =(SUM(G12:H12)*2)-L12 -> 8566.925
A13: - Correios - ECT -reduziu porque não temos mais contrato de encomendas | B13: Comunicação | C13: 2 | D13: VGM01N01J1N | E13: 34028316000707 | F13: 1207/2023 | G13: 3000 | I13: =G13*12 -> 36000 | J13: 8738.57 | K13: 0 | L13: =SUM(J13:K13) -> 8738.57 | W13: =G13 -> 3000 | X13: =G13 -> 3000 | Y13: =SUM(T13:X13) -> 6000 | AA13: =G13*2 -> 6000 | AC13: -642 | AD13: =(SUM(G13:H13)*2)-L13 -> -2738.57
A14: - Empresa Brasil de Comunicação (EBC) | B14: Comunicação | C14: 2 | D14: VGM01N01I9N | F14: 213/2020 | G14: 2000 | I14: =G14*12 -> 24000 | J14: 4242.4 | K14: 0 | L14: =SUM(J14:K14) -> 4242.4 | Q14: =G14-307 -> 1693 | W14: =G14 -> 2000 | X14: =G14 -> 2000 | Y14: =SUM(T14:X14) -> 4000 | AA14: =G14*2 -> 4000 | AB14: =L14-AA14 -> 242.4 | AD14: =(SUM(G14:H14)*2)-L14 -> -242.4
A15: Total da despesa | G15: =SUM(G4:G14) -> 202000 | H15: =SUM(H4:H14) -> 174228.04 | I15: =SUM(I4:I14) -> 4507261.9 | J15: =SUM(J4:J14) -> 539904.43 | K15: =SUM(K4:K14) -> 2965.4 | L15: =SUM(L4:L14) -> 542869.83 | M15: =SUM(M4:M14) -> 0 | N15: =SUM(N4:N14) -> 0 | ... Y15: =SUM(Y4:Y14) -> 1069195.6 | AA15: =SUM(AA4:AA14) -> 752456.07 | AB15: =SUM(AB4:AB14) -> 4719.07 | AC15: =SUM(AC4:AC14) -> -385815.84 | AD15: =SUM(AD4:AD14) -> 129586.56
I17: =I15/12 -> 375605.16 | AC17: =#REF! -> #REF!
AC18: -6000000
AC19: -1280820.9
AC21: =SUM(AC17:AC18) -> #REF!
AC22: =AC21+#REF! -> #REF!

Sheet Prog-18.08
A3: Descrição das despesas | B3: UGR | C3: PI 2025 | D3: CNPJ | E3: nº Contrato | F3: Total necessário
A4: Pasep - UnB | B4: DGP/ folha | C4: VGM01N01N1N | F4: 1589464.9
A5: SANEAGO - Água e esgoto UnB Cerrado (corrigir a média) | B5: UnB Cerrado | C5: VGM01N01I3N | D5: 01616929000102 | F5: 999
A6: Energia Elétrica UnB Cerrado - CONTRATO CCER - ENEL N. 36/2020 e CELG DISTRIBUIÇÃO S.A - CELG D, Equatorial Goiás Distribuidora de Energia S/A | B6: UnB Cerrado | C6: VGM01N01I2N | D6: 1543032/0001-04 | E6: 36/2020 | F6: 3525.03
A7: OI SA recuperação judicial | B7: STI | C7: VGM01N01I4N | D7: 76535764/0001-43 | E7: 515/2021 | F7: 63161
A8: - Fornecimento de combustível (Ticket soluções HDFGT S/A) | B8: PRC | C8: VGM01N01I5N | D8: 3506307/0001-57 | E8: 1222/2022 | F8: 67774
A9: CRUZEIRO CONTROLE DE PRAGAS E DESENTUPIMENTO | B9: PRC | C9: VGM01N01D3N | D9: 22.575.793/0001-00 | E9: 1222/2024 | F9: 77841.04
A10: VILELA SERVIÇO DE PAISAGISMO, PARQUES E JARDINS LTDA (jardinagem) | B10: PRC | C10: VGM01N01A5N | D10: 32.751.565/0001-05 | E10: 1217/2023 | F10: 568923
A11: Tafa Engenharia (serviços continuados de manutenção preventiva e corretiva de equipamentos e sistemas de ar condicionado, com fornecimento de peças e materiais) | B11: PRC | C11: VGM01N01F1N | D11: 12859652000165 | E11: 616/2024 | F11: 25220
A12: - Taxigov (demanda) - VIP service | B12: PRC | C12: VGM01N01A4N | D12: 02605452000122 | E12: 036/2020 | F12: 2125
A13: 3P HGM solução visual (serviços de comunicação visual) | B13: PRC | C13: VGM01N01O7N | D13: 34.998.513/0001-55 | E13: 1217/2022 | F13: 1291844
A14: ARTES GRÁFICA COMÉRCIO E REPRESENTAÇÕES EIRELI (serviços continuados de Designer Gráfico) | B14: Contratos DCA | C14: VGM01N01P4N | D14: 05606994000108 | E14: 147/2022 | F14: 12640.77
A15: ELYON BRASIL - ESPLANADA SERVICOS TERCEIRIZADOS EIRELI - serviços continuados de pessoal - coletores de resíduos de serviços de saúde | B15: Contratos DCA | C15: VGM01N01E4N | D15: 01099686/0001-82 | E15: 111/2020 | F15: 67008.02
A16: - ALFA E OMEGA Apoio Técnico EDU | B16: Contratos DCA | C16: VGM01N01D5N | D16: 16650774000106 | E16: 022/2021 | F16: 24316.78
A17: RCS Tecnologia LTDA - copeiragem | B17: Contratos DCA | C17: VGM01N01O2N | D17: 8220952/0001-22 | E17: 07/2021 | F17: 131667.49
A18: T&S Engenharia Telemática e Sistemas LTDA - contínuo | B18: Contratos DCA | C18: VGM01N01B7N | D18: 00712411000100 | E18: 006/2021 | F18: 183316.03
A19: - RCA (Limpeza e Conservação) | B19: Contratos DCA | C19: VGM01N01A7N | D19: 69.207.850/0001-61 | E19: 02/2022 | F19: 2385193
A20: Life Defense (Segurança) | B20: Contratos DCA | C20: VGM01N01A8N | D20: 02674687000176 | E20: 011/2020 | F20: 2117878.6
A21: G&E SERVICOS TERCEIRIZADOS LTDA (PORTARIA) | B21: Contratos DCA | C21: VGM01N01A9N | D21: 08744139000151 | E21: 081/2022 | F21: 1238298.9
A22: G&E SERVICOS TERCEIRIZADOS LTDA - serviços continuados de motorista | B22: Contratos DCA | C22: VGM01N01P5N | D22: 08744139000151 | E22: 001/2023 | F22: 236438.33
A23: MPE ENGENHARIA E SERVICOS S/A (serviços comuns de engenharia, incluindo manutenção, conservação, adaptação, reparação e instalação de infraestruturas prediais e imobiliárias) - | B23: Contratos DCA | C23: VGM01N01H3N | D23: 04743858000105 | E23: 1201/2023 | F23: 2739808
... A30: Engemega - (Manutenção de Imóveis gerenciados pela Secretaria de Patrimônio Imobiliário (SPI)) | B30: Contratos SPI | C30: VGM01N01D4N | D30: 33480104/0001-08 | E30: 1223/2022 | F30: 368690
A31: - ENERGIA ELÉTRICA - SPI | B31: Contratos SPI | C31: VGM01N01I2N | D31: 07522669000192 | F31: 34195
A32: - Despesas de Condomínio | B32: Contratos SPI | C32: VGM01N01K6N | F32: 343318
A33: Restaurante ISM EIRELI (diretoria RU) - Ação 20RK planilha DRU | B33: Contrato DAC/RU | C33: VGM01N01B5N | D33: 04228626001263 | E33: 31/2021 | F33: 1791326.9
A34: PGFN: 2° ATI, negociação conta n°: 8815031 (Consulta Acordo n°2 - Conta da Negociação 8815031 (SEI nº 10576277)) | B34: Contratos Diversos | C34: VGH01N0112N | F34: 28500
A35: CONCEIÇÃO Aparecida Braga 67186920691 ME (análise e levantamento de conjuntos documentais do arquivo do Cespe/UnB) | B35: Contratos Diversos | C35: VGM01N01P1N | D35: 41423145000182 | E35: 1230/2022 | F35: 36008
A36: - Correios - ECT -reduziu porque não temos mais contrato de encomendas | B36: Comunicação | C36: VGM01N01J1N | D36: 34028316000707 | E36: 1207/2023 | F36: 6000
A37: - Empresa Brasil de Comunicação (EBC) | B37: Comunicação | C37: VGM01N01I9N | E37: 213/2020 | F37: 1500
A38: - SIMPRESS - Outsourcing de serviços de impressão | B38: (STI) | C38: VGM01N01M8N | D38: 07432517000107 | E38: 512/2021 | F38: 109582.18
A40: Total da despesa | F40: =SUM(F4:F38) -> 18785489
A43: Descrição das despesas | B43: UGR | C43: PI 2025 | D43: CNPJ | E43: nº Contrato | F43: Total necessário
A44: Pasep - UnB | B44: DGP/ folha | C44: VGM01N01N1N | F44: 1589464.9
A45: SANEAGO - Água e esgoto UnB Cerrado (corrigir a média) | B45: UnB Cerrado | C45: VGM01N01I3N | D45: 01616929000102 | F45: 999
A46: Energia Elétrica UnB Cerrado - CONTRATO CCER - ENEL N. 36/2020 e CELG DISTRIBUIÇÃO S.A - CELG D, Equatorial Goiás Distribuidora de Energia S/A | B46: UnB Cerrado | C46: VGM01N01I2N | D46: 1543032/0001-04 | E46: 36/2020 | F46: 3525.03
A47: OI SA recuperação judicial | B47: STI | C47: VGM01N01I4N | D47: 76535764/0001-43 | E47: 515/2021 | F47: 63161
A48: - Fornecimento de combustível (Ticket soluções HDFGT S/A) | B48: PRC | C48: VGM01N01I5N | D48: 3506307/0001-57 | E48: 1222/2022 | F48: 67774
A49: CRUZEIRO CONTROLE DE PRAGAS E DESENTUPIMENTO | B49: PRC | C49: VGM01N01D3N | D49: 22.575.793/0001-00 | E49: 1222/2024 | F49: 77841.04
A50: VILELA SERVIÇO DE PAISAGISMO, PARQUES E JARDINS LTDA (jardinagem) | B50: PRC | C50: VGM01N01A5N | D50: 32.751.565/0001-05 | E50: 1217/2023 | F50: 568923
A51: Tafa Engenharia (serviços continuados de manutenção preventiva e corretiva de equipamentos e sistemas de ar condicionado, com fornecimento de peças e materiais) | B51: PRC | C51: VGM01N01F1N | D51: 12859652000165 | E51: 616/2024 | F51: 25220
A52: - Taxigov (demanda) - VIP service | B52: PRC | C52: VGM01N01A4N | D52: 02605452000122 | E52: 036/2020 | F52: 2125
A53: 3P HGM solução visual (serviços de comunicação visual) | B53: PRC | C53: VGM01N01O7N | D53: 34.998.513/0001-55 | E53: 1217/2022 | F53: 1291844
A54: ARTES GRÁFICA COMÉRCIO E REPRESENTAÇÕES EIRELI (serviços continuados de Designer Gráfico) | B54: Contratos DCA | C54: VGM01N01P4N | D54: 05606994000108 | E54: 147/2022 | F54: 12640.77
A55: ELYON BRASIL - ESPLANADA SERVICOS TERCEIRIZADOS EIRELI - serviços continuados de pessoal - coletores de resíduos de serviços de saúde | B55: Contratos DCA | C55: VGM01N01E4N | D55: 01099686/0001-82 | E55: 111/2020 | F55: 67008.02
A56: - ALFA E OMEGA Apoio Técnico EDU | B56: Contratos DCA | C56: VGM01N01D5N | D56: 16650774000106 | E56: 022/2021 | F56: 24316.78
A57: RCS Tecnologia LTDA - copeiragem | B57: Contratos DCA | C57: VGM01N01O2N | D57: 8220952/0001-22 | E57: 07/2021 | F57: 131667.49
A58: T&S Engenharia Telemática e Sistemas LTDA - contínuo | B58: Contratos DCA | C58: VGM01N01B7N | D58: 00712411000100 | E58: 006/2021 | F58: 183316.03
A59: - RCA (Limpeza e Conservação) | B59: Contratos DCA | C59: VGM01N01A7N | D59: 69.207.850/0001-61 | E59: 02/2022 | F59: 2385193
A60: Life Defense (Segurança) | B60: Contratos DCA | C60: VGM01N01A8N | D60: 02674687000176 | E60: 011/2020 | F60: 2117878.6
A61: G&E SERVICOS TERCEIRIZADOS LTDA (PORTARIA) | B61: Contratos DCA | C61: VGM01N01A9N | D61: 08744139000151 | E61: 081/2022 | F61: 1238298.9
A62: Total da despesa | F62: =SUM(F44:F61) -> 9851196.6
A65: Descrição das despesas | B65: UGR | C65: PI 2025 | D65: CNPJ | E65: nº Contrato | F65: Total necessário
A66: G&E SERVICOS TERCEIRIZADOS LTDA - serviços continuados de motorista | B66: Contratos DCA | C66: VGM01N01P5N | D66: 08744139000151 | E66: 001/2023 | F66: 236438.33
A67: MPE ENGENHARIA E SERVICOS S/A (serviços comuns de engenharia, incluindo manutenção, conservação, adaptação, reparação e instalação de infraestruturas prediais e imobiliárias) - | B67: Contratos DCA | C67: VGM01N01H3N | D67: 04743858000105 | E67: 1201/2023 | F67: 2739808
A68: MPE - Adequação e impermeabilização | B68: Contratos DCA | C68: VGA02N43E3N | D68: 04743858000105 | E68: 1110/2024 | F68: 2069132.1
A69: POLI ENGENHARIA LTDA (serviços comuns de engenharia, incluindo manutenção, conservação, adaptação, reparação e instalação de infraestruturas prediais e imobiliárias) | B69: Contratos DCA | C69: VGM01N01H3N | D69: 00700518000138 | E69: 1226/2022 | F69: 125875.27
A70: Ágil (Serviços Agropecuários) | B70: Contratos DCA | C70: VGM01N01C5N | D70: 72620735000129 | E70: 25/2020 | F70: 458615.91
A71: Recepcionista – AMR LIMPEZA E LOCACAO DE AUTOMOVEIS LTDA | B71: UnB Cerrado | C71: VGM01N01B3N | D71: 10.258.826/0001-09 | E71: 12/2024 | F71: 8581.82
A72: '- GESTOR SERVICOS EMPRESARIAIS (Portaria - SPI) | B72: Contratos SPI | C72: VGM01N01E8N | D72: 02.685.728/0001-20 | E72: 001/2022 | F72: 382896.8
A73: - SEFIX (Limpeza e Conservação - SPI) | B73: Contratos SPI | C73: VGM01N01E9N | D73: 13258899000199 | E73: 033/2022 | F73: 193823.77
A74: Engemega - (Manutenção de Imóveis gerenciados pela Secretaria de Patrimônio Imobiliário (SPI)) | B74: Contratos SPI | C74: VGM01N01D4N | D74: 33480104/0001-08 | E74: 1223/2022 | F74: 368690
A75: - ENERGIA ELÉTRICA - SPI | B75: Contratos SPI | C75: VGM01N01I2N | D75: 07522669000192 | F75: 34195
A76: - Despesas de Condomínio | B76: Contratos SPI | C76: VGM01N01K6N | F76: 343318
A77: Restaurante ISM EIRELI (diretoria RU) - Ação 20RK planilha DRU | B77: Contrato DAC/RU | C77: VGM01N01B5N | D77: 04228626001263 | E77: 31/2021 | F77: 1791326.9
A78: PGFN: 2° ATI, negociação conta n°: 8815031 (Consulta Acordo n°2 - Conta da Negociação 8815031 (SEI nº 10576277)) | B78: Contratos Diversos | C78: VGH01N0112N | F78: 28500
A79: CONCEIÇÃO Aparecida Braga 67186920691 ME (análise e levantamento de conjuntos documentais do arquivo do Cespe/UnB) | B79: Contratos Diversos | C79: VGM01N01P1N | D79: 41423145000182 | E79: 1230/2022 | F79: 36008
A80: - Correios - ECT -reduziu porque não temos mais contrato de encomendas | B80: Comunicação | C80: VGM01N01J1N | D80: 34028316000707 | E80: 1207/2023 | F80: 6000
A81: - Empresa Brasil de Comunicação (EBC) | B81: Comunicação | C81: VGM01N01I9N | E81: 213/2020 | F81: 1500
A82: - SIMPRESS - Outsourcing de serviços de impressão | B82: (STI) | C82: VGM01N01M8N | D82: 07432517000107 | E82: 512/2021 | F82: 109582.18
A83: Total da despesa | F83: =SUM(F66:F82) -> 8934292.1

Sheet Prog-08.07
A1: Acompanhamento de Contratos*
A3: Descrição das despesas | B3: UGR | C3: Prioridade | D3: PI 2025 | E3: CNPJ | F3: Processo | G3: Vigência | H3: Status do Contrato | I3: Situação da prorrogação | J3: nº Contrato | K3: Valor Contrato Média mensal | L3: Valor Cont Continuado Mensal | M3: Total estimado Anual | N3: Saldo Empenhos 2025 | O3: Saldo de Empenhos RAP | P3: Total RAP + Empenho | Q3: 45658 | R3: 45689 | S3: 45717 | T3: 45748 | U3: 45778 | V3: 45809 | W3: 45839 | X3: 45870 | Y3: 45901 | Z3: Total necessário
A4: Pasep - UnB | B4: DGP/ folha | C4: 1 | D4: VGM01N01N1N | K4: 810000 | M4: =K4*12 -> 9720000 | N4: 0 | O4: 0 | P4: =SUM(N4:O4) -> 0 | U4: =810000-556810 -> 253190 | V4: =K4 -> 810000 | W4: =K4 -> 810000 | X4: =K4 -> 810000 | Y4: =K4 -> 810000 | Z4: =SUM(W4:Y4)+101000 -> 2531000
A5: CRUZEIRO CONTROLE DE PRAGAS E DESENTUPIMENTO | B5: PRC | C5: 2 | D5: VGM01N01D3N | E5: 22.575.793/0001-00 | F5: 23106.058637/2021-45 | G5: 45980 | H5: =IF((G5-TODAY())<0,"EXPIRADO", IF((G5-TODAY())<=60,"EM BREVE","NO PRAZO")) -> EM BREVE | J5: 1222/2024 | K5: =M5/12 -> 65625.02 | M5: 787500.24 | N5: 55376.88 | O5: 5443 | P5: =SUM(N5:O5) -> 60819.88 | U5: =K5-P5 -> 4805.14 | V5: =K5-60820 -> 4805.02 | W5: =K5-60820 -> 4805.02 | X5: =K5 -> 65625.02 | Z5: =SUM(W5:Y5) -> 70430.04
A6: VILELA SERVIÇO DE PAISAGISMO, PARQUES E JARDINS LTDA (jardinagem) | B6: PRC | C6: 2 | D6: VGM01N01A5N | E6: 32.751.565/0001-05 | F6: 23106.028705/2019-27 | G6: 45866 | H6: =IF((G6-TODAY())<0,"EXPIRADO", IF((G6-TODAY())<=60,"EM BREVE","NO PRAZO")) -> EXPIRADO | I6: solicitou-se à empresa interesse em renovar | J6: 1217/2023 | K6: 298000 | M6: 3119907.7 | N6: 271060.23 | O6: 0 | P6: =SUM(N6:O6) -> 271060.23 | T6: =291576.42-21573 -> 270003.42 | U6: =K6-P6 -> 26939.77 | V6: =K6 -> 298000 | W6: =K6-271060 -> 26940 | Z6: =SUM(W6:Y6) -> 26940
A7: - TRANSMONICI TRANSPORTE E TURISMO (ônibus rodoviário executivo) | B7: PRC | C7: 2 | D7: VGM01N01K1N | E7: 09169349000126 | F7: 23106.000890/2021-18 | G7: 46062 | H7: =IF((G7-TODAY())<0,"EXPIRADO", IF((G7-TODAY())<=60,"EM BREVE","NO PRAZO")) -> NO PRAZO | J7: 604/2022 | K7: 90000 | M7: =K7*12 -> 1080000 | N7: 116120.9 | O7: 0 | P7: =SUM(N7:O7) -> 116120.9 | X7: =90000-26121 -> 63879 | Y7: =K7 -> 90000 | Z7: =SUM(W7:Y7) -> 153879
A8: ARTES GRÁFICA COMÉRCIO E REPRESENTAÇÕES EIRELI (serviços continuados de Designer Gráfico) - foi solicitada prorrogação por 20 meses | B8: Contratos DCA | C8: 2 | D8: VGM01N01P4N | E8: 05606994000108 | F8: 23106.148085/2022-47 | G8: 46127 | H8: =IF((G8-TODAY())<0,"EXPIRADO", IF((G8-TODAY())<=60,"EM BREVE","NO PRAZO")) -> NO PRAZO | J8: 147/2022 | L8: =12640.77 -> 12640.77 | M8: =L8*12 -> 151689.24 | N8: 0 | O8: 0 | P8: =SUM(N8:O8) -> 0 | U8: =L8-536 -> 12104.77 | W8: =L8 -> 12640.77 | X8: =L8 -> 12640.77 | Y8: =L8 -> 12640.77 | Z8: =SUM(W8:Y8) -> 37922.31
A9: - ALFA E OMEGA Apoio Técnico EDU | B9: Contratos DCA | C9: 1 | D9: VGM01N01D5N | E9: 16650774000106 | F9: 23106.011967/2019-52 | G9: 46131 | H9: =IF((G9-TODAY())<0,"EXPIRADO", IF((G9-TODAY())<=60,"EM BREVE","NO PRAZO")) -> NO PRAZO | J9: 022/2021 | L9: =M9/12 -> 24316.78 | M9: 291801.36 | N9: 50982.01 | O9: 0 | P9: =SUM(N9:O9) -> 50982.01 | S9: 865.66 | T9: =L9-2497 -> 21819.78 | U9: =L9-22360 -> 1956.78 | V9: =L9 -> 24316.78 | Y9: =L9-2348 -> 21968.78 | Z9: =SUM(W9:Y9) -> 21968.78
A10: RCS Tecnologia LTDA - copeiragem | B10: Contratos DCA | C10: 1 | D10: VGM01N01O2N | E10: 08220952000122 | F10: 23106.125355/2019-46 23106.035022/2021-41 | G10: 45929 | H10: =IF((G10-TODAY())<0,"EXPIRADO", IF((G10-TODAY())<=60,"EM BREVE","NO PRAZO")) -> EXPIRADO | I10: Foi para a PF solicitando prorrogação com vigência em 29/09/2025 | J10: 07/2021 | L10: 131667.49 | M10: =L10*12 -> 1580009.9 | N10: 264774.55 | O10: 0 | P10: =SUM(N10:O10) -> 264774.55 | T10: 131667 | V10: =L10 -> 131667.49 | Y10: =L10 -> 131667.49 | Z10: =SUM(W10:Y10) -> 131667.49
A11: T&S Engenharia Telemática e Sistemas LTDA - contínuo | B11: Contratos DCA | C11: 1 | D11: VGM01N01B7N | E11: 00712411000100 | F11: 23106.034924/2021-60 | G11: 45745 | H11: =IF((G11-TODAY())<0,"EXPIRADO", IF((G11-TODAY())<=60,"EM BREVE","NO PRAZO")) -> EXPIRADO | I11: Foi para PF, prorrogação excepcional | J11: 006/2021 | L11: 183316.03 | M11: =L11*12 -> 2199792.4 | N11: 183316.03 | O11: 0 | P11: =SUM(N11:O11) -> 183316.03 | S11: =L11-P11 -> 0 | T11: =L11 -> 183316.03 | X11: =L11 -> 183316.03 | Y11: =L11 -> 183316.03 | Z11: =SUM(W11:Y11) -> 366632.06
A12: Novo contrato de serviços de apoio administrativo (contínuo) e de copeiragem | B12: Contratos DCA | C12: 1 | D12: VGM01N01B7N | F12: 23106.030343/2024-00 | Z12: =SUM(W12:Y12) -> 0
A13: Phoenix Comércio e Serviços de Limpeza LTDA - Almoxarifado e de transporte interno de móveis e materiais | B13: Contratos DCA | C13: 1 | D13: VGM01N01F7N | E13: 12978051000171 | F13: 23106.001099/2022-06 | G13: 45902 | H13: =IF((G13-TODAY())<0,"EXPIRADO", IF((G13-TODAY())<=60,"EM BREVE","NO PRAZO")) -> EXPIRADO | J13: 111/2022 | L13: 117871.46 | M13: =L13*12 -> 1414457.5 | N13: 235742.92 | O13: 0 | P13: =SUM(N13:O13) -> 235742.92 | T13: =117871-49371 -> 68500 | U13: =L13-P13 -> -117871.46 | V13: =L13 -> 117871.46 | Y13: =L13 -> 117871.46 | Z13: =SUM(W13:Y13) -> 117871.46
A14: - RCA (Limpeza e Conservação) | B14: Contratos DCA | C14: 1 | D14: VGM01N01A7N | E14: 69.207.850/0001-61 | F14: 23106.057738/2021-07 | G14: 46402 | H14: =IF((G14-TODAY())<0,"EXPIRADO", IF((G14-TODAY())<=60,"EM BREVE","NO PRAZO")) -> NO PRAZO | J14: 02/2022 | L14: 1889237.8 | M14: =L14*12 -> 22670853 | N14: 2846580.6 | O14: 0 | P14: =SUM(N14:O14) -> 2846580.6 | T14: =1882331-116567 -> 1765764 | V14: =L14 -> 1889237.8 | X14: =L14-957343 -> 931894.76 | Y14: =L14 -> 1889237.8 | Z14: =SUM(W14:Y14)+1000000 -> 3821132.5
A15: Life Defense (Segurança) | B15: Contratos DCA | C15: 1 | D15: VGM01N01A8N | E15: 02674687000176 | F15: 23106.016977/2013-99 23106.083943/2018-14 23106.047642/2024-75 | G15: 46097 | H15: =IF((G15-TODAY())<0,"EXPIRADO", IF((G15-TODAY())<=60,"EM BREVE","NO PRAZO")) -> NO PRAZO | I15: Foi solicitado parecer à PF para prorrogação. | J15: 011/2020 | L15: 1617878.6 | M15: =L15*12 -> 19414543 | N15: 2426817.9 | O15: 0 | P15: =SUM(N15:O15) -> 2426817.9 | T15: =L15 -> 1617878.6 | V15: =L15 -> 1617878.6 | X15: =L15-808939 -> 808939.59 | Y15: =L15 -> 1617878.6 | Z15: =SUM(W15:Y15)+1000000 -> 3426818.2
A16: G&E SERVICOS TERCEIRIZADOS LTDA (PORTARIA) | B16: Contratos DCA | C16: 1 | D16: VGM01N01A9N | E16: 08744139000151 | F16: 23106.085840/2022-75 23106.005560/2022-91 23106.046596/2024-97 | G16: 46020 | H16: =IF((G16-TODAY())<0,"EXPIRADO", IF((G16-TODAY())<=60,"EM BREVE","NO PRAZO")) -> EM BREVE | J16: 081/2022 | L16: =1205875.51+32423.44 -> 1238298.9 | M16: =L16*12 -> 14859587 | N16: 1859307.3 | O16: 0 | P16: =SUM(N16:O16) -> 1859307.3 | S16: =L16-O16 -> 1238298.9 | T16: =1238299-555 -> 1237744 | V16: =L16 -> 1238298.9 | X16: =L16-621008 -> 617290.95 | Y16: =L16 -> 1238298.9 | Z16: =SUM(W16:Y16) -> 1855589.9
A17: G&E SERVICOS TERCEIRIZADOS LTDA - serviços continuados de motorista | B17: Contratos DCA | C17: 1 | D17: VGM01N01P5N | E17: 08744139000151 | F17: 23106.038810/2022-70 | G17: 46166 | H17: =IF((G17-TODAY())<0,"EXPIRADO", IF((G17-TODAY())<=60,"EM BREVE","NO PRAZO")) -> NO PRAZO | J17: 001/2023 | L17: 236438.33 | M17: =L17*12 -> 2837260 | N17: 332837.48 | O17: 0 | P17: =SUM(N17:O17) -> 332837.48 | T17: 190000 | V17: =L17-171405 -> 65033.331 | X17: =L17-96399 -> 140039.33 | Y17: =L17 -> 236438.33 | Z17: =SUM(W17:Y17) -> 376477.66
A18: MPE ENGENHARIA E SERVICOS S/A (serviços comuns de engenharia, incluindo manutenção, conservação, adaptação, reparação e instalação de infraestruturas prediais e imobiliárias) - (exceto DAC) | B18: Contratos DCA | C18: 2 | D18: VGM01N01H3N | E18: 04743858000105 | F18: 23106.149436/2022-37 | G18: 46114 | H18: =IF((G18-TODAY())<0,"EXPIRADO", IF((G18-TODAY())<=60,"EM BREVE","NO PRAZO")) -> NO PRAZO | J18: 1201/2023 | K18: 1600000 | M18: =K18*12 -> 19200000 | N18: =1387659.05 -> 1387659.1 | O18: 6102.62 | P18: =SUM(N18:O18) -> 1393761.7 | V18: =K18-836351 -> 763649 | W18: =K18-1393762 -> 206238 | X18: =K18 -> 1600000 | Z18: =SUM(W18:Y18) -> 1806238
A19: MPE - Adequação e impermeabilização | B19: Contratos DCA | C19: 2 | D19: VGA02N43E3N | E19: 04743858000105 | F19: 23106.149228/2022-38 | G19: 46022 | H19: =IF((G19-TODAY())<0,"EXPIRADO", IF((G19-TODAY())<=60,"EM BREVE","NO PRAZO")) -> EM BREVE | J19: 1110/2024 | K19: =M19/12 -> 1924342.1 | M19: =8383552.34+14708553.16 -> 23092106 | N19: 2198081.8 | O19: 378631.87 | P19: =SUM(N19:O19) -> 2576713.6 | V19: =K19-P19 -> -652371.52 | X19: =K19-652371.53 -> 1271970.6 | Z19: =SUM(W19:Y19) -> 1271970.6
A20: POLI ENGENHARIA LTDA (serviços comuns de engenharia, incluindo manutenção, conservação, adaptação, reparação e instalação de infraestruturas prediais e imobiliárias) - contrato 20 meses | B20: Contratos DCA | C20: 2 | D20: VGM01N01H3N | E20: 00700518000138 | F20: 23106.117479/2022-53 | G20: 46146 | H20: =IF((G20-TODAY())<0,"EXPIRADO", IF((G20-TODAY())<=60,"EM BREVE","NO PRAZO")) -> NO PRAZO | J20: 1226/2022 | K20: 145000 | M20: =K20*12 -> 1740000 | N20: =64791.35+188772.36 -> 253563.71 | O20: 10932 | P20: =SUM(N20:O20) -> 264495.71 | X20: =K20-119495.71 -> 25504.29 | Y20: =K20 -> 145000 | Z20: =SUM(W20:Y20) -> 170504.29
A21: Ágil (Serviços Agropecuários) | B21: Contratos DCA | C21: 1 | D21: VGM01N01C5N | E21: 72620735000129 | F21: 23106.076196/2018-68 23106.030688/2022-93 | G21: 46097 | H21: =IF((G21-TODAY())<0,"EXPIRADO", IF((G21-TODAY())<=60,"EM BREVE","NO PRAZO")) -> NO PRAZO | I21: Solicitado parecer à PF para prorrogação. | J21: 25/2020 | L21: 458615.91 | M21: =L21*12 -> 5503390.9 | N21: 917231.82 | P21: =SUM(N21:O21) -> 917231.82 | S21: =L21-O21 -> 458615.91 | V21: =L21 -> 458615.91 | Y21: =L21 -> 458615.91 | Z21: =SUM(W21:Y21) -> 458615.91
A22: RB GRÁFICA DIGITAL LTDA | B22: Contratos DCA | C22: 2 | D22: VGM01N01Q1N | E22: 16.951.665/0001-10 | F22: 23106.041918/2022-40 | G22: 45901 | H22: =IF((G22-TODAY())<0,"EXPIRADO", IF((G22-TODAY())<=60,"EM BREVE","NO PRAZO")) -> EXPIRADO | J22: 104/2023 | K22: 100 | M22: =K22*12 -> 1200 | N22: 200 | O22: 139 | P22: =SUM(N22:O22) -> 339 | S22: =K22 -> 100 | Y22: =K22 -> 100 | Z22: =SUM(W22:Y22) -> 100
A23: ARTECOR GRÁFICO E EDITORA LTDA | B23: Contratos DCA | C23: 2 | D23: VGM01N01Q1N | E23: 38.013.991/0001-10 | F23: 23106.041918/2022-40 | G23: 45901 | H23: =IF((G23-TODAY())<0,"EXPIRADO", IF((G23-TODAY())<=60,"EM BREVE","NO PRAZO")) -> EXPIRADO | J23: 105/2023 | K23: 15000 | M23: =K23*12 -> 180000 | N23: 30000 | O23: 0 | P23: =SUM(N23:O23) -> 30000 | S23: =K23 -> 15000 | Y23: =K23 -> 15000 | Z23: =SUM(W23:Y23) -> 15000
A24: Contrato de Limpeza - UnB Cerrado (AP PISCINAS EIRELI) | B24: UnB Cerrado | C24: 1 | D24: VGM01N01A7N (VGM01N1F2N-PI indevido) | E24: 08475822000130 | F24: 23106.116355/2019-55 | G24: 45889 | H24: =IF((G24-TODAY())<0,"EXPIRADO", IF((G24-TODAY())<=60,"EM BREVE","NO PRAZO")) -> EXPIRADO | J24: 112/2020 | L24: =M24/12 -> 5331.32 | M24: 63975.84 | N24: 4395.71 | O24: 0 | P24: =SUM(N24:O24) -> 4395.71 | S24: =L24-P24 -> 935.61 | T24: =L24-4688 -> 643.32 | V24: =5331-P24 -> 935.29 | W24: =L24-4396 -> 935.32 | X24: =L24 -> 5331.32 | Y24: =L24 -> 5331.32 | Z24: =SUM(W24:Y24) -> 11597.96
A25: - Segurança - ULTRASEG Segurança Patrimonial Ltda | B25: UnB Cerrado | C25: 1 | D25: VGM01N01A8N | E25: 09151154000159 | F25: 23106.020717/2022-17 | G25: 45938 | H25: =IF((G25-TODAY())<0,"EXPIRADO", IF((G25-TODAY())<=60,"EM BREVE","NO PRAZO")) -> EXPIRADO | J25: 1207/2022 | L25: 23452.22 | M25: =L25*12 -> 281426.64 | N25: 46904.44 | O25: 0 | P25: =SUM(N25:O25) -> 46904.44 | V25: =L25 -> 23452.22 | Y25: =L25 -> 23452.22 | Z25: =SUM(W25:Y25) -> 23452.22
A26: Recepcionista – AMR LIMPEZA E LOCACAO DE AUTOMOVEIS LTDA | B26: UnB Cerrado | C26: 1 | D26: VGM01N01B3N | E26: 10.258.826/0001-09 | F26: 23106.100112/2023-81 | G26: 46068 | H26: =IF((G26-TODAY())<0,"EXPIRADO", IF((G26-TODAY())<=60,"EM BREVE","NO PRAZO")) -> NO PRAZO | J26: 12/2024 | L26: =M26/12 -> 4290.91 | M26: 51490.92 | N26: 4537 | O26: 0 | P26: =SUM(N26:O26) -> 4537 | V26: =L26 -> 4290.91 | X26: =L26 -> 4290.91 | Y26: =L26 -> 4290.91 | Z26: =SUM(W26:Y26) -> 8581.82
A27: '- GESTOR SERVICOS EMPRESARIAIS (Portaria - SPI) | B27: Contratos SPI | C27: 1 | D27: VGM01N01E8N | E27: 02.685.728/0001-20 | F27: 23106.047067/2021-68 | G27: 46434 | H27: =IF((G27-TODAY())<0,"EXPIRADO", IF((G27-TODAY())<=60,"EM BREVE","NO PRAZO")) -> NO PRAZO | J27: 001/2022 | L27: 382896.8 | M27: =L27*12 -> 4594761.6 | N27: 385232.05 | O27: 0 | P27: =SUM(N27:O27) -> 385232.05 | S27: =L27-P27 -> -2335.25 | V27: =L27-P27 -> -2335.25 | X27: =L27 -> 382896.8 | Y27: =L27 -> 382896.8 | Z27: =SUM(W27:Y27) -> 765793.6
A28: - SEFIX (Limpeza e Conservação - SPI) | B28: Contratos SPI | C28: 1 | D28: VGM01N01E9N | E28: 13258899000199 | F28: 23106.047036/2021-15 | G28: 45854 | H28: =IF((G28-TODAY())<0,"EXPIRADO", IF((G28-TODAY())<=60,"EM BREVE","NO PRAZO")) -> EXPIRADO | I28: em renovação | J28: 033/2022 | L28: 193823.77 | M28: =L28*12 -> 2325885.2 | N28: 193823.77 | O28: 0 | P28: =SUM(N28:O28) -> 193823.77 | T28: =L28 -> 193823.77 | V28: =L28 -> 193823.77 | X28: =L28 -> 193823.77 | Y28: =L28 -> 193823.77 | Z28: =SUM(W28:Y28) -> 387647.54
A29: SILVA EDIFICAÇÕES LTDA - emissão de laudos técnicos de avaliação de valores imobiliários | B29: Contratos SPI | C29: 2 | D29: VGM01N01Q7N | E29: 44.532.592/0001-68 | F29: 23106.019008/2024-42 | K29: =M29/12 -> 832.5 | M29: 9990 | N29: 1638 | O29: 0 | P29: =SUM(N29:O29) -> 1638 | S29: =K29-P29 -> -805.5 | T29: =K29-27 -> 805.5 | U29: =K29 -> 832.5 | Y29: =K29 -> 832.5 | Z29: =SUM(W29:Y29) -> 832.5
A30: HONIX (elevadores) (01 de um mês a 30 do mesmo mês) | B30: Contratos SPI | C30: 2 | D30: VGM01N01I7N | E30: 21051130000123 | F30: 23106.053280/2018-11 | G30: 45920 | H30: =IF((G30-TODAY())<0,"EXPIRADO", IF((G30-TODAY())<=60,"EM BREVE","NO PRAZO")) -> EXPIRADO | J30: 090/2019 | L30: =M30/12 -> 39124.22 | M30: 469490.64 | N30: 82722.66 | P30: =SUM(N30:O30) -> 82722.66 | Y30: =L30-4474.2 -> 34650.02 | Z30: =SUM(W30:Y30) -> 34650.02
A31: - ENERGIA ELÉTRICA - SPI | B31: Contratos SPI | C31: 3 | D31: VGM01N01I2N | E31: 07522669000192 | K31: 40000 | M31: =K31*12 -> 480000 | N31: 69292.17 | O31: 2965.4 | P31: =SUM(N31:O31) -> 72257.57 | T31: =40000-12743 -> 27257 | V31: =K31-23261 -> 16739 | X31: =K31-32258 -> 7742 | Y31: =K31 -> 40000 | Z31: =SUM(W31:Y31) -> 47742
A32: - CAESB - SPI | B32: Contratos SPI | C32: 3 | D32: VGM01N01I3N | E32: 00082024000137 | K32: 136350 | M32: =K32*12 -> 1636200 | N32: 1162.83 | O32: 0 | P32: =SUM(N32:O32) -> 1162.83 | S32: =K32-P32 -> 135187.17 | T32: =K32 -> 136350 | W32: =K32-1163 -> 135187 | X32: =K32 -> 136350 | Y32: =K32 -> 136350 | Z32: =SUM(W32:Y32) -> 407887
A33: - Despesas de Condomínio | B33: Contratos SPI | C33: 1 | D33: VGM01N01K6N | F33: 23106.134844/2020-22 | K33: 245000 | M33: =K33*12 -> 2940000 | N33: 258564.89 | O33: 0 | P33: =SUM(N33:O33) -> 258564.89 | S33: =K33-P33 -> -13564.89 | U33: =K33-8976 -> 236024 | V33: =K33-49349 -> 195651 | X33: =K33-13565 -> 231435 | Y33: =K33 -> 245000 | Z33: =SUM(W33:Y33) -> 476435
A34: PGFN: 1° ATI, negociação conta n°: 7300348 ( Consulta Acordo n°1 - Conta da Negociação 7300348 (SEI nº 10575553) SEI origem: 23106.094258/2021-19 SEI pagamento em 2023: 23106.005996/2023-61 Despacho que contém explicação: 10567234 do SEI 23106.132563/2023-88 Acordo de Transação Individual (ATI), referente à dívida ativa tributária junto à PGFN -débitos previdenciários Empenho atual: 2024NE000285 | B34: Contratos Diversos | C34: 2 | D34: VGH01N0112N | F34: 23106.094258/2021-19 23106.001775/2022-33 23106.005996/2023-61 23106.044758/2024-52 23106.132563/2023-88 | G34: 60 parcelas (já pagou 20/60) | K34: 285000 | M34: =K34*12 -> 3420000 | N34: =237631.38+50000 -> 287631.38 | O34: 0 | P34: =SUM(N34:O34) -> 287631.38 | V34: =285000-P34 -> -2631.38 | X34: 285000 | Y34: 285000 | Z34: =SUM(W34:Y34) -> 570000
A35: PGFN: 2° ATI, negociação conta n°: 8815031 (Consulta Acordo n°2 - Conta da Negociação 8815031 (SEI nº 10576277)) SEI origem: 23106.059565/2023-15 SEI pagamento 2023:23106.123083/2023-26 que foi realizado o pagamento da entrada e no 23106.128684/2023-25 constará os demais pagamentos. Despacho que contém explicação: 10567234 do SEI 23106.132563/2023-88 Guias de Recolhimento de FGTS e Informações à Previdência Social (GFIP) das competências de janeiro/2011, fevereiro/2011, abril/2011, junho/2011 e novembro/2011 Empenho atual: 2023NE003705; 2024NE000487 | B35: Contratos Diversos | C35: 2 | D35: VGH01N0112N | F35: 23106.059565/2023-15 23106.128684/2023-25 23106.044758/2024-52 23106.132563/2023-88 | G35: 60 parcelas (já pagou 10/60) | K35: 28500 | M35: =K35*12 -> 342000 | N35: =35030.6+24893 -> 59923.6 | O35: 0 | P35: =SUM(N35:O35) -> 59923.6 | V35: =28500-24893 -> 3607 | Y35: 28500 | Z35: =SUM(W35:Y35) -> 28500
A37: Total da despesa | K37: =SUM(K4:K35) -> 5683749.6 | L37: =SUM(L4:L35) -> 6559201.3 | M37: =SUM(M4:M35) -> 1.4645932e+08 | N37: =SUM(N4:N35) -> 14825482 | O37: =SUM(O4:O35) -> 404213.89 | P37: =SUM(P4:P35) -> 15229696 | Q37: =SUM(Q4:Q35) -> 0 | R37: =SUM(R4:R35) -> 0 | ... Z37: =SUM(Z4:Z35) -> 19423878
Y39: limite | Z39: 21927315
Y40: CI | Z40: 1032613
Y41: compostagem | Z41: 855000
Z43: =Z39-Z40-Z41 -> 20039702
Y45: detalhado | Z45: 205548.5
Z46: 4401.63
Z47: 221.06
Z48: 1619.08
Z49: 0.49
Z50: 6739
Z51: 257776
Z52: 136055.06
Z53: 350.77
Z54: 2250
Z56: =Z43-SUM(Z45:Z54) -> 19424741
Y57: demais Ações | Z57: ?
Z58: =Z56-Z37 -> 862.713
A60: Descrição das despesas | B60: UGR | C60: Prioridade | D60: PI 2025 | E60: CNPJ | F60: Processo | G60: Vigência | H60: Status do Contrato | I60: Situação da prorrogação | J60: nº Contrato | K60: Valor Contrato Média mensal | L60: Valor Cont Continuado Mensal | M60: Total estimado Anual | N60: Saldo Empenhos 2025 | O60: Saldo de Empenhos RAP | P60: Total RAP + Empenho | Q60: 45658 | R60: 45689 | S60: 45717 | T60: 45748 | U60: 45778 | V60: 45809 | W60: 45839 | X60: 45870 | Y60: 45901 | Z60: Total necessário
A61: Pasep - UnB | B61: DGP/ folha | C61: 1 | D61: VGM01N01N1N | K61: 810000 | M61: =K61*12 -> 9720000 | N61: 0 | O61: 0 | P61: =SUM(N61:O61) -> 0 | U61: =810000-556810 -> 253190 | V61: =K61 -> 810000 | W61: =K61 -> 810000 | X61: =K61 -> 810000 | Y61: =K61 -> 810000 | Z61: =SUM(W61:Y61)+101000 -> 2531000
A62: CRUZEIRO CONTROLE DE PRAGAS E DESENTUPIMENTO | B62: PRC | C62: 2 | D62: VGM01N01D3N | E62: 22.575.793/0001-00 | F62: 23106.058637/2021-45 | G62: 45980 | H62: =IF((G62-TODAY())<0,"EXPIRADO", IF((G62-TODAY())<=60,"EM BREVE","NO PRAZO")) -> EM BREVE | J62: 1222/2024 | K62: =M62/12 -> 65625.02 | M62: 787500.24 | N62: 55376.88 | O62: 5443 | P62: =SUM(N62:O62) -> 60819.88 | U62: =K62-P62 -> 4805.14 | V62: =K62-60820 -> 4805.02 | W62: =K62-60820 -> 4805.02 | X62: =K62 -> 65625.02 | Z62: =SUM(W62:Y62) -> 70430.04
A63: VILELA SERVIÇO DE PAISAGISMO, PARQUES E JARDINS LTDA (jardinagem) | B63: PRC | C63: 2 | D63: VGM01N01A5N | E63: 32.751.565/0001-05 | F63: 23106.028705/2019-27 | G63: 45866 | H63: =IF((G63-TODAY())<0,"EXPIRADO", IF((G63-TODAY())<=60,"EM BREVE","NO PRAZO")) -> EXPIRADO | I63: solicitou-se à empresa interesse em renovar | J63: 1217/2023 | K63: 298000 | M63: 3119907.7 | N63: 271060.23 | O63: 0 | P63: =SUM(N63:O63) -> 271060.23 | T63: =291576.42-21573 -> 270003.42 | U63: =K63-P63 -> 26939.77 | V63: =K63 -> 298000 | W63: =K63-271060 -> 26940 | Z63: =SUM(W63:Y63) -> 26940
A64: - TRANSMONICI TRANSPORTE E TURISMO (ônibus rodoviário executivo) | B64: PRC | C64: 2 | D64: VGM01N01K1N | E64: 09169349000126 | F64: 23106.000890/2021-18 | G64: 46062 | H64: =IF((G64-TODAY())<0,"EXPIRADO", IF((G64-TODAY())<=60,"EM BREVE","NO PRAZO")) -> NO PRAZO | J64: 604/2022 | K64: 90000 | M64: =K64*12 -> 1080000 | N64: 116120.9 | O64: 0 | P64: =SUM(N64:O64) -> 116120.9 | X64: =90000-26121 -> 63879 | Y64: =K64 -> 90000 | Z64: =SUM(W64:Y64) -> 153879
A65: ARTES GRÁFICA COMÉRCIO E REPRESENTAÇÕES EIRELI (serviços continuados de Designer Gráfico) | B65: Contratos DCA | C65: 2 | D65: VGM01N01P4N | E65: 05606994000108 | F65: 23106.148085/2022-47 | G65: 46127 | H65: =IF((G65-TODAY())<0,"EXPIRADO", IF((G65-TODAY())<=60,"EM BREVE","NO PRAZO")) -> NO PRAZO | J65: 147/2022 | L65: =12640.77 -> 12640.77 | M65: =L65*12 -> 151689.24 | N65: 0 | O65: 0 | P65: =SUM(N65:O65) -> 0 | U65: =L65-536 -> 12104.77 | W65: =L65 -> 12640.77 | X65: =L65 -> 12640.77 | Y65: =L65 -> 12640.77 | Z65: =SUM(W65:Y65) -> 37922.31
A66: - ALFA E OMEGA Apoio Técnico EDU | B66: Contratos DCA | C66: 1 | D66: VGM01N01D5N | E66: 16650774000106 | F66: 23106.011967/2019-52 | G66: 46131 | H66: =IF((G66-TODAY())<0,"EXPIRADO", IF((G66-TODAY())<=60,"EM BREVE","NO PRAZO")) -> NO PRAZO | J66: 022/2021 | L66: =M66/12 -> 24316.78 | M66: 291801.36 | N66: 50982.01 | O66: 0 | P66: =SUM(N66:O66) -> 50982.01 | S66: 865.66 | T66: =L66-2497 -> 21819.78 | U66: =L66-22360 -> 1956.78 | V66: =L66 -> 24316.78 | Y66: =L66-2348 -> 21968.78 | Z66: =SUM(W66:Y66) -> 21968.78
A67: RCS Tecnologia LTDA - copeiragem | B67: Contratos DCA | C67: 1 | D67: VGM01N01O2N | E67: 08220952000122 | F67: 23106.125355/2019-46 23106.035022/2021-41 | G67: 45929 | H67: =IF((G67-TODAY())<0,"EXPIRADO", IF((G67-TODAY())<=60,"EM BREVE","NO PRAZO")) -> EXPIRADO | I67: Foi para a PF solicitando prorrogação com vigência em 29/09/2025 | J67: 07/2021 | L67: 131667.49 | M67: =L67*12 -> 1580009.9 | N67: 264774.55 | O67: 0 | P67: =SUM(N67:O67) -> 264774.55 | T67: 131667 | V67: =L67 -> 131667.49 | Y67: =L67 -> 131667.49 | Z67: =SUM(W67:Y67) -> 131667.49
A68: T&S Engenharia Telemática e Sistemas LTDA - contínuo | B68: Contratos DCA | C68: 1 | D68: VGM01N01B7N | E68: 00712411000100 | F68: 23106.034924/2021-60 | G68: 45745 | H68: =IF((G68-TODAY())<0,"EXPIRADO", IF((G68-TODAY())<=60,"EM BREVE","NO PRAZO")) -> EXPIRADO | I68: Foi para PF, prorrogação excepcional | J68: 006/2021 | L68: 183316.03 | M68: =L68*12 -> 2199792.4 | N68: 183316.03 | O68: 0 | P68: =SUM(N68:O68) -> 183316.03 | S68: =L68-P68 -> 0 | T68: =L68 -> 183316.03 | X68: =L68 -> 183316.03 | Y68: =L68 -> 183316.03 | Z68: =SUM(W68:Y68) -> 366632.06
A69: Phoenix Comércio e Serviços de Limpeza LTDA - Almoxarifado e de transporte interno de móveis e materiais | B69: Contratos DCA | C69: 1 | D69: VGM01N01F7N | E69: 12978051000171 | F69: 23106.001099/2022-06 | G69: 45902 | H69: =IF((G69-TODAY())<0,"EXPIRADO", IF((G69-TODAY())<=60,"EM BREVE","NO PRAZO")) -> EXPIRADO | J69: 111/2022 | L69: 117871.46 | M69: =L69*12 -> 1414457.5 | N69: 235742.92 | O69: 0 | P69: =SUM(N69:O69) -> 235742.92 | T69: =117871-49371 -> 68500 | U69: =L69-P69 -> -117871.46 | V69: =L69 -> 117871.46 | Y69: =L69 -> 117871.46 | Z69: =SUM(W69:Y69) -> 117871.46
A70: - RCA (Limpeza e Conservação) | B70: Contratos DCA | C70: 1 | D70: VGM01N01A7N | E70: 69.207.850/0001-61 | F70: 23106.057738/2021-07 | G70: 46402 | H70: =IF((G70-TODAY())<0,"EXPIRADO", IF((G70-TODAY())<=60,"EM BREVE","NO PRAZO")) -> NO PRAZO | J70: 02/2022 | L70: 1889237.8 | M70: =L70*12 -> 22670853 | N70: 2846580.6 | O70: 0 | P70: =SUM(N70:O70) -> 2846580.6 | T70: =1882331-116567 -> 1765764 | V70: =L70 -> 1889237.8 | X70: =L70-957343 -> 931894.76 | Y70: =L70 -> 1889237.8 | Z70: =SUM(W70:Y70)+1000000 -> 3821132.5
A71: G&E SERVICOS TERCEIRIZADOS LTDA (PORTARIA) | B71: Contratos DCA | C71: 1 | D71: VGM01N01A9N | E71: 08744139000151 | F71: 23106.085840/2022-75 23106.005560/2022-91 23106.046596/2024-97 | G71: 46020 | H71: =IF((G71-TODAY())<0,"EXPIRADO", IF((G71-TODAY())<=60,"EM BREVE","NO PRAZO")) -> EM BREVE | J71: 081/2022 | L71: =1205875.51+32423.44 -> 1238298.9 | M71: =L71*12 -> 14859587 | N71: 1859307.3 | O71: 0 | P71: =SUM(N71:O71) -> 1859307.3 | S71: =L71-O71 -> 1238298.9 | T71: =1238299-555 -> 1237744 | V71: =L71 -> 1238298.9 | X71: =L71-621008 -> 617290.95 | Y71: =L71 -> 1238298.9 | Z71: =SUM(W71:Y71) -> 1855589.9
A72: G&E SERVICOS TERCEIRIZADOS LTDA - serviços continuados de motorista | B72: Contratos DCA | C72: 1 | D72: VGM01N01P5N | E72: 08744139000151 | F72: 23106.038810/2022-70 | G72: 46166 | H72: =IF((G72-TODAY())<0,"EXPIRADO", IF((G72-TODAY())<=60,"EM BREVE","NO PRAZO")) -> NO PRAZO | J72: 001/2023 | L72: 236438.33 | M72: =L72*12 -> 2837260 | N72: 332837.48 | O72: 0 | P72: =SUM(N72:O72) -> 332837.48 | T72: 190000 | V72: =L72-171405 -> 65033.331 | X72: =L72-96399 -> 140039.33 | Y72: =L72 -> 236438.33 | Z72: =SUM(W72:Y72) -> 376477.66
A73: Total da despesa | K73: =SUM(K41:K71) -> 1263625 | L73: =SUM(L41:L71) -> 3597349.2 | M73: =SUM(M41:M71) -> 57875599 | N73: =SUM(N41:N71) -> 5883261.5 | O73: =SUM(O41:O71) -> 5443 | P73: =SUM(P41:P71) -> 5888704.5 | Q73: =SUM(Q41:Q71) -> 45658 | R73: =SUM(R41:R71) -> 45689 | ... V73: =SUM(V41:V71) -> 4560006.5 | W73: =SUM(W61:W72) -> 854385.79 | X73: =SUM(X61:X72) -> 2824685.9 | Y73: =SUM(Y61:Y72) -> 4731439.6 | Z73: =SUM(Z61:Z72) -> 9511511.2
A77: Descrição das despesas | B77: UGR | C77: Prioridade | D77: PI 2025 | E77: CNPJ | F77: Processo | G77: Vigência | H77: Status do Contrato | I77: Situação da prorrogação | J77: nº Contrato | K77: Valor Contrato Média mensal | L77: Valor Cont Continuado Mensal | M77: Total estimado Anual | N77: Saldo Empenhos 2025 | O77: Saldo de Empenhos RAP | P77: Total RAP + Empenho | Q77: 45658 | R77: 45689 | S77: 45717 | T77: 45748 | U77: 45778 | V77: 45809 | W77: 45839 | X77: 45870 | Y77: 45901 | Z77: Total necessário
A78: Life Defense (Segurança) | B78: Contratos DCA | C78: 1 | D78: VGM01N01A8N | E78: 02674687000176 | F78: 23106.016977/2013-99 23106.083943/2018-14 23106.047642/2024-75 | G78: 46097 | H78: =IF((G78-TODAY())<0,"EXPIRADO", IF((G78-TODAY())<=60,"EM BREVE","NO PRAZO")) -> NO PRAZO | I78: Foi solicitado parecer à PF para prorrogação. | J78: 011/2020 | L78: 1617878.6 | M78: =L78*12 -> 19414543 | N78: 2426817.9 | O78: 0 | P78: =SUM(N78:O78) -> 2426817.9 | T78: =L78 -> 1617878.6 | V78: =L78 -> 1617878.6 | X78: =L78-808939 -> 808939.59 | Y78: =L78 -> 1617878.6 | Z78: =SUM(W78:Y78)+1000000 -> 3426818.2
A79: MPE ENGENHARIA E SERVICOS S/A (serviços comuns de engenharia, incluindo manutenção, conservação, adaptação, reparação e instalação de infraestruturas prediais e imobiliárias) | B79: Contratos DCA | C79: 2 | D79: VGM01N01H3N | E79: 04743858000105 | F79: 23106.149436/2022-37 | G79: 46114 | H79: =IF((G79-TODAY())<0,"EXPIRADO", IF((G79-TODAY())<=60,"EM BREVE","NO PRAZO")) -> NO PRAZO | J79: 1201/2023 | K79: 1600000 | M79: =K79*12 -> 19200000 | N79: =1387659.05 -> 1387659.1 | O79: 6102.62 | P79: =SUM(N79:O79) -> 1393761.7 | V79: =K79-836351 -> 763649 | W79: =K79-1393762 -> 206238 | X79: =K79 -> 1600000 | Z79: =SUM(W79:Y79) -> 1806238
A80: MPE - Adequação e impermeabilização | B80: Contratos DCA | C80: 2 | D80: VGA02N43E3N | E80: 04743858000105 | F80: 23106.149228/2022-38 | G80: 46022 | H80: =IF((G80-TODAY())<0,"EXPIRADO", IF((G80-TODAY())<=60,"EM BREVE","NO PRAZO")) -> EM BREVE | J80: 1110/2024 | K80: =M80/12 -> 1924342.1 | M80: =8383552.34+14708553.16 -> 23092106 | N80: 2198081.8 | O80: 378631.87 | P80: =SUM(N80:O80) -> 2576713.6 | V80: =K80-P80 -> -652371.52 | X80: =K80-652371.53 -> 1271970.6 | Z80: =SUM(W80:Y80) -> 1271970.6
A81: POLI ENGENHARIA LTDA (serviços comuns de engenharia, incluindo manutenção, conservação, adaptação, reparação e instalação de infraestruturas prediais e imobiliárias) | B81: Contratos DCA | C81: 2 | D81: VGM01N01H3N | E81: 00700518000138 | F81: 23106.117479/2022-53 | G81: 46146 | H81: =IF((G81-TODAY())<0,"EXPIRADO", IF((G81-TODAY())<=60,"EM BREVE","NO PRAZO")) -> NO PRAZO | J81: 1226/2022 | K81: 145000 | M81: =K81*12 -> 1740000 | N81: =64791.35+188772.36 -> 253563.71 | O81: 10932 | P81: =SUM(N81:O81) -> 264495.71 | X81: =K81-119495.71 -> 25504.29 | Y81: =K81 -> 145000 | Z81: =SUM(W81:Y81) -> 170504.29
A82: Ágil (Serviços Agropecuários) | B82: Contratos DCA | C82: 1 | D82: VGM01N01C5N | E82: 72620735000129 | F82: 23106.076196/2018-68 23106.030688/2022-93 | G82: 46097 | H82: =IF((G82-TODAY())<0,"EXPIRADO", IF((G82-TODAY())<=60,"EM BREVE","NO PRAZO")) -> NO PRAZO | I82: Solicitado parecer à PF para prorrogação. | J82: 25/2020 | L82: 458615.91 | M82: =L82*12 -> 5503390.9 | N82: 917231.82 | P82: =SUM(N82:O82) -> 917231.82 | S82: =L82-O82 -> 458615.91 | V82: =L82 -> 458615.91 | Y82: =L82 -> 458615.91 | Z82: =SUM(W82:Y82) -> 458615.91
A83: Contrato de Limpeza - UnB Cerrado (AP PISCINAS EIRELI) | B83: UnB Cerrado | C83: 1 | D83: VGM01N01A7N | E83: 08475822000130 | F83: 23106.116355/2019-55 | G83: 45889 | H83: =IF((G83-TODAY())<0,"EXPIRADO", IF((G83-TODAY())<=60,"EM BREVE","NO PRAZO")) -> EXPIRADO | J83: 112/2020 | L83: =M83/12 -> 5331.32 | M83: 63975.84 | N83: 4395.71 | O83: 0 | P83: =SUM(N83:O83) -> 4395.71 | S83: =L83-P83 -> 935.61 | T83: =L83-4688 -> 643.32 | V83: =5331-P83 -> 935.29 | W83: =L83-4396 -> 935.32 | X83: =L83 -> 5331.32 | Y83: =L83 -> 5331.32 | Z83: =SUM(W83:Y83) -> 11597.96
A84: - Segurança - ULTRASEG Segurança Patrimonial Ltda | B84: UnB Cerrado | C84: 1 | D84: VGM01N01A8N | E84: 09151154000159 | F84: 23106.020717/2022-17 | G84: 45938 | H84: =IF((G84-TODAY())<0,"EXPIRADO", IF((G84-TODAY())<=60,"EM BREVE","NO PRAZO")) -> EXPIRADO | J84: 1207/2022 | L84: 23452.22 | M84: =L84*12 -> 281426.64 | N84: 46904.44 | O84: 0 | P84: =SUM(N84:O84) -> 46904.44 | V84: =L84 -> 23452.22 | Y84: =L84 -> 23452.22 | Z84: =SUM(W84:Y84) -> 23452.22
A85: Recepcionista – AMR LIMPEZA E LOCACAO DE AUTOMOVEIS LTDA | B85: UnB Cerrado | C85: 1 | D85: VGM01N01B3N | E85: 10.258.826/0001-09 | F85: 23106.100112/2023-81 | G85: 46068 | H85: =IF((G85-TODAY())<0,"EXPIRADO", IF((G85-TODAY())<=60,"EM BREVE","NO PRAZO")) -> NO PRAZO | J85: 12/2024 | L85: =M85/12 -> 4290.91 | M85: 51490.92 | N85: 4537 | O85: 0 | P85: =SUM(N85:O85) -> 4537 | V85: =L85 -> 4290.91 | X85: =L85 -> 4290.91 | Y85: =L85 -> 4290.91 | Z85: =SUM(W85:Y85) -> 8581.82
A86: '- GESTOR SERVICOS EMPRESARIAIS (Portaria - SPI) | B86: Contratos SPI | C86: 1 | D86: VGM01N01E8N | E86: 02.685.728/0001-20 | F86: 23106.047067/2021-68 | G86: 46434 | H86: =IF((G86-TODAY())<0,"EXPIRADO", IF((G86-TODAY())<=60,"EM BREVE","NO PRAZO")) -> NO PRAZO | J86: 001/2022 | L86: 382896.8 | M86: =L86*12 -> 4594761.6 | N86: 385232.05 | O86: 0 | P86: =SUM(N86:O86) -> 385232.05 | S86: =L86-P86 -> -2335.25 | V86: =L86-P86 -> -2335.25 | X86: =L86 -> 382896.8 | Y86: =L86 -> 382896.8 | Z86: =SUM(W86:Y86) -> 765793.6
A87: - SEFIX (Limpeza e Conservação - SPI) | B87: Contratos SPI | C87: 1 | D87: VGM01N01E9N | E87: 13258899000199 | F87: 23106.047036/2021-15 | G87: 45854 | H87: =IF((G87-TODAY())<0,"EXPIRADO", IF((G87-TODAY())<=60,"EM BREVE","NO PRAZO")) -> EXPIRADO | I87: em renovação | J87: 033/2022 | L87: 193823.77 | M87: =L87*12 -> 2325885.2 | N87: 193823.77 | O87: 0 | P87: =SUM(N87:O87) -> 193823.77 | T87: =L87 -> 193823.77 | V87: =L87 -> 193823.77 | X87: =L87 -> 193823.77 | Y87: =L87 -> 193823.77 | Z87: =SUM(W87:Y87) -> 387647.54
A88: HONIX (elevadores) | B88: Contratos SPI | C88: 2 | D88: VGM01N01I7N | E88: 21051130000123 | F88: 23106.053280/2018-11 | G88: 45920 | H88: =IF((G88-TODAY())<0,"EXPIRADO", IF((G88-TODAY())<=60,"EM BREVE","NO PRAZO")) -> EXPIRADO | J88: 090/2019 | L88: =M88/12 -> 39124.22 | M88: 469490.64 | N88: 82722.66 | P88: =SUM(N88:O88) -> 82722.66 | Y88: =L88-4474.2 -> 34650.02 | Z88: =SUM(W88:Y88) -> 34650.02
A89: - ENERGIA ELÉTRICA - SPI | B89: Contratos SPI | C89: 3 | D89: VGM01N01I2N | E89: 07522669000192 | K89: 40000 | M89: =K89*12 -> 480000 | N89: 69292.17 | O89: 2965.4 | P89: =SUM(N89:O89) -> 72257.57 | T89: =40000-12743 -> 27257 | V89: =K89-23261 -> 16739 | X89: =K89-32258 -> 7742 | Y89: =K89 -> 40000 | Z89: =SUM(W89:Y89) -> 47742
A90: - CAESB - SPI | B90: Contratos SPI | C90: 3 | D90: VGM01N01I3N | E90: 00082024000137 | K90: 136350 | M90: =K90*12 -> 1636200 | N90: 1162.83 | O90: 0 | P90: =SUM(N90:O90) -> 1162.83 | S90: =K90-P90 -> 135187.17 | T90: =K90 -> 136350 | W90: =K90-1163 -> 135187 | X90: =K90 -> 136350 | Y90: =K90 -> 136350 | Z90: =SUM(W90:Y90) -> 407887
A91: - Despesas de Condomínio | B91: Contratos SPI | C91: 1 | D91: VGM01N01K6N | F91: 23106.134844/2020-22 | K91: 245000 | M91: =K91*12 -> 2940000 | N91: 258564.89 | O91: 0 | P91: =SUM(N91:O91) -> 258564.89 | S91: =K91-P91 -> -13564.89 | U91: =K91-8976 -> 236024 | V91: =K91-49349 -> 195651 | X91: =K91-13565 -> 231435 | Y91: =K91 -> 245000 | Z91: =SUM(W91:Y91) -> 476435
A92: PGFN: 1° ATI, negociação conta n°: 7300348 ( Consulta Acordo n°1 - Conta da Negociação 7300348 | B92: Contratos Diversos | C92: 2 | D92: VGH01N0112N | F92: 23106.094258/2021-19 23106.001775/2022-33 23106.005996/2023-61 23106.044758/2024-52 23106.132563/2023-88 | G92: 60 parcelas (já pagou 20/60) | K92: 285000 | M92: =K92*12 -> 3420000 | N92: =237631.38+50000 -> 287631.38 | O92: 0 | P92: =SUM(N92:O92) -> 287631.38 | V92: =285000-P92 -> -2631.38 | X92: 285000 | Y92: 285000 | Z92: =SUM(W92:Y92) -> 570000
A93: PGFN: 2° ATI, negociação conta n°: 8815031 (Consulta Acordo n°2 - Conta da Negociação 8815031 | B93: Contratos Diversos | C93: 2 | D93: VGH01N0112N | F93: 23106.059565/2023-15 23106.128684/2023-25 23106.044758/2024-52 23106.132563/2023-88 | G93: 60 parcelas (já pagou 10/60) | K93: 28500 | M93: =K93*12 -> 342000 | N93: =35030.6+24893 -> 59923.6 | O93: 0 | P93: =SUM(N93:O93) -> 59923.6 | V93: =28500-24893 -> 3607 | Y93: 28500 | Z93: =SUM(W93:Y93) -> 28500
A94: Total da despesa | K94: =SUM(K65:K92) -> 5639317.1 | L94: =SUM(L65:L92) -> 10156551 | M94: =SUM(M65:M92) -> 1.8909432e+08 | N94: =SUM(N65:N92) -> 20174424 | O94: =SUM(O65:O92) -> 404074.89 | P94: =SUM(P65:P92) -> 20578498 | Q94: =SUM(Q65:Q92) -> 91316 | R94: =SUM(R65:R92) -> 91378 | ... V94: =SUM(V65:V92) -> 10689939 | W94: =SUM(W78:W93) -> 342360.32 | X94: =SUM(X78:X93) -> 4953284.3 | Y94: =SUM(Y78:Y93) -> 3600789.5 | Z94: =SUM(Z78:Z93) -> 9896434.1
Z97: =Z73+Z94 -> 19407945

Sheet Prog 03.06
A1: Acompanhamento de Contratos*
A2: Data de Atualização: 11/03/2025
A3: Descrição das despesas | B3: UGR | C3: Prioridade | D3: PI 2025 | E3: CNPJ | F3: nº Contrato | G3: Valor a Empenhar
A4: Life Defense (Segurança) | B4: Contratos DCA | C4: 1 | D4: VGM01N01A8N | E4: 02674687000176 | F4: 011/2020 | G4: 4044696.5
A5: G&E SERVICOS TERCEIRIZADOS LTDA (PORTARIA) | B5: Contratos DCA | C5: 1 | D5: VGM01N01A9N | E5: 08744139000151 | F5: 081/2022 | G5: 3095747.4
A6: G&E SERVICOS TERCEIRIZADOS LTDA - serviços continuados de motorista | B6: Contratos DCA | C6: 1 | D6: VGM01N01P5N | E6: 08744139000151 | F6: 001/2023 | G6: 537909.99
A7: Total da despesa | G7: =SUM(G4:G6) -> 7678353.8
A10: Descrição das despesas | B10: UGR | C10: Prioridade | D10: PI 2025 | E10: CNPJ | F10: nº Contrato | G10: Valor a Empenhar
A11: CRUZEIRO CONTROLE DE PRAGAS E DESENTUPIMENTO | B11: PRC | C11: 2 | D11: VGM01N01D3N | E11: 22.575.793/0001-00 | F11: 1222/2024 | G11: 136055.06
A12: VILELA SERVIÇO DE PAISAGISMO, PARQUES E JARDINS LTDA (jardinagem) | B12: PRC | C12: 2 | D12: VGM01N01A5N | E12: 32.751.565/0001-05 | F12: 1217/2023 | G12: 290000
A13: - TRANSMONICI TRANSPORTE E TURISMO (ônibus rodoviário executivo) | B13: PRC | C13: 2 | D13: VGM01N01K1N | E13: 09169349000126 | F13: 604/2022 | G13: 98246
A14: 3P HGM solução visual (serviços de comunicação visual) | B14: PRC | C14: 2 | D14: VGM01N01O7N | E14: 34.998.513/0001-55 | F14: 1217/2022 | G14: 83593
A15: Restaurante ISM EIRELI (diretoria RU) - Ação 20RK planilha DRU | B15: Contrato DAC/RU | C15: 1 | D15: VGM01N01B5N | E15: 04228626001263 | F15: 31/2021 | G15: 3916409.8
A16: Total da despesa | G16: =SUM(G11:G15) -> 4524303.8
A19: Descrição das despesas | B19: UGR | C19: Prioridade | D19: PI 2025 | E19: CNPJ | F19: nº Contrato | G19: Valor a Empenhar
A20: Pasep - UnB | B20: DGP/ folha | C20: 1 | D20: VGM01N01N1N | G20: 2430000
A21: - Serviços de Água e Esgoto (PRC) | B21: INFRA | C21: 3 | D21: VGM01N01I3N | E21: 82024000137 | G21: 1395599
A22: Energia Elétrica UnB Cerrado - CONTRATO CCER - ENEL N. 36/2020 e CELG DISTRIBUIÇÃO S.A - CELG D, Equatorial Goiás Distribuidora de Energia S/A | B22: UnB Cerrado | C22: 3 | D22: VGM01N01I2N | E22: 1543032000104 | F22: 36/2020 | G22: 4431.09
A23: QUALIFICAR - Suporte TI (Serviços de Manutenção dos Computadores da UnB) | B23: STI | C23: 2 | D23: VGM01N01A3N | E23: 04.752.792/0001-01 | F23: 512/2025 | G23: 546864
A24: ELYON BRASIL - ESPLANADA SERVICOS TERCEIRIZADOS EIRELI | B24: Contratos DCA | C24: 1 | D24: VGM01N01E4N | E24: 01099686000182 | F24: 111/2020 | G24: 20877.34
A25: - ALFA E OMEGA Apoio Técnico EDU | B25: Contratos DCA | C25: 1 | D25: VGM01N01D5N | E25: 16650774000106 | F25: 022/2021 | G25: 72950.34
A26: RCS Tecnologia LTDA - copeiragem | B26: Contratos DCA | C26: 1 | D26: VGM01N01O2N | E26: 08220952000122 | F26: 07/2021 | G26: 395002.47
A27: Phoenix Comércio e Serviços de Limpeza LTDA - Almoxarifado e de transporte interno de móveis e materiais | B27: Contratos DCA | C27: 1 | D27: VGM01N01F7N | E27: 12978051000171 | F27: 111/2022 | G27: 353614.38
A28: - RCA (Limpeza e Conservação) | B28: Contratos DCA | C28: 1 | D28: VGM01N01A7N | E28: 69207850000161 | F28: 02/2022 | G28: 4723094.4
A29: Tratador de Piscinas CO e casa Oscar Niemayer - (AP Piscinas EIRELI) - em fase de renovação | B29: Contratos Diversos | C29: 1 | D29: VGM01N01E2N | E29: 08475822000130 | F29: 93/2020 | G29: 10078.695
A30: - Correios - ECT -reduziu porque não temos mais contrato de encomendas | B30: Comunicação | C30: 2 | D30: VGM01N01J1N | E30: 34028316000707 | F30: 1207/2023 | G30: 1269
A31: - Empresa Brasil de Comunicação (EBC) | B31: Comunicação | C31: 2 | D31: VGM01N01I9N | F31: 213/2020 | G31: 2000
A32: Jardinagem - UnB Cerrado - AMBIENTAL DO BRASIL ESTUDOS E PROJETOS AMBIENTAIS LTDA | B32: UnB Cerrado | C32: 2 | D32: VGM01N01A5N | E32: 09150575000165 | F32: 659/2020 | G32: 3945.9275
A33: Recepcionista – AMR LIMPEZA E LOCACAO DE AUTOMOVEIS LTDA | B33: UnB Cerrado | C33: 1 | D33: VGM01N01B3N | E33: 10.258.826/0001-09 | F33: 12/2024 | G33: 12872.73
A34: FORMIGA ENGENHARIA E ARQUITETURA LTDA, especializada na prestação de serviços continuados, sem dedicação exclusiva de mão de obra, para realização de vistorias de entrada e saída nos imóveis de propriedade da Universidade de Brasília | B34: Contratos SPI | C34: 2 | D34: VGM01N01D2N | E34: 22.352.353/0001-93 | F34: 93/2024 | G34: 7018
A35: Contrato de Limpeza - UnB Cerrado (AP PISCINAS EIRELI) | B35: UnB Cerrado | C35: 1 | D35: VGM01N01A7N (VGM01N1F2N-PI indevido) | E35: 08475822000130 | F35: 112/2020 | G35: 11305.06
A36: Total da despesa | G36: =SUM(G20:G35) -> 9990922.4
A38: Descrição das despesas | B38: UGR | C38: Prioridade | D38: PI 2025 | E38: CNPJ | F38: nº Contrato | G38: Valor a Empenhar
A39: MPE ENGENHARIA E SERVICOS S/A (serviços comuns de engenharia, incluindo manutenção, conservação, adaptação, reparação e instalação de infraestruturas prediais e imobiliárias) | B39: Contratos DCA | C39: 2 | D39: VGM01N01H3N | E39: 04743858000105 | F39: 1201/2023 | G39: 2363649
A40: MPE - Adequação e impermeabilização | B40: Contratos DCA | C40: 2 | D40: VGA02N43E3N | E40: 04743858000105 | F40: 1110/2024 | G40: 2198081.8
A41: POLI ENGENHARIA LTDA (serviços comuns de engenharia, incluindo manutenção, conservação, adaptação, reparação e instalação de infraestruturas prediais e imobiliárias) | B41: Contratos DCA | C41: 2 | D41: VGM01N01H3N | E41: 00700518000138 | F41: 1226/2022 | G41: 102806
A42: Ágil (Serviços Agropecuários) | B42: Contratos DCA | C42: 1 | D42: VGM01N01C5N | E42: 72620735000129 | F42: 25/2020 | G42: 1375847.7
A43: - Segurança - ULTRASEG Segurança Patrimonial Ltda | B43: UnB Cerrado | C43: 1 | D43: VGM01N01A8N | E43: 09151154000159 | F43: 1207/2022 | G43: 70356.66
A44: '- GESTOR SERVICOS EMPRESARIAIS (Portaria - SPI) | B44: Contratos SPI | C44: 1 | D44: VGM01N01E8N | E44: 02685728000120 | F44: 001/2022 | G44: 759746.54
A45: - SEFIX (Limpeza e Conservação - SPI) | B45: Contratos SPI | C45: 1 | D45: VGM01N01E9N | E45: 13258899000199 | F45: 033/2022 | G45: 387647.54
A46: Engemega - (Manutenção de Imóveis gerenciados pela Secretaria de Patrimônio Imobiliário (SPI)) – contrato 1 (contrato antigo) | B46: Contratos SPI | C46: 2 | D46: VGM01N01D4N | E46: 33480104/0001-08 | F46: 1223/2022 | G46: 450108.97
A47: HONIX (elevadores) (01 de um mês a 30 do mesmo mês) | B47: Contratos SPI | C47: 2 | D47: VGM01N01I7N | E47: 21051130000123 | F47: 090/2019 | G47: 39124.22
A48: - ENERGIA ELÉTRICA - SPI | B48: Contratos SPI | C48: 3 | D48: VGM01N01I2N | E48: 07522669000192 | G48: 96739
A49: - CAESB - SPI | B49: Contratos SPI | C49: 3 | D49: VGM01N01I3N | E49: 00082024000137 | G49: 257776
A50: - Despesas de Condomínio | B50: Contratos SPI | C50: 1 | D50: VGM01N01K6N | G50: 685651
A51: PGFN: 1° ATI, negociação conta n°: 7300348 ( Consulta Acordo n°1 - Conta da Negociação 7300348 (SEI nº 10575553) | B51: Contratos Diversos | C51: 2 | D51: VGH01N0112N | G51: 778015.24
A52: PGFN: 2° ATI, negociação conta n°: 8815031 (Consulta Acordo n°2 - Conta da Negociação 8815031 (SEI nº 10576277)) | B52: Contratos Diversos | C52: 2 | D52: VGH01N0112N | G52: 60607
A53: RFB: Conta da Negociação 0211000120 (Consulta Parcelamento n°1 - Conta da Negociação 0211000120 (SEI nº 10580261)) | B53: Contratos Diversos | C53: 2 | D53: VGH01N0112N | G53: 35000
A54: CONCEIÇÃO Aparecida Braga 67186920691 ME (análise e levantamento de conjuntos documentais do arquivo do Cespe/UnB) | B54: Contratos Diversos | C54: 1 | D54: VGM01N01P1N | E54: 41423145000182 | F54: 1230/2022 | G54: 51000
A55: Total da despesa | G55: =SUM(G39:G54) -> 9712156.7
G58: =10000000-G55 -> 287843.32

Sheet Prog 07.04
A1: Acompanhamento de Contratos* | AB1: continuados
A2: Data de Atualização: 11/03/2025
A3: Descrição das despesas | B3: UGR | C3: Prioridade | D3: PI 2025 | E3: CNPJ | F3: Processo | G3: Vigência | H3: Status do Contrato | I3: Situação da prorrogação | J3: nº Contrato | K3: Valor Contrato Média mensal | L3: Valor Cont Continuado Mensal | M3: Total estimado Anual | N3: Saldo Empenhos 2025 | O3: Saldo de Empenhos RAP | P3: Total RAP + Empenho | Q3: 45658 | R3: 45689 | S3: 45717 | T3: 45748 | U3: 45778 | V3: 45809 | W3: 45839 | X3: 45870 | Y3: 45901 | Z3: 45931 | AA3: 45962 | AB3: 45992 | AC3: Total necessário | AD3: Fonte
A4: Pasep - UnB | B4: DGP/ folha | C4: 1 | D4: VGM01N01N1N | K4: 810000 | M4: =K4*12 -> 9720000 | N4: 848332.15 | O4: 0 | P4: =SUM(N4:O4) -> 848332.15 | U4: =810000-38332 -> 771668 | V4: =K4 -> 810000 | W4: =K4 -> 810000 | X4: =K4 -> 810000 | Y4: =K4 -> 810000 | Z4: =K4 -> 810000 | AA4: =K4 -> 810000 | AB4: =K4 -> 810000 | AC4: =T4+U4 -> 771668 | AD4: 1000 | AE4: =SUM(K4:L4)*2 -> 1620000 | AF4: =P4-AE4 -> -771667.85 | AH4: =(SUM(K4:L4)*2)-P4 -> 771667.85
A5: OI SA recuperação judicial | B5: STI | C5: 3 | D5: VGM01N01I4N | E5: 76535764000143 | F5: 23106.012727/2018-94 | G5: 45882 | H5: =IF((G5-TODAY())<0,"EXPIRADO", IF((G5-TODAY())<=60,"EM BREVE","NO PRAZO")) -> EXPIRADO | J5: 515/2021 | K5: 60000 | M5: =K5*12 -> 720000 | N5: 181857.31 | O5: 0 | P5: =SUM(O5:O5) -> 0 | S5: =K5 -> 60000 | T5: =K5 -> 60000 | U5: =K5 -> 60000 | V5: =K5 -> 60000 | W5: =K5 -> 60000 | X5: =K5 -> 60000 | Y5: =K5 -> 60000 | Z5: =K5 -> 60000 | AA5: =K5 -> 60000 | AB5: =K5 -> 60000 | AC5: =T5+U5 -> 120000 | AD5: 1000 | AE5: =SUM(K5:L5)*2 -> 120000 | AF5: =P5-AE5 -> -120000 | AG5: =-Z5-AA5 -> -120000 | AH5: =(SUM(K5:L5)*2)-P5 -> 120000
A6: -SIG SOFTWARE & CONSULTORIA EM TECNOLOGIA DA I (Serviço de apoio especializado nas atividades necessárias ao suporte negocial, customização e sustentação do Sistemas Institucionais Integrados de Gestão (SIG)) | B6: STI | C6: 2 | D6: VGM01N01Q4N | E6: 13.406.686/0001-67 | F6: 23106.125254/2022-71 | G6: 46082 | H6: =IF((G6-TODAY())<0,"EXPIRADO", IF((G6-TODAY())<=60,"EM BREVE","NO PRAZO")) -> NO PRAZO | J6: 505/2024 | K6: =M6/12 -> 236095 | L6: ainda sem histórico de liquidação | M6: 2833140 | N6: 100 | O6: 201936.5 | P6: =SUM(N6:O6) -> 202036.5 | T6: =236037-202037 -> 34000 | U6: =K6 -> 236095 | V6: =K6 -> 236095 | W6: =K6 -> 236095 | X6: =K6 -> 236095 | Y6: =K6 -> 236095 | Z6: =K6 -> 236095 | AA6: =K6 -> 236095 | AB6: =K6 -> 236095 | AC6: =T6+U6 -> 270095 | AD6: 1000 | AE6: =SUM(K6:L6)*2 -> 472190 | AG6: -99075 | AH6: =(SUM(K6:L6)*2)-P6 -> 270153.5
A7: BELFORT GERENCIAMENTO DE RESIDUOS LTDA - empresa especializada nos serviços continuados de coleta, transporte, tratamento e disposição final de resíduos de serviços de saúde (RSS) | B7: Contratos DCA | C7: 2 | D7: VGM01N01E4N | E7: 10865146000153 | F7: 23106.065223/2022-53 | G7: 46039 | H7: =IF((G7-TODAY())<0,"EXPIRADO", IF((G7-TODAY())<=60,"EM BREVE","NO PRAZO")) -> EM BREVE | J7: 1204/2023 | K7: 4000 | M7: =K7*12 -> 48000 | N7: 1948.01 | O7: 0 | P7: =SUM(N7:O7) -> 1948.01 | S7: =K7-P7 -> 2051.99 | T7: =K7-1948 -> 2052 | U7: =K7 -> 4000 | V7: =K7 -> 4000 | W7: =K7 -> 4000 | X7: =K7 -> 4000 | Y7: =K7 -> 4000 | Z7: =K7 -> 4000 | AA7: =K7 -> 4000 | AB7: =K7 -> 4000 | AC7: =T7+U7 -> 6052 | AD7: 1000 | AE7: =SUM(K7:L7)*2 -> 8000 | AF7: =P7-AE7 -> -6051.99
A8: ARTES GRÁFICA COMÉRCIO E REPRESENTAÇÕES EIRELI (serviços continuados de Designer Gráfico) - foi solicitada prorrogação por 20 meses | B8: Contratos DCA | C8: 2 | D8: VGM01N01P4N | E8: 05606994000108 | F8: 23106.148085/2022-47 | G8: 46127 | H8: =IF((G8-TODAY())<0,"EXPIRADO", IF((G8-TODAY())<=60,"EM BREVE","NO PRAZO")) -> NO PRAZO | J8: 147/2022 | L8: =12640.77 -> 12640.77 | M8: =L8*12 -> 151689.24 | N8: 13176.77 | O8: 0 | P8: =SUM(N8:O8) -> 13176.77 | U8: =L8-536 -> 12104.77 | V8: =L8 -> 12640.77 | W8: =L8 -> 12640.77 | X8: =L8 -> 12640.77 | Y8: =L8 -> 12640.77 | Z8: =L8 -> 12640.77 | AA8: =L8 -> 12640.77 | AB8: =L8 -> 12640.77 | AC8: =T8+U8 -> 12104.77 | AD8: 1000 | AE8: =SUM(K8:L8)*2 -> 25281.54 | AF8: =P8-AE8 -> -12104.77 | AH8: =(SUM(K8:L8)*2)-P8 -> 12104.77
A9: ELYON BRASIL - ESPLANADA SERVICOS TERCEIRIZADOS EIRELI - serviços continuados de pessoal - coletores de resíduos de serviços de saúde | B9: Contratos DCA | C9: 1 | D9: VGM01N01E4N | E9: 01099686000182 | F9: 23106.031888/2020-00 | G9: 45854 | H9: =IF((G9-TODAY())<0,"EXPIRADO", IF((G9-TODAY())<=60,"EM BREVE","NO PRAZO")) -> EXPIRADO | J9: 111/2020 | L9: =M9/12 -> 22669.34 | M9: 272032.08 | N9: 24500.93 | O9: 0 | P9: =SUM(N9:O9) -> 24500.93 | U9: =22669-1831.59 -> 20837.41 | V9: =L9 -> 22669.34 | W9: =L9 -> 22669.34 | X9: =L9 -> 22669.34 | Y9: =L9 -> 22669.34 | Z9: =L9 -> 22669.34 | AA9: =L9 -> 22669.34 | AB9: =L9 -> 22669.34 | AC9: =T9+U9 -> 20837.41 | AD9: 1000 | AE9: =SUM(K9:L9)*2 -> 45338.68 | AF9: =P9-AE9 -> -20837.75 | AH9: =(SUM(K9:L9)*2)-P9 -> 20837.75
A10: - ALFA E OMEGA Apoio Técnico EDU | B10: Contratos DCA | C10: 1 | D10: VGM01N01D5N | E10: 16650774000106 | F10: 23106.011967/2019-52 | G10: 45766 | H10: =IF((G10-TODAY())<0,"EXPIRADO", IF((G10-TODAY())<=60,"EM BREVE","NO PRAZO")) -> EXPIRADO | I10: Em fase de prorrogação | J10: 022/2021 | L10: =M10/12 -> 23238.88 | M10: 278866.56 | N10: 2226.86 | O10: 270 | P10: =SUM(N10:O10) -> 2496.86 | S10: 865.66 | T10: =L10-2497 -> 20741.88 | U10: =L10 -> 23238.88 | V10: =L10 -> 23238.88 | W10: =L10 -> 23238.88 | X10: =L10 -> 23238.88 | Y10: =L10 -> 23238.88 | Z10: =L10 -> 23238.88 | AA10: =L10 -> 23238.88 | AB10: =L10 -> 23238.88 | AC10: =T10+U10 -> 43980.76 | AD10: 1000 | AE10: =SUM(K10:L10)*2 -> 46477.76 | AF10: =P10-AE10 -> -43980.9 | AH10: =(SUM(K10:L10)*2)-P10 -> 43980.9
A11: RCS Tecnologia LTDA - copeiragem | B11: Contratos DCA | C11: 1 | D11: VGM01N01O2N | E11: 08220952000122 | F11: 23106.125355/2019-46 23106.035022/2021-41 | G11: 45929 | H11: =IF((G11-TODAY())<0,"EXPIRADO", IF((G11-TODAY())<=60,"EM BREVE","NO PRAZO")) -> EXPIRADO | I11: Foi para a PF solicitando prorrogação com vigência em 29/09/2025 | J11: 07/2021 | L11: 131667.49 | M11: =L11*12 -> 1580009.9 | N11: 0 | O11: 0 | P11: =SUM(N11:O11) -> 0 | T11: 131667 | U11: =L11 -> 131667.49 | V11: =L11 -> 131667.49 | W11: =L11 -> 131667.49 | X11: =L11 -> 131667.49 | Y11: =L11 -> 131667.49 | Z11: =L11 -> 131667.49 | AA11: =L11 -> 131667.49 | AB11: =L11 -> 131667.49 | AC11: =T11+U11 -> 263334.49 | AD11: 1000 | AE11: =SUM(K11:L11)*2 -> 263334.98 | AF11: =P11-AE11 -> -263334.98 | AH11: =(SUM(K11:L11)*2)-P11 -> 263334.98
A12: T&S Engenharia Telemática e Sistemas LTDA - contínuo | B12: Contratos DCA | C12: 1 | D12: VGM01N01B7N | E12: 00712411000100 | F12: 23106.034924/2021-60 | G12: 45745 | H12: =IF((G12-TODAY())<0,"EXPIRADO", IF((G12-TODAY())<=60,"EM BREVE","NO PRAZO")) -> EXPIRADO | I12: Foi para PF, prorrogação excepcional | J12: 006/2021 | L12: 183316.03 | M12: =L12*12 -> 2199792.4 | N12: 0 | O12: 0 | P12: =SUM(N12:O12) -> 0 | S12: =L12-P12 -> 183316.03 | T12: =L12 -> 183316.03 | U12: =L12 -> 183316.03 | V12: =L12 -> 183316.03 | W12: =L12 -> 183316.03 | X12: =L12 -> 183316.03 | Y12: =L12 -> 183316.03 | Z12: =L12 -> 183316.03 | AA12: =L12 -> 183316.03 | AB12: =L12 -> 183316.03 | AC12: =T12+U12 -> 366632.06 | AD12: 1000 | AE12: =SUM(K12:L12)*2 -> 366632.06 | AF12: =P12-AE12 -> -366632.06 | AH12: =(SUM(K12:L12)*2)-P12 -> 366632.06
A13: Phoenix Comércio e Serviços de Limpeza LTDA - Almoxarifado e de transporte interno de móveis e materiais | B13: Contratos DCA | C13: 1 | D13: VGM01N01F7N | E13: 12978051000171 | F13: 23106.001099/2022-06 | G13: 45902 | H13: =IF((G13-TODAY())<0,"EXPIRADO", IF((G13-TODAY())<=60,"EM BREVE","NO PRAZO")) -> EXPIRADO | J13: 111/2022 | L13: 117871.46 | M13: =L13*12 -> 1414457.5 | N13: =7661.65+41709.35 -> 49371 | O13: 0 | P13: =SUM(N13:O13) -> 49371 | T13: =117871-49371 -> 68500 | U13: =L13 -> 117871.46 | V13: =L13 -> 117871.46 | W13: =L13 -> 117871.46 | X13: =L13 -> 117871.46 | Y13: =L13 -> 117871.46 | Z13: =L13 -> 117871.46 | AA13: =L13 -> 117871.46 | AB13: =L13 -> 117871.46 | AC13: =T13+U13 -> 186371.46 | AD13: 1000 | AE13: =SUM(K13:L13)*2 -> 235742.92 | AG13: -212997.86 | AH13: =(SUM(K13:L13)*2)-P13 -> 186371.92 | AJ13: =SUM(AC4:AC14)+390828.95 -> 6100000
A14: - RCA (Limpeza e Conservação) | B14: Contratos DCA | C14: 1 | D14: VGM01N01A7N | E14: 69207850000161 | F14: 23106.057738/2021-07 | G14: 45792 | H14: =IF((G14-TODAY())<0,"EXPIRADO", IF((G14-TODAY())<=60,"EM BREVE","NO PRAZO")) -> EXPIRADO | J14: 02/2022 | L14: 1882331.1 | M14: =L14*12 -> 22587973 | N14: 116566.68 | O14: 0 | P14: =SUM(N14:O14) -> 116566.68 | T14: =1882331-116567 -> 1765764 | U14: =L14 -> 1882331.1 | V14: =L14 -> 1882331.1 | W14: =L14 -> 1882331.1 | X14: =L14 -> 1882331.1 | Y14: =L14 -> 1882331.1 | Z14: =L14 -> 1882331.1 | AA14: =L14 -> 1882331.1 | AB14: =L14 -> 1882331.1 | AC14: =T14+U14 -> 3648095.1 | AD14: 1000 | AE14: =SUM(K14:L14)*2 -> 3764662.2 | AG14: =P14-AE14 -> -3648095.5 | AJ14: =6100000-SUM(AC4:AC14) -> 390828.95
A15: Life Defense (Segurança) | B15: Contratos DCA | C15: 1 | D15: VGM01N01A8N | E15: 02674687000176 | F15: 23106.016977/2013-99 23106.083943/2018-14 23106.047642/2024-75 | G15: 46097 | H15: =IF((G15-TODAY())<0,"EXPIRADO", IF((G15-TODAY())<=60,"EM BREVE","NO PRAZO")) -> NO PRAZO | I15: Foi solicitado parecer à PF para prorrogação. | J15: 011/2020 | L15: 1617878.6 | M15: =L15*12 -> 19414543 | N15: 0 | O15: 0 | P15: =SUM(N15:O15) -> 0 | T15: =L15 -> 1617878.6 | U15: =L15 -> 1617878.6 | V15: =L15 -> 1617878.6 | W15: =L15 -> 1617878.6 | X15: =L15 -> 1617878.6 | Y15: =L15 -> 1617878.6 | Z15: =L15 -> 1617878.6 | AA15: =L15 -> 1617878.6 | AB15: =L15 -> 1617878.6 | AC15: =T15+U15 -> 3235757.2 | AD15: 1050 | AE15: =SUM(K15:L15)*2 -> 3235757.2 | AG15: =P15-AE15 -> -3235757.2 | AH15: =(SUM(K15:L15)*2)-P15 -> 3235757.2 | AJ15: =AC15-AJ14 -> 2844928.2
A16: G&E SERVICOS TERCEIRIZADOS LTDA - serviços continuados de motorista | B16: Contratos DCA | C16: 1 | D16: VGM01N01P5N | E16: 08744139000151 | F16: 23106.038810/2022-70 | G16: 46166 | H16: =IF((G16-TODAY())<0,"EXPIRADO", IF((G16-TODAY())<=60,"EM BREVE","NO PRAZO")) -> NO PRAZO | J16: 001/2023 | L16: 190000 | M16: =L16*12 -> 2280000 | N16: 0 | O16: 0 | P16: =SUM(N16:O16) -> 0 | T16: 190000 | U16: =L16 -> 190000 | V16: =L16 -> 190000 | W16: =L16 -> 190000 | X16: =L16 -> 190000 | Y16: =L16 -> 190000 | Z16: =L16 -> 190000 | AA16: =L16 -> 190000 | AB16: =L16 -> 190000 | AC16: =T16+U16 -> 380000 | AD16: 1050 | AE16: =SUM(K16:L16)*2 -> 380000 | AF16: =P16-AE16 -> -380000 | AH16: =(SUM(K16:L16)*2)-P16 -> 380000
A17: POLI ENGENHARIA LTDA (serviços comuns de engenharia, incluindo manutenção, conservação, adaptação, reparação e instalação de infraestruturas prediais e imobiliárias) - contrato 20 meses | B17: Contratos DCA | C17: 2 | D17: VGM01N01H3N | E17: 00700518000138 | F17: 23106.117479/2022-53 | G17: 46146 | H17: =IF((G17-TODAY())<0,"EXPIRADO", IF((G17-TODAY())<=60,"EM BREVE","NO PRAZO")) -> NO PRAZO | J17: 1226/2022 | K17: 145000 | M17: =K17*12 -> 1740000 | N17: =90296.37+2393.36 -> 92689.73 | O17: 113737.72 | P17: =SUM(N17:O17) -> 206427.45 | U17: =145000-61427 -> 83573 | V17: =K17 -> 145000 | W17: =K17 -> 145000 | X17: =K17 -> 145000 | Y17: =K17 -> 145000 | Z17: =K17 -> 145000 | AA17: =K17 -> 145000 | AB17: =K17 -> 145000 | AC17: =T17+U17 -> 83573 | AD17: 1050 | AE17: =SUM(K17:L17)*2 -> 290000 | AF17: =P17-AE17 -> -83572.55 | AJ17: =SUM(AC15:AC25) -> 4275683.3
A18: Ágil (Serviços Agropecuários) | B18: Contratos DCA | C18: 1 | D18: VGM01N01C5N | E18: 72620735000129 | F18: 23106.076196/2018-68 23106.030688/2022-93 | G18: 46097 | H18: =IF((G18-TODAY())<0,"EXPIRADO", IF((G18-TODAY())<=60,"EM BREVE","NO PRAZO")) -> NO PRAZO | I18: Solicitado parecer à PF para prorrogação. | J18: 25/2020 | L18: 458615.91 | M18: =L18*12 -> 5503390.9 | N18: 413328.12 | O18: 45809.43 | P18: =SUM(N18:O18) -> 459137.55 | S18: =L18-O18 -> 412806.48 | U18: =L18-521.64 -> 458094.27 | V18: =L18 -> 458615.91 | W18: =L18 -> 458615.91 | X18: =L18 -> 458615.91 | Y18: =L18 -> 458615.91 | Z18: =L18 -> 458615.91 | AA18: =L18 -> 458615.91 | AB18: =L18 -> 458615.91 | AC18: =T18+U18 -> 458094.27 | AD18: 1050 | AE18: =SUM(K18:L18)*2 -> 917231.82 | AF18: =P18-AE18 -> -458094.27 | AH18: =(SUM(K18:L18)*2)-P18 -> 458094.27 | AJ18: 5798525.9
A19: Contrato de Limpeza - UnB Cerrado (AP PISCINAS EIRELI) | B19: UnB Cerrado | C19: 1 | D19: VGM01N01A7N | E19: 08475822000130 | F19: 23106.116355/2019-55 | G19: 45889 | H19: =IF((G19-TODAY())<0,"EXPIRADO", IF((G19-TODAY())<=60,"EM BREVE","NO PRAZO")) -> EXPIRADO | J19: 112/2020 | L19: =M19/12 -> 5331.32 | M19: 63975.84 | N19: 4688.29 | O19: 0 | P19: =SUM(N19:O19) -> 4688.29 | S19: =L19-P19 -> 643.03 | T19: =L19-4688 -> 643.32 | U19: =L19 -> 5331.32 | V19: =L19 -> 5331.32 | W19: =L19 -> 5331.32 | X19: =L19 -> 5331.32 | Y19: =L19 -> 5331.32 | Z19: =L19 -> 5331.32 | AA19: =L19 -> 5331.32 | AB19: =L19 -> 5331.32 | AC19: =T19+U19 -> 5974.64 | AD19: 1050 | AE19: =SUM(K19:L19)*2 -> 10662.64 | AG19: -643.35 | AH19: =(SUM(K19:L19)*2)-P19 -> 5974.35 | AJ19: =AJ13-AJ18 -> 301474.11
A20: - Segurança - ULTRASEG Segurança Patrimonial Ltda | B20: UnB Cerrado | C20: 1 | D20: VGM01N01A8N | E20: 09151154000159 | F20: 23106.020717/2022-17 | G20: 45938 | H20: =IF((G20-TODAY())<0,"EXPIRADO", IF((G20-TODAY())<=60,"EM BREVE","NO PRAZO")) -> EXPIRADO | J20: 1207/2022 | L20: 23452.22 | M20: =L20*12 -> 281426.64 | N20: 23452.22 | O20: 0 | P20: =SUM(N20:O20) -> 23452.22 | U20: =L20 -> 23452.22 | V20: =L20 -> 23452.22 | W20: =L20 -> 23452.22 | X20: =L20 -> 23452.22 | Y20: =L20 -> 23452.22 | Z20: =L20 -> 23452.22 | AA20: =L20 -> 23452.22 | AB20: =L20 -> 23452.22 | AC20: =T20+U20 -> 23452.22 | AD20: 1050 | AE20: =SUM(K20:L20)*2 -> 46904.44 | AG20: -46904.36 | AH20: =(SUM(K20:L20)*2)-P20 -> 23452.22
A21: PGFN: 1° ATI, negociação conta n°: 7300348 ( Consulta Acordo n°1 - Conta da Negociação 7300348 (SEI nº 10575553) | B21: Contratos Diversos | C21: 2 | D21: VGH01N0112N | F21: 23106.094258/2021-19 23106.001775/2022-33 23106.005996/2023-61 23106.044758/2024-52 23106.132563/2023-88 | G21: 60 parcelas (já pagou 20/60) | K21: 285000 | M21: =K21*12 -> 3420000 | N21: =61992.46+508007.54 -> 570000 | O21: 0 | P21: =SUM(N21:O21) -> 570000 | V21: 285000 | W21: 285000 | X21: 285000 | Y21: 285000 | Z21: 285000 | AA21: 285000 | AB21: 285000 | AC21: 50000 | AD21: 1050 | AH21: =(SUM(K21:L21)*2)-P21 -> 0 | AJ21: =AJ17+AC34+AC46 -> 9909690.2
A22: PGFN: 2° ATI, negociação conta n°: 8815031 (Consulta Acordo n°2 - Conta da Negociação 8815031 (SEI nº 10576277)) | B22: Contratos Diversos | C22: 2 | D22: VGH01N0112N | F22: 23106.059565/2023-15 23106.128684/2023-25 23106.044758/2024-52 23106.132563/2023-88 | G22: 60 parcelas (já pagou 10/60) | K22: 28500 | M22: =K22*12 -> 342000 | N22: 32106.5 | O22: 0 | P22: =SUM(N22:O22) -> 32106.5 | U22: =28500-3607 -> 24893 | V22: 28500 | W22: 28500 | X22: 28500 | Y22: 28500 | Z22: 28500 | AA22: 28500 | AB22: 28500 | AC22: =T22+U22 -> 24893 | AD22: 1050 | AH22: =(SUM(K22:L22)*2)-P22 -> 24893.5 | AJ22: 12244660
A23: RFB: Conta da Negociação 0211000120 (Consulta Parcelamento n°1 - Conta da Negociação 0211000120 (SEI nº 10580261)) | B23: Contratos Diversos | C23: 2 | D23: VGH01N0112N | F23: 23106.059634/2023-91 23106.087581/2023-06 23106.044758/2024-52 23106.132563/2023-88 | G23: 60 parcelas (já pagou 13/60) | K23: 17500 | M23: =K23*12 -> 210000 | N23: 22573.93 | O23: 5053.56 | P23: =SUM(N23:O23) -> 27627.49 | U23: =17500-10127 -> 7373 | V23: 17500 | W23: 17500 | X23: 17500 | Y23: 17500 | Z23: 17500 | AA23: 17500 | AB23: 17500 | AC23: =T23+U23 -> 7373 | AD23: 1050 | AH23: =(SUM(K23:L23)*2)-P23 -> 7372.51 | AJ23: =AJ22-AJ21 -> 2334969.9
A24: Tratador de Piscinas CO e casa Oscar Niemayer - (AP Piscinas EIRELI) - em fase de renovação | B24: Contratos Diversos | C24: 1 | D24: VGM01N01E2N | E24: 08475822000130 | F24: 23106.013349/2019-47 | G24: 45844 | H24: =IF((G24-TODAY())<0,"EXPIRADO", IF((G24-TODAY())<=60,"EM BREVE","NO PRAZO")) -> EXPIRADO | J24: 93/2020 | L24: =M24/12 -> 5039.3475 | M24: 60472.17 | N24: 5205.73 | O24: 0 | P24: =SUM(N24:O24) -> 5205.73 | U24: =L24-166.38 -> 4872.9675 | V24: =L24 -> 5039.3475 | W24: =L24 -> 5039.3475 | X24: =L24 -> 5039.3475 | Y24: =L24 -> 5039.3475 | Z24: =L24 -> 5039.3475 | AA24: =L24 -> 5039.3475 | AB24: =L24 -> 5039.3475 | AC24: =T24+U24 -> 4872.9675 | AD24: 1050 | AE24: =L24*2 -> 10078.695 | AH24: =(SUM(K24:L24)*2)-P24 -> 4872.965
A25: - Empresa Brasil de Comunicação (EBC) | B25: Comunicação | C25: 2 | D25: VGM01N01I9N | F25: 23106.048294/2020-20 | G25: 46001 | H25: =IF((G25-TODAY())<0,"EXPIRADO", IF((G25-TODAY())<=60,"EM BREVE","NO PRAZO")) -> EM BREVE | J25: 213/2020 | K25: 2000 | M25: =K25*12 -> 24000 | N25: 531.84 | O25: 1774.72 | P25: =SUM(N25:O25) -> 2306.56 | U25: =K25-307 -> 1693 | V25: =K25 -> 2000 | W25: =K25 -> 2000 | X25: =K25 -> 2000 | Y25: =K25 -> 2000 | Z25: =K25 -> 2000 | AA25: =K25 -> 2000 | AB25: =K25 -> 2000 | AC25: =T25+U25 -> 1693 | AD25: 1050 | AE25: =K25*2 -> 4000 | AF25: =P25-AE25 -> -1693.44 | AH25: =(SUM(K25:L25)*2)-P25 -> 1693.44
A26: Total da despesa | K26: =SUM(K4:K25) -> 1588095 | L26: =SUM(L4:L25) -> 4674052.5 | M26: =SUM(M4:M25) -> 75145769 | N26: =SUM(N4:N25) -> 2402656.1 | O26: =SUM(O4:O25) -> 368581.93 | P26: =SUM(P4:P25) -> 2589380.7 | Q26: =SUM(Q4:Q25) -> 0 | R26: =SUM(R4:R25) -> 0 | ... AC26: =SUM(AC4:AC25) -> 9984854.3 | AE26: =SUM(AE4:AE25) -> 11862295 | AF26: =SUM(AF4:AF25) -> -2527970.6 | AG26: =SUM(AG4:AG25) -> -7363473.3 | AH26: =SUM(AH4:AH25) -> 6197194.2
AG28: =#REF! -> #REF!
AG29: -6000000
A30: Descrição das despesas | B30: UGR | C30: Prioridade | D30: PI 2025 | E30: CNPJ | F30: Processo | G30: Vigência | H30: Status do Contrato | I30: Situação da prorrogação | J30: nº Contrato | K30: Valor Contrato Média mensal | L30: Valor Cont Continuado Mensal | M30: Total estimado Anual | N30: Saldo Empenhos 2025 | O30: Saldo de Empenhos RAP | P30: Total RAP + Empenho | Q30: 45658 | R30: 45689 | S30: 45717 | T30: 45748 | U30: 45778 | V30: 45809 | W30: 45839 | X30: 45870 | Y30: 45901 | Z30: 45931 | AA30: 45962 | AB30: 45992 | AC30: Total necessário | AG30: -1280820.9
A31: CRUZEIRO CONTROLE DE PRAGAS E DESENTUPIMENTO | B31: PRC | D31: VGM01N01D3N | E31: 22.575.793/0001-00 | AC31: 14882
A32: VILELA SERVIÇO DE PAISAGISMO, PARQUES E JARDINS LTDA (jardinagem) | B32: PRC | D32: VGM01N01A5N | E32: 32.751.565/0001-05 | AC32: 568003.42 | AG32: =SUM(AG28:AG29) -> #REF!
A33: - Taxigov (demanda) - VIP service | B33: PRC | D33: VGM01N01A4N | E33: 02605452000122 | AC33: 5836 | AG33: =AG32+#REF! -> #REF!
A34: Total da despesa | F34: Processo | G34: Vigência | H34: Status do Contrato | I34: Situação da prorrogação | K34: Valor Contrato Média mensal | L34: Valor Cont Continuado Mensal | M34: Total estimado Anual | N34: Saldo Empenhos 2025 | O34: Saldo de Empenhos RAP | P34: Total RAP + Empenho | Q34: 45658 | R34: 45689 | S34: 45717 | T34: 45748 | U34: 45778 | V34: 45809 | W34: 45839 | X34: 45870 | Y34: 45901 | Z34: 45931 | AA34: 45962 | AB34: 45992 | AC34: =SUM(AC31:AC33) -> 588721.42
A36: Descrição das despesas | B36: UGR | C36: Prioridade | D36: PI 2025 | E36: CNPJ | F36: Processo | G36: Vigência | H36: Status do Contrato | I36: Situação da prorrogação | J36: nº Contrato | K36: Valor Contrato Média mensal | L36: Valor Cont Continuado Mensal | M36: Total estimado Anual | N36: Saldo Empenhos 2025 | O36: Saldo de Empenhos RAP | P36: Total RAP + Empenho | Q36: 45658 | R36: 45689 | S36: 45717 | T36: 45748 | U36: 45778 | V36: 45809 | W36: 45839 | X36: 45870 | Y36: 45901 | Z36: 45931 | AA36: 45962 | AB36: 45992 | AC36: Total necessário
A37: '- GESTOR SERVICOS EMPRESARIAIS (Portaria - SPI) | B37: Contratos SPI | D37: VGM01N01E8N | E37: 02685728000120 | J37: 001/2022 | AC37: 359669.2
A38: - SEFIX (Limpeza e Conservação - SPI) | B38: Contratos SPI | D38: VGM01N01E9N | E38: 13258899000199 | J38: 033/2022 | AC38: 387647.54
A39: Engemega - (Manutenção de Imóveis gerenciados pela Secretaria de Patrimônio Imobiliário (SPI)) – contrato 1 | B39: Contratos SPI | D39: VGM01N01D4N | E39: 33480104/0001-08 | J39: 1223/2022 | AC39: 61167
A40: SILVA EDIFICAÇÕES LTDA - emissão de laudos técnicos de avaliação de valores imobiliários | B40: Contratos SPI | D40: VGM01N01Q7N | E40: 44.532.592/0001-68 | AC40: 1638
A41: - ENERGIA ELÉTRICA - SPI | B41: Contratos SPI | D41: VGM01N01I2N | E41: 07522669000192 | AC41: 67257
A42: - CAESB - SPI | B42: Contratos SPI | D42: VGM01N01I3N | E42: 00082024000137 | AC42: 272700
A43: - Despesas de Condomínio | B43: Contratos SPI | D43: VGM01N01K6N | AC43: 140000
A44: G&E SERVICOS TERCEIRIZADOS LTDA (PORTARIA) | B44: Contratos DCA | C44: 1 | D44: VGM01N01A9N | E44: 08744139000151 | F44: 23106.085840/2022-75 23106.005560/2022-91 23106.046596/2024-97 | G44: 46020 | H44: =IF((G44-TODAY())<0,"EXPIRADO", IF((G44-TODAY())<=60,"EM BREVE","NO PRAZO")) -> EM BREVE | J44: 081/2022 | L44: =1205875.51+32423.44 -> 1238298.9 | M44: =L44*12 -> 14859587 | N44: 554.82 | O44: 0 | P44: =SUM(N44:O44) -> 554.82 | S44: =L44-O44 -> 1238298.9 | T44: =1238299-555 -> 1237744 | U44: =L44 -> 1238298.9 | V44: =L44 -> 1238298.9 | W44: =L44 -> 1238298.9 | X44: =L44 -> 1238298.9 | Y44: =L44 -> 1238298.9 | Z44: =L44 -> 1238298.9 | AA44: =L44 -> 1238298.9 | AB44: =L44 -> 1238298.9 | AC44: =T44+U44 -> 2476043 | AE44: =SUM(K44:L44)*2 -> 2476597.9 | AG44: =P44-AE44 -> -2476043.1 | AH44: =(SUM(K44:L44)*2)-P44 -> 2476043.1
A45: Restaurante ISM EIRELI (diretoria RU) - Ação 20RK planilha DRU | B45: Contrato DAC/RU | C45: 1 | D45: VGM01N01B5N | E45: 04228626001263 | F45: 23106.013653/2020-28 | G45: 45909 | H45: =IF((G45-TODAY())<0,"EXPIRADO", IF((G45-TODAY())<=60,"EM BREVE","NO PRAZO")) -> EXPIRADO | J45: 31/2021 | K45: =M45/12 -> 1500933.6 | M45: 18011203 | N45: 2013096.4 | O45: 0 | P45: =SUM(N45:O45) -> 2013096.4 | U45: ='DRU 25'!J9-512163 -> 1279163.9 | V45: ='DRU 25'!J10 -> 1791326.9 | W45: ='DRU 25'!J11 -> 1506537.9 | X45: ='DRU 25'!J12 -> 618545.02 | Y45: ='DRU 25'!J13 -> 1791326.9 | Z45: ='DRU 25'!J14 -> 1791326.9 | AA45: ='DRU 25'!J15 -> 1791326.9 | AB45: ='DRU 25'!J16 -> 1506537.9 | AC45: =T45+U45 -> 1279163.9 | AE45: =Z45+AA45 -> 3582653.7 | AH45: =(SUM(K45:L45)*2)-P45 -> 988770.71
A46: Total da despesa | F46: Processo | G46: Vigência | H46: Status do Contrato | I46: Situação da prorrogação | K46: Valor Contrato Média mensal | L46: Valor Cont Continuado Mensal | M46: Total estimado Anual | N46: Saldo Empenhos 2025 | O46: Saldo de Empenhos RAP | P46: Total RAP + Empenho | Q46: 45658 | R46: 45689 | S46: 45717 | T46: 45748 | U46: 45778 | V46: 45809 | W46: 45839 | X46: 45870 | Y46: 45901 | Z46: 45931 | AA46: 45962 | AB46: 45992 | AC46: =SUM(AC37:AC45) -> 5045285.6
AC49: =AC46+AC34+AC26 -> 15618861 | AD49: =AC46+AC34+SUM(AC15:AC25) -> 9909690.2
AD50: 230
AD51: 4865.55
AD52: 100
AD53: 206.06
AD54: 100
AD55: 3250
AD56: 5000
AD57: 2253
AD58: 50773.59
AD59: 0.1
AD60: 192.79
AD62: 11004172
AD63: =AD62-SUM(AD49:AD60) -> 1027510.7

Sheet Prog-17.03 PRC
A1: Programação de Despesas
A2: Data de Atualização: 12/03/2025
A3: Descrição das despesas | C3: UGR | D3: Prioridade | E3: PI 2025 | F3: CNPJ | G3: nº Contrato | H3: 45658 | I3: 45689 | J3: Total necessário | O3: Fonte da Ação 20RK
A4: 1 | B4: - NORESA NOVO RIO ENERGIA E SERVICOS AMBIENTAIS (empresa especializada na prestação de serviços de coleta, transporte, triagem e destinação final de resíduos sólidos orgânicos) | C4: PRC | D4: 2 | E4: VGM01N01E4N | F4: 07044248000101 | G4: 1213/2023 | J4: 14000 | O4: 1000
A5: 2 | B5: - Taxigov (demanda) - VIP service | C5: PRC | D5: 3 | E5: VGM01N01A4N | F5: 02605452000122 | G5: 036/2020 | J5: 5164 | O5: 1000
A6: 3 | B6: 3P HGM solução visual (serviços de comunicação visual) | C6: PRC | D6: 2 | E6: VGM01N01O7N | F6: 34.998.513/0001-55 | G6: 1217/2022 | J6: 916407 | K6: =SUM(#REF!)*2 -> #REF! | L6: =#REF!-K6 -> #REF! | N6: =(SUM(#REF!)*2)-#REF! -> #REF! | O6: 1000
A7: Total da despesa | H7: =SUM(H4:H6) -> 0 | I7: =SUM(I4:I6) -> 0 | J7: =SUM(J4:J6) -> 935571 | K7: =SUM(K4:K6) -> #REF! | L7: =SUM(L4:L6) -> #REF! | M7: =SUM(M4:M6) -> 0 | N7: =SUM(N4:N6) -> #REF!

Sheet Prog-12.03
A1: Programação de Despesas
A2: Data de Atualização: 12/03/2025
A3: Descrição das despesas | C3: UGR | D3: Prioridade | E3: PI 2025 | F3: CNPJ | G3: nº Contrato | H3: 45658 | I3: 45689 | J3: Total necessário | O3: Fonte da Ação 20RK
A4: 1 | B4: Pasep - UnB | C4: DGP/ folha | D4: 1 | E4: VGM01N01N1N | J4: 620000 | O4: 1000
A5: 2 | B5: OI SA recuperação judicial | C5: STI | D5: 3 | E5: VGM01N01I4N | F5: 76535764000143 | G5: 515/2021 | J5: 120000 | O5: 1000
A6: 3 | B6: - Central IT - Suporte TI (Serviços de Manutenção dos Computadores da UnB) | C6: STI | D6: 2 | E6: VGM01N01A3N | F6: 07171299000196 | G6: 507/2019 | J6: 594865.84 | K6: =SUM(#REF!)*2 -> #REF! | L6: =#REF!-K6 -> #REF! | N6: =(SUM(#REF!)*2)-#REF! -> #REF! | O6: 1000
A7: 4 | B7: BELFORT GERENCIAMENTO DE RESIDUOS LTDA - empresa especializada nos serviços continuados de coleta, transporte, tratamento e disposição final de resíduos de serviços de saúde (RSS) | C7: Contratos DCA | D7: 2 | E7: VGM01N01E4N | F7: 10865146000153 | G7: 1204/2023 | J7: 5850.87 | K7: =SUM(#REF!)*2 -> #REF! | L7: =#REF!-K7 -> #REF! | O7: 1000
A8: 5 | B8: ARTES GRÁFICA COMÉRCIO E REPRESENTAÇÕES EIRELI (serviços continuados de Designer Gráfico) | C8: Contratos DCA | D8: 2 | E8: VGM01N01P4N | F8: 05606994000108 | G8: 147/2022 | J8: 10753.53 | K8: =SUM(#REF!)*2 -> #REF! | L8: =#REF!-K8 -> #REF! | N8: =(SUM(#REF!)*2)-#REF! -> #REF! | O8: 1000
A9: 6 | B9: RCS Tecnologia LTDA - copeiragem | C9: Contratos DCA | D9: 1 | E9: VGM01N01O2N | F9: 08220952000122 | G9: 07/2021 | J9: 130952.88 | K9: =SUM(#REF!)*2 -> #REF! | L9: =#REF!-K9 -> #REF! | N9: =(SUM(#REF!)*2)-#REF! -> #REF! | O9: 1000
A10: 7 | B10: Phoenix Comércio e Serviços de Limpeza LTDA - Almoxarifado e de transporte interno de móveis e materiais | C10: Contratos DCA | D10: 1 | E10: VGM01N01F7N | F10: 12978051000171 | G10: 111/2022 | J10: 22744.6 | K10: =SUM(#REF!)*2 -> #REF! | M10: -212997.86 | N10: =(SUM(#REF!)*2)-#REF! -> #REF! | O10: 1000
A11: 8 | B11: - RCA (Limpeza e Conservação) | C11: Contratos DCA | D11: 1 | E11: VGM01N01A7N | F11: 69207850000161 | G11: 02/2022 | J11: 212841.48 | K11: =SUM(#REF!)*2 -> #REF! | M11: =#REF!-K11 -> #REF! | O11: 1000
A12: 9 | B12: Life Defense (Segurança) | C12: Contratos DCA | D12: 1 | E12: VGM01N01A8N | F12: 02674687000176 | G12: 011/2020 | J12: 1617878.6 | K12: =SUM(#REF!)*2 -> #REF! | M12: =#REF!-K12 -> #REF! | N12: =(SUM(#REF!)*2)-#REF! -> #REF! | O12: 1000
A13: 10 | B13: G&E SERVICOS TERCEIRIZADOS LTDA (PORTARIA) | C13: Contratos DCA | D13: 1 | E13: VGM01N01A9N | F13: 08744139000151 | G13: 081/2022 | J13: 2361607.5 | K13: =SUM(#REF!)*2 -> #REF! | M13: =#REF!-K13 -> #REF! | N13: =(SUM(#REF!)*2)-#REF! -> #REF! | O13: 1000
A14: 11 | B14: MPE ENGENHARIA E SERVICOS S/A (serviços comuns de engenharia, incluindo manutenção, conservação, adaptação, reparação e instalação de infraestruturas prediais e imobiliárias) - (exceto DAC) | C14: Contratos DCA | D14: 2 | E14: VGM01N01H3N | F14: 04743858000105 | G14: 1201/2023 | J14: 1592033 | K14: =SUM(#REF!)*2 -> #REF! | M14: -419070 | N14: =(SUM(#REF!)*2)-#REF! -> #REF! | O14: 1000
A15: 12 | B15: POLI ENGENHARIA LTDA (serviços comuns de engenharia, incluindo manutenção, conservação, adaptação, reparação e instalação de infraestruturas prediais e imobiliárias) - contrato 20 meses | C15: Contratos DCA | D15: 2 | E15: VGM01N01H3N | F15: 00700518000138 | G15: 1226/2022 | J15: 2393.36 | K15: =SUM(#REF!)*2 -> #REF! | L15: =#REF!-K15 -> #REF! | O15: 1000
A16: 13 | B16: ARTECOR GRÁFICO E EDITORA LTDA | C16: Contratos DCA | D16: 2 | E16: VGM01N01Q1N | F16: 38.013.991/0001-10 | G16: 105/2023 | J16: 30000 | K16: =SUM(#REF!)*2 -> #REF! | O16: 1000
A17: 14 | B17: Contrato de Limpeza - UnB Cerrado (AP PISCINAS EIRELI) | C17: UnB Cerrado | D17: 1 | E17: VGM01N01A7N (VGM01N1F2N-PI indevido) | F17: 08475822000130 | G17: 112/2020 | J17: 6140.73 | K17: =SUM(#REF!)*2 -> #REF! | M17: -643.35 | N17: =(SUM(#REF!)*2)-#REF! -> #REF! | O17: 1000
A18: 15 | B18: - Segurança - ULTRASEG Segurança Patrimonial Ltda | C18: UnB Cerrado | D18: 1 | E18: VGM01N01A8N | F18: 09151154000159 | G18: 1207/2022 | J18: 23452.22 | K18: =SUM(#REF!)*2 -> #REF! | M18: -46904.36 | N18: =(SUM(#REF!)*2)-#REF! -> #REF! | O18: 1000
A19: 16 | B19: Restaurante ISM EIRELI (diretoria RU) - Ação 20RK planilha DRU | C19: Contrato DAC/RU | D19: 1 | E19: VGM01N01B5N | F19: 04228626001263 | G19: 31/2021 | J19: 1104719.8 | K19: =#REF!+#REF! -> #REF! | N19: =(SUM(#REF!)*2)-#REF! -> #REF! | O19: 1000
A20: 17 | B20: PGFN: 1° ATI, negociação conta n°: 7300348 ( Consulta Acordo n°1 - Conta da Negociação 7300348 (SEI nº 10575553) SEI origem: 23106.094258/2021-19 SEI pagamento em 2023: 23106.005996/2023-61 Despacho que contém explicação: 10567234 do SEI 23106.132563/2023-88 Acordo de Transação Individual (ATI), referente à dívida ativa tributária junto à PGFN -débitos previdenciários Empenho atual: 2024NE000285 | C20: Contratos Diversos | D20: 2 | E20: VGH01N0112N | J20: 61992.46 | N20: =(SUM(#REF!)*2)-#REF! -> #REF! | O20: 1000
A21: 18 | B21: PGFN: 2° ATI, negociação conta n°: 8815031 (Consulta Acordo n°2 - Conta da Negociação 8815031 (SEI nº 10576277)) SEI origem: 23106.059565/2023-15 SEI pagamento 2023:23106.123083/2023-26 que foi realizado o pagamento da entrada e no 23106.128684/2023-25 constará os demais pagamentos. Despacho que contém explicação: 10567234 do SEI 23106.132563/2023-88 Guias de Recolhimento de FGTS e Informações à Previdência Social (GFIP) das competências de janeiro/2011, fevereiro/2011, abril/2011, junho/2011 e novembro/2011 Empenho atual: 2023NE003705; 2024NE000487 | C21: Contratos Diversos | D21: 2 | E21: VGH01N0112N | J21: 24066.75 | N21: =(SUM(#REF!)*2)-#REF! -> #REF! | O21: 1000
A22: 19 | B22: RFB: Conta da Negociação 0211000120 (Consulta Parcelamento n°1 - Conta da Negociação 0211000120 (SEI nº 10580261)) SEI origem: 23106.059634/2023-91 SEI pagamento em 2023: 23106.087581/2023-06 Despacho que contém explicação: 10567234 do SEI 23106.132563/2023-88 Atraso das Guias de Recolhimento de FGTS e Informações à Previdência Social (GFIP) das competências de julho/2010, outubro/2010, novembro/2010, dezembro/2011 e 13°/2011 Empenho atual: 2023NE003850 e 2024NE000284 | C22: Contratos Diversos | D22: 2 | E22: VGH01N0112N | J22: 7372.51 | N22: =(SUM(#REF!)*2)-#REF! -> #REF! | O22: 1000
A23: 20 | B23: Tratador de Piscinas CO e casa Oscar Niemayer - (AP Piscinas EIRELI) | C23: Contratos Diversos | D23: 1 | E23: VGM01N01E2N | F23: 08475822000130 | G23: 93/2020 | J23: 5039.3475 | K23: =#REF!*2 -> #REF! | N23: =(SUM(#REF!)*2)-#REF! -> #REF! | O23: 1000
A24: 21 | B24: Correios - EC | C24: Comunicação | D24: 2 | E24: VGM01N01J1N | F24: 34028316000707 | G24: 1204/2024 | J24: 609.75 | K24: =#REF!*2 -> #REF! | M24: -642 | N24: =(SUM(#REF!)*2)-#REF! -> #REF! | O24: 1000
A25: 22 | B25: Empresa Brasil de Comunicação (EBC) | C25: Comunicação | D25: 2 | E25: VGM01N01I9N | G25: 213/2020 | J25: 531.84 | K25: =#REF!*2 -> #REF! | L25: =#REF!-K25 -> #REF! | N25: =(SUM(#REF!)*2)-#REF! -> #REF! | O25: 1000
A26: Total da despesa | H26: =SUM(H4:H18) -> 0 | I26: =SUM(I4:I18) -> 0 | J26: =SUM(J4:J25) -> 8555847 | K26: =SUM(K4:K18) -> #REF! | L26: =SUM(L4:L18) -> #REF! | M26: =SUM(M4:M18) -> #REF! | N26: =SUM(N4:N18) -> #REF!
A28: Descrição das despesas | C28: UGR | D28: Prioridade | E28: PI 2025 | F28: CNPJ | G28: nº Contrato | H28: 45658 | I28: 45689 | J28: Total necessário | O28: Fonte
A29: 1 | B29: '- GESTOR SERVICOS EMPRESARIAIS (Portaria - SPI) | C29: Contratos SPI | D29: 1 | E29: VGM01N01E8N | F29: 02685728000120 | G29: 001/2022 | J29: 746313.59 | K29: =SUM(#REF!)*2 -> #REF! | L29: =#REF!-K29 -> #REF! | N29: =(SUM(#REF!)*2)-#REF! -> #REF! | O29: 1050
A30: 2 | B30: - SEFIX (Limpeza e Conservação - SPI) | C30: Contratos SPI | D30: 1 | E30: VGM01N01E9N | F30: 13258899000199 | G30: 033/2022 | J30: 193823.77 | K30: =SUM(#REF!)*2 -> #REF! | L30: =#REF!-K30 -> #REF! | N30: =(SUM(#REF!)*2)-#REF! -> #REF! | O30: 1050
A31: 3 | B31: Engemega - (Manutenção de Imóveis gerenciados pela Secretaria de Patrimônio Imobiliário (SPI)) – contrato 1 (contrato antigo) | C31: Contratos SPI | D31: 2 | E31: VGM01N01D4N | F31: 33480104/0001-08 | G31: 1223/2022 | J31: 542145.49 | K31: =#REF!*2 -> #REF! | L31: =#REF!-K31 -> #REF! | N31: =(SUM(#REF!)*2)-#REF! -> #REF! | O31: 1050
A32: 4 | B32: - ENERGIA ELÉTRICA - SPI | C32: Contratos SPI | D32: 3 | E32: VGM01N01I2N | F32: 07522669000192 | J32: 36780.26 | K32: =#REF!*2 -> #REF! | L32: =#REF!-K32 -> #REF! | N32: =(SUM(#REF!)*2)-#REF! -> #REF! | O32: 1050
A33: 5 | B33: - CAESB - SPI | C33: Contratos SPI | D33: 3 | E33: VGM01N01I3N | F33: 00082024000137 | J33: 271444.86 | K33: =#REF!*2 -> #REF! | L33: =#REF!-K33 -> #REF! | O33: 1050
A34: 6 | B34: - Despesas de Condomínio | C34: Contratos SPI | D34: 1 | E34: VGM01N01K6N | J34: 265208.24 | K34: =#REF!*2 -> #REF! | L34: =#REF!-K34 -> #REF! | N34: =(SUM(#REF!)*2)-#REF! -> #REF! | O34: 1050
A35: Total da despesa | H35: =SUM(H29:H34) -> 0 | I35: =SUM(I29:I34) -> 0 | J35: =SUM(J29:J34) -> 2055716.2 | K35: =SUM(K29:K34) -> #REF! | L35: =SUM(L29:L34) -> #REF! | M35: =SUM(M29:M34) -> 0 | N35: =SUM(N29:N34) -> #REF!

Sheet Ressarc DAC 25
A1: Ressarcimento ao DAC
A2: N° do processo | B2: Valor a ser ressarcido ao DAC
A3: 23106.139541/2023-49 | B3: 530
A4: 23106.032530/2023-39 | B4: 407.2
A5: 23106.035517/2023-31 | B5: 400
A6: 23106.034998/2023-68 | B6: 880.6
A7: 23106.035525/2023-88 | B7: 800
A8: 23106.142681/2023-02 | B8: 1430
A9: 23106.139136/2023-21 | B9: 2000
A10: 23106.035396/2024-17 | B10: 1060
A11: 23106.035907/2024-92 | B11: 300
A12: 23106.034997/2023-13 | B12: 1027.13
A13: 23106.016343/2023-16 | B13: 237.17
A14: 23106.045918/2024-81 | B14: 1060
... A18: 23106.098557/2024-75 | B18: 700
A20: Total | B20: =SUM(B3:B19) -> 13567.82
A22: N° do processo | B22: Valor a ser ressarcido ao DAC
A23: 23106.098561/2024-33 | B23: 700
A24: 23106.099121/2024-01 | B24: 700
A25: Total | B25: =SUM(B23:B24) -> 1400
A27: N° do processo | B27: Valor a ser ressarcido ao DAC
A28: 23106.107639/2024-18 | B28: 800
A29: 23106.098552/2024-42 | B29: 800
A30: 23106.116295/2024-38 | B30: 3000 | C30: GUSTAVO
A33: Ressarcimento ao DAC - 2025
A34: 23106.005058/2023-61 | B34: 2400
A35: 23106.122417/2024-25 | B35: 700
A36: 23106.122396/2024-48 | B36: 700
A37: 23106.096794/2025-82 | B37: 2100
A38: 23106.104288/2025-74 | B38: 400
A39: 23106.101649/2025-21 | B39: 400
A54: Total | B54: =SUM(B3:B53) -> 41235.64

Sheet Prog-25.02
A1: Acompanhamento de Contratos*
A2: Data de Atualização: 05/02/2025
A3: Descrição das despesas | B3: UGR | C3: Prioridade | D3: PI 2025 | E3: CNPJ | F3: Processo | G3: Vigência | H3: Status do Contrato | I3: Situação da prorrogação | J3: nº Contrato | K3: Valor Contrato Média mensal | L3: Valor Cont Continuado Mensal | M3: Total estimado Anual | N3: Saldo Empenhos 2025 | O3: Saldo de Empenhos RAP | P3: Total RAP + Empenho | Q3: 45658 | R3: 45689 | S3: 45717 | T3: Total necessário
A4: - Pasep (há saldo no emepnho 2022NE000109 no PI VGH01N0101N) | B4: DGP/ folha | C4: 1 | D4: VGM01N01N1N | K4: 810000 | M4: =K4*12 -> 9720000 | N4: 0 | O4: 0 | P4: =SUM(N4:O4) -> 0 | R4: =K4 -> 810000 | S4: =K4 -> 810000 | T4: =SUM(Q4:S4) -> 1620000
A5: Energia Elétrica UnB Cerrado - CONTRATO CCER - ENEL N. 36/2020 e CELG DISTRIBUIÇÃO S.A - CELG D, Equatorial Goiás Distribuidora de Energia S/A | B5: UnB Cerrado | C5: 3 | D5: VGM01N01I2N | E5: 1543032000104 | F5: 23106.044802/2020-09 23106.083937/2023-24 | J5: 36/2020 | K5: 1585.03 | M5: =K5*12 -> 19020.36 | N5: 83.5 | O5: 428.86 | P5: =SUM(N5:O5) -> 512.36 | R5: =K5-P5 -> 1072.67 | S5: =K5 -> 1585.03 | T5: =SUM(Q5:S5) -> 2657.7 | V5: =SUM(K5:L5)*2 -> 3170.06 | W5: =P5-V5 -> -2657.7 | Y5: =(SUM(K5:L5)*2)-P5 -> 2657.7
A6: OI SA recuperação judicial | B6: STI | C6: 3 | D6: VGM01N01I4N | E6: 76535764000143 | F6: 23106.012727/2018-94 | G6: 45882 | H6: =IF((G6-TODAY())<0,"EXPIRADO", IF((G6-TODAY())<=60,"EM BREVE","NO PRAZO")) -> EXPIRADO | J6: 515/2021 | K6: 60000 | M6: =K6*12 -> 720000 | O6: 58853.98 | P6: =SUM(O6:O6) -> 58853.98 | R6: =K6-P6 -> 1146.02 | S6: =K6 -> 60000 | T6: =SUM(Q6:S6) -> 61146.02 | V6: =SUM(K6:L6)*2 -> 120000 | W6: =P6-V6 -> -61146.02 | X6: =-#REF!-#REF! -> #REF! | Y6: =(SUM(K6:L6)*2)-P6 -> 61146.02
A7: - Central IT - Suporte TI (Serviços de Manutenção dos Computadores da UnB) | B7: STI | C7: 2 | D7: VGM01N01A3N | E7: 07171299000196 | F7: 23106.007549/2018-80 | G7: 45836 | H7: =IF((G7-TODAY())<0,"EXPIRADO", IF((G7-TODAY())<=60,"EM BREVE","NO PRAZO")) -> EXPIRADO | J7: 507/2019 | L7: =M7/12 -> 369702.92 | M7: =4436435.04 -> 4436435 | N7: 0 | O7: 364226.06 | P7: =SUM(N7:O7) -> 364226.06 | R7: =L7-P7 -> 5476.86 | S7: =L7 -> 369702.92 | T7: =SUM(Q7:S7) -> 375179.78 | V7: =SUM(K7:L7)*2 -> 739405.84 | W7: =P7-V7 -> -375179.78 | Y7: =(SUM(K7:L7)*2)-P7 -> 375179.78
A8: - Seguro de aluno/ estagiário (MBM Seguradora S.A) | B8: Contratos DCO | C8: 1 | D8: VGM01N01N7N | E8: 87883807000106 | F8: 23106.085902/2019-43 | G8: 45721 | H8: =IF((G8-TODAY())<0,"EXPIRADO", IF((G8-TODAY())<=60,"EM BREVE","NO PRAZO")) -> EXPIRADO | I8: será prorrogado excepcionalmente | J8: 024/2020 | K8: 3870 | M8: 48000 | N8: 0 | O8: 85.6 | P8: =SUM(N8:O8) -> 85.6 | R8: =K8-P8 -> 3784.4 | S8: =K8 -> 3870 | T8: =SUM(Q8:S8) -> 7654.4 | V8: =SUM(K8:L8)*2 -> 7740
A9: CRUZEIRO CONTROLE DE PRAGAS E DESENTUPIMENTO | B9: Contratos PRC | C9: 2 | D9: VGM01N01D3N | E9: 22.575.793/0001-00 | F9: 23106.058637/2021-45 | G9: 45980 | H9: =IF((G9-TODAY())<0,"EXPIRADO", IF((G9-TODAY())<=60,"EM BREVE","NO PRAZO")) -> EM BREVE | J9: 1222/2024 | K9: =M9/12 -> 65625.02 | M9: 787500.24 | N9: 0 | O9: 65625.02 | P9: =SUM(N9:O9) -> 65625.02 | S9: =K9 -> 65625.02 | T9: =SUM(Q9:S9) -> 65625.02 | Y9: =(SUM(K9:L9)*2)-P9 -> 65625.02
A10: VILELA SERVIÇO DE PAISAGISMO, PARQUES E JARDINS LTDA (jardinagem) | B10: Contratos PRC | C10: 2 | D10: VGM01N01A5N | E10: 32.751.565/0001-05 | F10: 23106.028705/2019-27 | G10: 45866 | H10: =IF((G10-TODAY())<0,"EXPIRADO", IF((G10-TODAY())<=60,"EM BREVE","NO PRAZO")) -> EXPIRADO | J10: 1217/2023 | K10: 298000 | M10: 3119907.7 | N10: 0 | O10: 58661.65 | P10: =SUM(N10:O10) -> 58661.65 | R10: =K10-O10 -> 239338.35 | S10: =K10 -> 298000 | T10: =SUM(Q10:S10) -> 537338.35 | V10: =SUM(K10:L10)*2 -> 596000 | W10: =P10-V10 -> -537338.35 | Y10: =(SUM(K10:L10)*2)-P10 -> 537338.35
A11: - TRANSMONICI TRANSPORTE E TURISMO (ônibus rodoviário executivo) | B11: Contratos PRC | C11: 2 | D11: VGM01N01K1N | E11: 09169349000126 | F11: 23106.000890/2021-18 | G11: 45697 | H11: =IF((G11-TODAY())<0,"EXPIRADO", IF((G11-TODAY())<=60,"EM BREVE","NO PRAZO")) -> EXPIRADO | I11: Em fase de prorrogação 12129647 | J11: 604/2022 | K11: 105000 | M11: =K11*12 -> 1260000 | N11: 196800 | O11: 0 | P11: =SUM(N11:O11) -> 196800 | S11: =105000-91800 -> 13200 | T11: =SUM(Q11:S11) -> 13200 | V11: =SUM(K11:L11)*2 -> 210000 | Y11: =(SUM(K11:L11)*2)-P11 -> 13200
A12: ARTES GRÁFICA COMÉRCIO E REPRESENTAÇÕES EIRELI (serviços continuados de Designer Gráfico) - foi solicitada prorrogação por 20 meses | B12: Contratos DCA | C12: 2 | D12: VGM01N01P4N | E12: 05606994000108 | F12: 23106.148085/2022-47 | G12: 46127 | H12: =IF((G12-TODAY())<0,"EXPIRADO", IF((G12-TODAY())<=60,"EM BREVE","NO PRAZO")) -> NO PRAZO | J12: 147/2022 | L12: 13366.39 | M12: =L12*12 -> 160396.68 | N12: 0 | O12: 587.48 | P12: =SUM(N12:O12) -> 587.48 | R12: =L12-P12 -> 12778.91 | S12: =L12 -> 13366.39 | T12: =SUM(Q12:S12) -> 26145.3 | V12: =SUM(K12:L12)*2 -> 26732.78 | W12: =P12-V12 -> -26145.3 | Y12: =(SUM(K12:L12)*2)-P12 -> 26145.3
A13: ELYON BRASIL - ESPLANADA SERVICOS TERCEIRIZADOS EIRELI - serviços continuados de pessoal - coletores de resíduos de serviços de saúde | B13: Contratos DCA | C13: 1 | D13: VGM01N01E4N | E13: 01099686000182 | F13: 23106.031888/2020-00 | G13: 45854 | H13: =IF((G13-TODAY())<0,"EXPIRADO", IF((G13-TODAY())<=60,"EM BREVE","NO PRAZO")) -> EXPIRADO | J13: 111/2020 | L13: =M13/12 -> 22669.34 | M13: 272032.08 | N13: 21063.29 | O13: 1351.12 | P13: =SUM(N13:O13) -> 22414.41 | R13: =L13-P13 -> 254.93 | S13: =L13 -> 22669.34 | T13: =SUM(Q13:S13) -> 22924.27 | V13: =SUM(K13:L13)*2 -> 45338.68 | W13: =P13-V13 -> -22924.27 | Y13: =(SUM(K13:L13)*2)-P13 -> 22924.27
A14: - ALFA E OMEGA Apoio Técnico EDU | B14: Contratos DCA | C14: 1 | D14: VGM01N01D5N | E14: 16650774000106 | F14: 23106.011967/2019-52 | G14: 45766 | H14: =IF((G14-TODAY())<0,"EXPIRADO", IF((G14-TODAY())<=60,"EM BREVE","NO PRAZO")) -> EXPIRADO | J14: 022/2021 | L14: =M14/12 -> 23238.88 | M14: 278866.56 | N14: 0 | O14: 2308.96 | P14: =SUM(N14:O14) -> 2308.96 | R14: =L14-P14 -> 20929.92 | S14: =L14 -> 23238.88 | T14: =SUM(Q14:S14) -> 44168.8 | V14: =SUM(K14:L14)*2 -> 46477.76 | W14: =P14-V14 -> -44168.8 | Y14: =(SUM(K14:L14)*2)-P14 -> 44168.8
